Workbook

Sheet PEDIDOS
A1: OP | B1: Fecha | C1: N° OC | D1: CLIENTE | E1: PRODUCTO | F1: S | G1: Q | H1: Ml | I1: ESTADO | M1: N° LOTE
A2: 25293 | B2: 46035 | C2: 163 | D2: THE MINIMAL CO | E2: MILKY TONER | F2: P | G2: 900 | H2: 100 | I2: =IF(OR(L2="entregado",K2="despacho",J2="en proceso"),"","ingreso") | J2: =IF(OR(L2="entregado",K2="despacho"),"", IF(AND(ELABORACION!F2<>"-",ELABORACION!F2<>"PENDIENTE ELAB"),"en proceso","")) | K2: =IF(L2="entregado","",IF(EXPEDICION!L2="listo para entregar","despacho","")) | L2: =IF(EXPEDICION!L2="entregado", "entregado", "") -> entregado | M2: =EXPEDICION!M2 -> F26021
A3: 25294 | B3: 46035 | C3: 14297 | D3: JACTANS | E3: JS-941 AGUA MICELAR BIFASCIA | F3: P | G3: 1000 | H3: 105 | I3: =IF(OR(L3="entregado",K3="despacho",J3="en proceso"),"","ingreso") | J3: =IF(OR(L3="entregado",K3="despacho"),"", IF(AND(ELABORACION!F3<>"-",ELABORACION!F3<>"PENDIENTE ELAB"),"en proceso","")) | K3: =IF(L3="entregado","",IF(EXPEDICION!L3="listo para entregar","despacho","")) | L3: =IF(EXPEDICION!L3="entregado", "entregado", "") -> entregado | M3: =EXPEDICION!M3 -> F26031
A4: 25295 | B4: 46035 | C4: 15074 | D4: THELMA Y LOUISE | E4: AGUA TERMAL | F4: P | G4: 2940 | H4: 100 | I4: =IF(OR(L4="entregado",K4="despacho",J4="en proceso"),"","ingreso") | J4: =IF(OR(L4="entregado",K4="despacho"),"", IF(AND(ELABORACION!F4<>"-",ELABORACION!F4<>"PENDIENTE ELAB"),"en proceso","")) | K4: =IF(L4="entregado","",IF(EXPEDICION!L4="listo para entregar","despacho","")) | L4: =IF(EXPEDICION!L4="entregado", "entregado", "") -> entregado | M4: =EXPEDICION!M4 -> F26041
A5: 25296 | B5: 46035 | D5: LIORA | E5: CREMA PARA PEINAR RULOS | F5: P | G5: 170 | H5: 300 | I5: =IF(OR(L5="entregado",K5="despacho",J5="en proceso"),"","ingreso") | J5: =IF(OR(L5="entregado",K5="despacho"),"", IF(AND(ELABORACION!F5<>"-",ELABORACION!F5<>"PENDIENTE ELAB"),"en proceso","")) | K5: =IF(L5="entregado","",IF(EXPEDICION!L5="listo para entregar","despacho","")) | L5: =IF(EXPEDICION!L5="entregado", "entregado", "") -> entregado | M5: =EXPEDICION!M5 -> Y26039
A6: 25298 | B6: 46042 | C6: P01203 | D6: BIOESENCIA | E6: SERUM ORIGENES | F6: P | G6: 1600 | H6: 30 | I6: =IF(OR(L6="entregado",K6="despacho",J6="en proceso"),"","ingreso") | J6: =IF(OR(L6="entregado",K6="despacho"),"", IF(AND(ELABORACION!F6<>"-",ELABORACION!F6<>"PENDIENTE ELAB"),"en proceso","")) | K6: =IF(L6="entregado","",IF(EXPEDICION!L6="listo para entregar","despacho","")) | L6: =IF(EXPEDICION!L6="entregado", "entregado", "") -> entregado | M6: =EXPEDICION!M6 -> 240201
A7: 25299 | B7: 46042 | D7: WSABI | E7: SERUM INTIMO | F7: P | G7: 300 | H7: 30 | I7: =IF(OR(L7="entregado",K7="despacho",J7="en proceso"),"","ingreso") | J7: =IF(OR(L7="entregado",K7="despacho"),"", IF(AND(ELABORACION!F7<>"-",ELABORACION!F7<>"PENDIENTE ELAB"),"en proceso","")) | K7: =IF(L7="entregado","",IF(EXPEDICION!L7="listo para entregar","despacho","")) | L7: =IF(EXPEDICION!L7="entregado", "entregado", "") -> entregado | M7: =EXPEDICION!M7 -> F26049
A8: 25300 | B8: 46042 | D8: MERMER | E8: ACEITE CORPORAL LAVANDA | F8: P | G8: 300 | H8: 200 | I8: =IF(OR(L8="entregado",K8="despacho",J8="en proceso"),"","ingreso") | J8: =IF(OR(L8="entregado",K8="despacho"),"", IF(AND(ELABORACION!F8<>"-",ELABORACION!F8<>"PENDIENTE ELAB"),"en proceso","")) | K8: =IF(L8="entregado","",IF(EXPEDICION!L8="listo para entregar","despacho","")) | L8: =IF(EXPEDICION!L8="entregado", "entregado", "") -> entregado | M8: =EXPEDICION!M8 -> E26087
A9: 25300 | B9: 46042 | D9: MERMER | E9: ACEITE CORPORAL ALMENDRA | F9: P | G9: 300 | H9: 200 | I9: =IF(OR(L9="entregado",K9="despacho",J9="en proceso"),"","ingreso") | J9: =IF(OR(L9="entregado",K9="despacho"),"", IF(AND(ELABORACION!F9<>"-",ELABORACION!F9<>"PENDIENTE ELAB"),"en proceso","")) | K9: =IF(L9="entregado","",IF(EXPEDICION!L9="listo para entregar","despacho","")) | L9: =IF(EXPEDICION!L9="entregado", "entregado", "") -> entregado | M9: =EXPEDICION!M9 -> E26088
A10: 25300 | B10: 46042 | D10: MERMER | E10: ACEITE CORPORAL ROSAS | F10: P | G10: 300 | H10: 200 | I10: =IF(OR(L10="entregado",K10="despacho",J10="en proceso"),"","ingreso") | J10: =IF(OR(L10="entregado",K10="despacho"),"", IF(AND(ELABORACION!F10<>"-",ELABORACION!F10<>"PENDIENTE ELAB"),"en proceso","")) | K10: =IF(L10="entregado","",IF(EXPEDICION!L10="listo para entregar","despacho","")) | L10: =IF(EXPEDICION!L10="entregado", "entregado", "") -> entregado | M10: =EXPEDICION!M10 -> E26089
A11: 25300 | B11: 46042 | D11: MERMER | E11: ACEITE CORPORAL SESAMO | F11: P | G11: 300 | H11: 200 | I11: =IF(OR(L11="entregado",K11="despacho",J11="en proceso"),"","ingreso") | J11: =IF(OR(L11="entregado",K11="despacho"),"", IF(AND(ELABORACION!F11<>"-",ELABORACION!F11<>"PENDIENTE ELAB"),"en proceso","")) | K11: =IF(L11="entregado","",IF(EXPEDICION!L11="listo para entregar","despacho","")) | L11: =IF(EXPEDICION!L11="entregado", "entregado", "") -> entregado | M11: =EXPEDICION!M11 -> E26090
A12: 25300 | B12: 46042 | D12: MERMER | E12: ACEITE CORPORAL INCIENSO | F12: P | G12: 300 | H12: 200 | I12: =IF(OR(L12="entregado",K12="despacho",J12="en proceso"),"","ingreso") | J12: =IF(OR(L12="entregado",K12="despacho"),"", IF(AND(ELABORACION!F12<>"-",ELABORACION!F12<>"PENDIENTE ELAB"),"en proceso","")) | K12: =IF(L12="entregado","",IF(EXPEDICION!L12="listo para entregar","despacho","")) | L12: =IF(EXPEDICION!L12="entregado", "entregado", "") -> entregado | M12: =EXPEDICION!M12 -> E26091
A13: 25300 | B13: 46042 | D13: MERMER | E13: ACEITE CORPORAL ARNICA | F13: P | G13: 300 | H13: 200 | I13: =IF(OR(L13="entregado",K13="despacho",J13="en proceso"),"","ingreso") | J13: =IF(OR(L13="entregado",K13="despacho"),"", IF(AND(ELABORACION!F13<>"-",ELABORACION!F13<>"PENDIENTE ELAB"),"en proceso","")) | K13: =IF(L13="entregado","",IF(EXPEDICION!L13="listo para entregar","despacho","")) | L13: =IF(EXPEDICION!L13="entregado", "entregado", "") -> entregado | M13: =EXPEDICION!M13 -> E26092
A14: 25300 | B14: 46042 | D14: MERMER | E14: LOCION CAPILAR | F14: P | G14: 400 | H14: 100 | I14: =IF(OR(L14="entregado",K14="despacho",J14="en proceso"),"","ingreso") | J14: =IF(OR(L14="entregado",K14="despacho"),"", IF(AND(ELABORACION!F14<>"-",ELABORACION!F14<>"PENDIENTE ELAB"),"en proceso","")) | K14: =IF(L14="entregado","",IF(EXPEDICION!L14="listo para entregar","despacho","")) | L14: =IF(EXPEDICION!L14="entregado", "entregado", "") -> entregado | M14: =EXPEDICION!M14 -> M26042
A15: 25300 | B15: 46042 | D15: MERMER | E15: SERUM CAPILAR | F15: P | G15: 400 | H15: 100 | I15: =IF(OR(L15="entregado",K15="despacho",J15="en proceso"),"","ingreso") | J15: =IF(OR(L15="entregado",K15="despacho"),"", IF(AND(ELABORACION!F15<>"-",ELABORACION!F15<>"PENDIENTE ELAB"),"en proceso","")) | K15: =IF(L15="entregado","",IF(EXPEDICION!L15="listo para entregar","despacho","")) | L15: =IF(EXPEDICION!L15="entregado", "entregado", "") -> entregado | M15: =EXPEDICION!M15 -> M26030
A16: 25301 | B16: 46049 | C16: 1708 | D16: LABORATORIO ONCE | E16: SERUM ACIDO HIALURONICO + NIACINAMIDA | F16: P | G16: 1653 | H16: 30 | I16: =IF(OR(L16="entregado",K16="despacho",J16="en proceso"),"","ingreso") | J16: =IF(OR(L16="entregado",K16="despacho"),"", IF(AND(ELABORACION!F16<>"-",ELABORACION!F16<>"PENDIENTE ELAB"),"en proceso","")) | K16: =IF(L16="entregado","",IF(EXPEDICION!L16="listo para entregar","despacho","")) | L16: =IF(EXPEDICION!L16="entregado", "entregado", "") -> entregado | M16: =EXPEDICION!M16 -> F26048
A17: 25302 | B17: 46050 | C17: 15098 | D17: THELMA Y LOUISE | E17: CREMA BIFASICA CHERRY | F17: M | G17: 1640 | H17: 160 | I17: =IF(OR(L17="entregado",K17="despacho",J17="en proceso"),"","ingreso") | J17: =IF(OR(L17="entregado",K17="despacho"),"", IF(AND(ELABORACION!F17<>"-",ELABORACION!F17<>"PENDIENTE ELAB"),"en proceso","")) | K17: =IF(L17="entregado","",IF(EXPEDICION!L17="listo para entregar","despacho","")) | L17: =IF(EXPEDICION!L17="entregado", "entregado", "") -> entregado | M17: =EXPEDICION!M17
A18: 25303 | B18: 46052 | D18: ALL BEAUTY | E18: SERUM ACIDO HIALURONICO | F18: P | G18: 1000 | H18: 30 | I18: =IF(OR(L18="entregado",K18="despacho",J18="en proceso"),"","ingreso") | J18: =IF(OR(L18="entregado",K18="despacho"),"", IF(AND(ELABORACION!F18<>"-",ELABORACION!F18<>"PENDIENTE ELAB"),"en proceso","")) | K18: =IF(L18="entregado","",IF(EXPEDICION!L18="listo para entregar","despacho","")) | L18: =IF(EXPEDICION!L18="entregado", "entregado", "") -> entregado | M18: =EXPEDICION!M18 -> E26083
A19: 25304 | B19: 46044 | D19: DWUAM | E19: BASE DE MAQUILLAJE TONO 1 | F19: P | G19: 500 | H19: 35 | I19: =IF(OR(L19="entregado",K19="despacho",J19="en proceso"),"","ingreso") | J19: =IF(OR(L19="entregado",K19="despacho"),"", IF(AND(ELABORACION!F19<>"-",ELABORACION!F19<>"PENDIENTE ELAB"),"en proceso","")) | K19: =IF(L19="entregado","",IF(EXPEDICION!L19="listo para entregar","despacho","")) | L19: =IF(EXPEDICION!L19="entregado", "entregado", "") -> entregado | M19: =EXPEDICION!M19 -> E26104
A20: 26001 | B20: 46071 | C20: 6433 | D20: HEBURN | E20: BRUMA FIJADORA de MAQUILLAJE x 125 cc | F20: P | G20: 600 | H20: 125 | I20: =IF(OR(L20="entregado",K20="despacho",J20="en proceso"),"","ingreso") | J20: =IF(OR(L20="entregado",K20="despacho"),"", IF(AND(ELABORACION!F20<>"-",ELABORACION!F20<>"PENDIENTE ELAB"),"en proceso","")) | K20: =IF(L20="entregado","",IF(EXPEDICION!L20="listo para entregar","despacho","")) | L20: =IF(EXPEDICION!L20="entregado", "entregado", "") -> entregado | M20: =EXPEDICION!M20 -> M26003
A21: 26002 | B21: 46052 | D21: ALL BEAUTY | E21: CREMA FACIAL HIDRATANTE X 50gr (DIA) | F21: P | G21: 1000 | H21: 50 | I21: =IF(OR(L21="entregado",K21="despacho",J21="en proceso"),"","ingreso") | J21: =IF(OR(L21="entregado",K21="despacho"),"", IF(AND(ELABORACION!F21<>"-",ELABORACION!F21<>"PENDIENTE ELAB"),"en proceso","")) | K21: =IF(L21="entregado","",IF(EXPEDICION!L21="listo para entregar","despacho","")) | L21: =IF(EXPEDICION!L21="entregado", "entregado", "") -> entregado | M21: =EXPEDICION!M21 -> F26040
A22: 26002 | B22: 46052 | D22: ALL BEAUTY | E22: UNGÜENTO POMADA OLEO 30 + 1 X 10gr | F22: P | G22: 1000 | H22: 10 | I22: =IF(OR(L22="entregado",K22="despacho",J22="en proceso"),"","ingreso") | J22: =IF(OR(L22="entregado",K22="despacho"),"", IF(AND(ELABORACION!F22<>"-",ELABORACION!F22<>"PENDIENTE ELAB"),"en proceso","")) | K22: =IF(L22="entregado","",IF(EXPEDICION!L22="listo para entregar","despacho","")) | L22: =IF(EXPEDICION!L22="entregado", "entregado", "") -> entregado | M22: =EXPEDICION!M22 -> F26045
A23: 26002 | B23: 46052 | D23: ALL BEAUTY | E23: CREMA DE ORDEÑE X 300gr | F23: M | G23: 1500 | H23: 300 | I23: =IF(OR(L23="entregado",K23="despacho",J23="en proceso"),"","ingreso") | J23: =IF(OR(L23="entregado",K23="despacho"),"", IF(AND(ELABORACION!F23<>"-",ELABORACION!F23<>"PENDIENTE ELAB"),"en proceso","")) | K23: =IF(L23="entregado","",IF(EXPEDICION!L23="listo para entregar","despacho","")) | L23: =IF(EXPEDICION!L23="entregado", "entregado", "") -> entregado | M23: =EXPEDICION!M23 -> F26039
A24: 26003 | B24: 46043 | C24: 103 | D24: UNICA | E24: CREMA ENEBRO | F24: M | G24: 500 | H24: 90 | I24: =IF(OR(L24="entregado",K24="despacho",J24="en proceso"),"","ingreso") | J24: =IF(OR(L24="entregado",K24="despacho"),"", IF(AND(ELABORACION!F24<>"-",ELABORACION!F24<>"PENDIENTE ELAB"),"en proceso","")) | K24: =IF(L24="entregado","",IF(EXPEDICION!L24="listo para entregar","despacho","")) | L24: =IF(EXPEDICION!L24="entregado", "entregado", "") -> entregado | M24: =EXPEDICION!M24 -> 200301
A25: 26004 | B25: 46066 | C25: 15114 | D25: THELMA Y LOUISE | E25: SERUM BIFASICO JOJOBA-POMELO | F25: M | G25: 3024 | H25: 30 | I25: =IF(OR(L25="entregado",K25="despacho",J25="en proceso"),"","ingreso") | J25: =IF(OR(L25="entregado",K25="despacho"),"", IF(AND(ELABORACION!F25<>"-",ELABORACION!F25<>"PENDIENTE ELAB"),"en proceso","")) | K25: =IF(L25="entregado","",IF(EXPEDICION!L25="listo para entregar","despacho","")) | L25: =IF(EXPEDICION!L25="entregado", "entregado", "") -> entregado | M25: =EXPEDICION!M25 -> M26024
A26: 26004 | B26: 46066 | C26: 15114 | D26: THELMA Y LOUISE | E26: SERUM BIFASICO PEPINO-HAMAMELIS | F26: M | G26: 3024 | H26: 30 | I26: =IF(OR(L26="entregado",K26="despacho",J26="en proceso"),"","ingreso") | J26: =IF(OR(L26="entregado",K26="despacho"),"", IF(AND(ELABORACION!F26<>"-",ELABORACION!F26<>"PENDIENTE ELAB"),"en proceso","")) | K26: =IF(L26="entregado","",IF(EXPEDICION!L26="listo para entregar","despacho","")) | L26: =IF(EXPEDICION!L26="entregado", "entregado", "") -> entregado | M26: =EXPEDICION!M26 -> M26083
A27: 26004 | B27: 46066 | C27: 15114 | D27: THELMA Y LOUISE | E27: SERUM BIFASICO LAVANDA-BLUEBERRY | F27: M | G27: 3024 | H27: 30 | I27: =IF(OR(L27="entregado",K27="despacho",J27="en proceso"),"","ingreso") | J27: =IF(OR(L27="entregado",K27="despacho"),"", IF(AND(ELABORACION!F27<>"-",ELABORACION!F27<>"PENDIENTE ELAB"),"en proceso","")) | K27: =IF(L27="entregado","",IF(EXPEDICION!L27="listo para entregar","despacho","")) | L27: =IF(EXPEDICION!L27="entregado", "entregado", "") -> entregado | M27: =EXPEDICION!M27 -> M26022
A28: 26004 | B28: 46066 | C28: 15114 | D28: THELMA Y LOUISE | E28: SERUM BIFASICO ROSA MOSQUETA-ROSAS | F28: M | G28: 3024 | H28: 30 | I28: =IF(OR(L28="entregado",K28="despacho",J28="en proceso"),"","ingreso") | J28: =IF(OR(L28="entregado",K28="despacho"),"", IF(AND(ELABORACION!F28<>"-",ELABORACION!F28<>"PENDIENTE ELAB"),"en proceso","")) | K28: =IF(L28="entregado","",IF(EXPEDICION!L28="listo para entregar","despacho","")) | L28: =IF(EXPEDICION!L28="entregado", "entregado", "") -> entregado | M28: =EXPEDICION!M28 -> M26084
A29: 26005 | B29: 46071 | C29: 772 | D29: CAV | E29: SHAMPOO BIO MOLECULAR X400ML VITAMIN SHOCK | F29: M | G29: 700 | H29: 400 | I29: =IF(OR(L29="entregado",K29="despacho",J29="en proceso"),"","ingreso") | J29: =IF(OR(L29="entregado",K29="despacho"),"", IF(AND(ELABORACION!F29<>"-",ELABORACION!F29<>"PENDIENTE ELAB"),"en proceso","")) | K29: =IF(L29="entregado","",IF(EXPEDICION!L29="listo para entregar","despacho","")) | L29: =IF(EXPEDICION!L29="entregado", "entregado", "") -> entregado | M29: =EXPEDICION!M29 -> E26064
A30: 26005 | B30: 46071 | C30: 772 | D30: CAV | E30: SERUM BIO MOLUECULAR X30ML VITAMIN SHOCK | F30: P | G30: 300 | H30: 30 | I30: =IF(OR(L30="entregado",K30="despacho",J30="en proceso"),"","ingreso") | J30: =IF(OR(L30="entregado",K30="despacho"),"", IF(AND(ELABORACION!F30<>"-",ELABORACION!F30<>"PENDIENTE ELAB"),"en proceso","")) | K30: =IF(L30="entregado","",IF(EXPEDICION!L30="listo para entregar","despacho","")) | L30: =IF(EXPEDICION!L30="entregado", "entregado", "") -> entregado | M30: =EXPEDICION!M30 -> M26009
A31: 26005 | B31: 46071 | C31: 772 | D31: CAV | E31: BALSAMO X400ML BIOMIC C/ ACIDO HIAL + CAPIMAX | F31: M | G31: 400 | H31: 400 | I31: =IF(OR(L31="entregado",K31="despacho",J31="en proceso"),"","ingreso") | J31: =IF(OR(L31="entregado",K31="despacho"),"", IF(AND(ELABORACION!F31<>"-",ELABORACION!F31<>"PENDIENTE ELAB"),"en proceso","")) -> en proceso | K31: =IF(L31="entregado","",IF(EXPEDICION!L31="listo para entregar","despacho","")) | L31: =IF(EXPEDICION!L31="entregado", "entregado", "") | M31: =EXPEDICION!M31
A32: 26005 | B32: 46071 | C32: 772 | D32: CAV | E32: MASCARA BIO MOLECULAR VITAMIN SHOCK X300ML | F32: M | G32: 700 | H32: 300 | I32: =IF(OR(L32="entregado",K32="despacho",J32="en proceso"),"","ingreso") | J32: =IF(OR(L32="entregado",K32="despacho"),"", IF(AND(ELABORACION!F32<>"-",ELABORACION!F32<>"PENDIENTE ELAB"),"en proceso","")) | K32: =IF(L32="entregado","",IF(EXPEDICION!L32="listo para entregar","despacho","")) | L32: =IF(EXPEDICION!L32="entregado", "entregado", "") -> entregado | M32: =EXPEDICION!M32 -> M26045
A33: 26006 | B33: 46071 | C33: 14329 | D33: JACTANS - DISNEY | E33: DSH-41823-Shampoo infantil fco pvc x45ml | F33: M | G33: 3000 | H33: 45 | I33: =IF(OR(L33="entregado",K33="despacho",J33="en proceso"),"","ingreso") | J33: =IF(OR(L33="entregado",K33="despacho"),"", IF(AND(ELABORACION!F33<>"-",ELABORACION!F33<>"PENDIENTE ELAB"),"en proceso","")) | K33: =IF(L33="entregado","",IF(EXPEDICION!L33="listo para entregar","despacho","")) | L33: =IF(EXPEDICION!L33="entregado", "entregado", "") -> entregado | M33: =EXPEDICION!M33 -> M26002
A34: 26006 | B34: 46071 | C34: 14329 | D34: JACTANS - DISNEY | E34: DES-41823-Espuma de Baño infantil fco pvc x45ml | F34: M | G34: 3000 | H34: 45 | I34: =IF(OR(L34="entregado",K34="despacho",J34="en proceso"),"","ingreso") | J34: =IF(OR(L34="entregado",K34="despacho"),"", IF(AND(ELABORACION!F34<>"-",ELABORACION!F34<>"PENDIENTE ELAB"),"en proceso","")) | K34: =IF(L34="entregado","",IF(EXPEDICION!L34="listo para entregar","despacho","")) | L34: =IF(EXPEDICION!L34="entregado", "entregado", "") -> entregado | M34: =EXPEDICION!M34 -> M26001
A35: 26007 | B35: 46071 | D35: BL COSMETICS | E35: ALISADO EXPERT | F35: M | G35: 500 | H35: 300 | I35: =IF(OR(L35="entregado",K35="despacho",J35="en proceso"),"","ingreso") | J35: =IF(OR(L35="entregado",K35="despacho"),"", IF(AND(ELABORACION!F35<>"-",ELABORACION!F35<>"PENDIENTE ELAB"),"en proceso","")) | K35: =IF(L35="entregado","",IF(EXPEDICION!L35="listo para entregar","despacho","")) | L35: =IF(EXPEDICION!L35="entregado", "entregado", "") -> entregado | M35: =EXPEDICION!M35 -> M26007
A36: 26007 | B36: 46071 | D36: BL COSMETICS | E36: ALISADO EXPERT X1KG | F36: M | G36: 500 | H36: 1000 | I36: =IF(OR(L36="entregado",K36="despacho",J36="en proceso"),"","ingreso") | J36: =IF(OR(L36="entregado",K36="despacho"),"", IF(AND(ELABORACION!F36<>"-",ELABORACION!F36<>"PENDIENTE ELAB"),"en proceso","")) | K36: =IF(L36="entregado","",IF(EXPEDICION!L36="listo para entregar","despacho","")) | L36: =IF(EXPEDICION!L36="entregado", "entregado", "") -> entregado | M36: =EXPEDICION!M36 -> M26007
A37: 26007 | B37: 46071 | D37: BL COSMETICS | E37: ALISADO KERATIN | F37: M | G37: 1000 | H37: 300 | I37: =IF(OR(L37="entregado",K37="despacho",J37="en proceso"),"","ingreso") | J37: =IF(OR(L37="entregado",K37="despacho"),"", IF(AND(ELABORACION!F37<>"-",ELABORACION!F37<>"PENDIENTE ELAB"),"en proceso","")) | K37: =IF(L37="entregado","",IF(EXPEDICION!L37="listo para entregar","despacho","")) | L37: =IF(EXPEDICION!L37="entregado", "entregado", "") -> entregado | M37: =EXPEDICION!M37 -> M26008
A38: 26008 | B38: 46071 | C38: P00147 | D38: LURE | E38: GOLD MASK | F38: M | G38: 600 | H38: 100 | I38: =IF(OR(L38="entregado",K38="despacho",J38="en proceso"),"","ingreso") | J38: =IF(OR(L38="entregado",K38="despacho"),"", IF(AND(ELABORACION!F38<>"-",ELABORACION!F38<>"PENDIENTE ELAB"),"en proceso","")) | K38: =IF(L38="entregado","",IF(EXPEDICION!L38="listo para entregar","despacho","")) | L38: =IF(EXPEDICION!L38="entregado", "entregado", "") -> entregado | M38: =EXPEDICION!M38 -> F26025
A39: 26009 | B39: 46071 | C39: TCL 2025-02-28 | D39: THE CHEMIST LOOK | E39: MANCHAS 5ML - PIGMENT PROTOCOL | F39: P | G39: 1000 | H39: 5 | I39: =IF(OR(L39="entregado",K39="despacho",J39="en proceso"),"","ingreso") | J39: =IF(OR(L39="entregado",K39="despacho"),"", IF(AND(ELABORACION!F39<>"-",ELABORACION!F39<>"PENDIENTE ELAB"),"en proceso","")) | K39: =IF(L39="entregado","",IF(EXPEDICION!L39="listo para entregar","despacho","")) | L39: =IF(EXPEDICION!L39="entregado", "entregado", "") -> entregado | M39: =EXPEDICION!M39 -> M26015
A40: 26009 | B40: 46071 | C40: TCL 2025-02-28 | D40: THE CHEMIST LOOK | E40: MANCHAS 30ML - PIGMENT PROTOCOL | F40: P | G40: 2000 | H40: 30 | I40: =IF(OR(L40="entregado",K40="despacho",J40="en proceso"),"","ingreso") | J40: =IF(OR(L40="entregado",K40="despacho"),"", IF(AND(ELABORACION!F40<>"-",ELABORACION!F40<>"PENDIENTE ELAB"),"en proceso","")) | K40: =IF(L40="entregado","",IF(EXPEDICION!L40="listo para entregar","despacho","")) | L40: =IF(EXPEDICION!L40="entregado", "entregado", "") -> entregado | M40: =EXPEDICION!M40 -> M26015
A41: 26009 | B41: 46071 | C41: TCL 2025-02-28 | D41: THE CHEMIST LOOK | E41: BOOSTER VIT C/GLUT | F41: P | G41: 3000 | H41: 15 | I41: =IF(OR(L41="entregado",K41="despacho",J41="en proceso"),"","ingreso") | J41: =IF(OR(L41="entregado",K41="despacho"),"", IF(AND(ELABORACION!F41<>"-",ELABORACION!F41<>"PENDIENTE ELAB"),"en proceso","")) | K41: =IF(L41="entregado","",IF(EXPEDICION!L41="listo para entregar","despacho","")) | L41: =IF(EXPEDICION!L41="entregado", "entregado", "") -> entregado | M41: =EXPEDICION!M41 -> F26059
A42: 26009 | B42: 46071 | C42: TCL 2025-02-28 | D42: THE CHEMIST LOOK | E42: BOOSTER NIACI/ZN | F42: P | G42: 3500 | H42: 15 | I42: =IF(OR(L42="entregado",K42="despacho",J42="en proceso"),"","ingreso") | J42: =IF(OR(L42="entregado",K42="despacho"),"", IF(AND(ELABORACION!F42<>"-",ELABORACION!F42<>"PENDIENTE ELAB"),"en proceso","")) | K42: =IF(L42="entregado","",IF(EXPEDICION!L42="listo para entregar","despacho","")) | L42: =IF(EXPEDICION!L42="entregado", "entregado", "") -> entregado | M42: =EXPEDICION!M42 -> F26058
A43: 26009 | B43: 46071 | C43: TCL 2025-02-28 | D43: THE CHEMIST LOOK | E43: BOOSTER HYALU-A/SI | F43: P | G43: 2400 | H43: 15 | I43: =IF(OR(L43="entregado",K43="despacho",J43="en proceso"),"","ingreso") | J43: =IF(OR(L43="entregado",K43="despacho"),"", IF(AND(ELABORACION!F43<>"-",ELABORACION!F43<>"PENDIENTE ELAB"),"en proceso","")) | K43: =IF(L43="entregado","",IF(EXPEDICION!L43="listo para entregar","despacho","")) | L43: =IF(EXPEDICION!L43="entregado", "entregado", "") -> entregado | M43: =EXPEDICION!M43 -> F26060
A44: 26009 | B44: 46071 | C44: TCL 2025-02-28 | D44: THE CHEMIST LOOK | E44: BOOSTER MUNAP-18 | F44: P | G44: 3000 | H44: 15 | I44: =IF(OR(L44="entregado",K44="despacho",J44="en proceso"),"","ingreso") | J44: =IF(OR(L44="entregado",K44="despacho"),"", IF(AND(ELABORACION!F44<>"-",ELABORACION!F44<>"PENDIENTE ELAB"),"en proceso","")) | K44: =IF(L44="entregado","",IF(EXPEDICION!L44="listo para entregar","despacho","")) | L44: =IF(EXPEDICION!L44="entregado", "entregado", "") -> entregado | M44: =EXPEDICION!M44 -> Y26017
A45: 26009 | B45: 46071 | C45: TCL 2025-02-28 | D45: THE CHEMIST LOOK | E45: TAN BOOSTER | F45: P | G45: 500 | H45: 30 | I45: =IF(OR(L45="entregado",K45="despacho",J45="en proceso"),"","ingreso") -> ingreso | J45: =IF(OR(L45="entregado",K45="despacho"),"", IF(AND(ELABORACION!F45<>"-",ELABORACION!F45<>"PENDIENTE ELAB"),"en proceso","")) | K45: =IF(L45="entregado","",IF(EXPEDICION!L45="listo para entregar","despacho","")) | L45: =IF(EXPEDICION!L45="entregado", "entregado", "") | M45: =EXPEDICION!M45
A46: 26009 | B46: 46071 | C46: TCL 2025-02-28 | D46: THE CHEMIST LOOK | E46: BOOSTER RETIN | F46: P | G46: 2000 | H46: 15 | I46: =IF(OR(L46="entregado",K46="despacho",J46="en proceso"),"","ingreso") | J46: =IF(OR(L46="entregado",K46="despacho"),"", IF(AND(ELABORACION!F46<>"-",ELABORACION!F46<>"PENDIENTE ELAB"),"en proceso","")) | K46: =IF(L46="entregado","",IF(EXPEDICION!L46="listo para entregar","despacho","")) | L46: =IF(EXPEDICION!L46="entregado", "entregado", "") -> entregado | M46: =EXPEDICION!M46 -> A26018
A47: 26009 | B47: 46071 | C47: TCL 2025-02-28 | D47: THE CHEMIST LOOK | E47: 2ND SKIN | F47: P | G47: 1000 | H47: 50 | I47: =IF(OR(L47="entregado",K47="despacho",J47="en proceso"),"","ingreso") -> ingreso | J47: =IF(OR(L47="entregado",K47="despacho"),"", IF(AND(ELABORACION!F47<>"-",ELABORACION!F47<>"PENDIENTE ELAB"),"en proceso","")) | K47: =IF(L47="entregado","",IF(EXPEDICION!L47="listo para entregar","despacho","")) | L47: =IF(EXPEDICION!L47="entregado", "entregado", "") | M47: =EXPEDICION!M47
A48: 26010 | B48: 46071 | C48: 14331 | D48: JACTANS | E48: JS-736 BRUMA FIJADORA FACIAL | F48: M | G48: 2000 | H48: 30 | I48: =IF(OR(L48="entregado",K48="despacho",J48="en proceso"),"","ingreso") | J48: =IF(OR(L48="entregado",K48="despacho"),"", IF(AND(ELABORACION!F48<>"-",ELABORACION!F48<>"PENDIENTE ELAB"),"en proceso","")) | K48: =IF(L48="entregado","",IF(EXPEDICION!L48="listo para entregar","despacho","")) | L48: =IF(EXPEDICION!L48="entregado", "entregado", "") -> entregado | M48: =EXPEDICION!M48 -> Y26022
A49: 26011 | B49: 46072 | D49: KALA | E49: AGUA DE ROSAS | F49: M | G49: 650 | H49: 90 | I49: =IF(OR(L49="entregado",K49="despacho",J49="en proceso"),"","ingreso") | J49: =IF(OR(L49="entregado",K49="despacho"),"", IF(AND(ELABORACION!F49<>"-",ELABORACION!F49<>"PENDIENTE ELAB"),"en proceso","")) | K49: =IF(L49="entregado","",IF(EXPEDICION!L49="listo para entregar","despacho","")) | L49: =IF(EXPEDICION!L49="entregado", "entregado", "") -> entregado | M49: =EXPEDICION!M49 -> F26057
A50: 26012 | B50: 46073 | D50: INTENCIONAL | E50: CREMA DE ORDEÑE | F50: M | G50: 2000 | H50: 250 | I50: =IF(OR(L50="entregado",K50="despacho",J50="en proceso"),"","ingreso") | J50: =IF(OR(L50="entregado",K50="despacho"),"", IF(AND(ELABORACION!F50<>"-",ELABORACION!F50<>"PENDIENTE ELAB"),"en proceso","")) | K50: =IF(L50="entregado","",IF(EXPEDICION!L50="listo para entregar","despacho","")) | L50: =IF(EXPEDICION!L50="entregado", "entregado", "") -> entregado | M50: =EXPEDICION!M50 -> F26062
A51: 26014 | B51: 46073 | C51: P01256 | D51: BIOESENCIA | E51: CREMA BABA DE CARACOL | F51: M | G51: 1000 | H51: 50 | I51: =IF(OR(L51="entregado",K51="despacho",J51="en proceso"),"","ingreso") | J51: =IF(OR(L51="entregado",K51="despacho"),"", IF(AND(ELABORACION!F51<>"-",ELABORACION!F51<>"PENDIENTE ELAB"),"en proceso","")) | K51: =IF(L51="entregado","",IF(EXPEDICION!L51="listo para entregar","despacho","")) | L51: =IF(EXPEDICION!L51="entregado", "entregado", "") -> entregado | M51: =EXPEDICION!M51 -> 270201
A52: 25298 | B52: 46042 | C52: P01203 | D52: BIOESENCIA | E52: SHAMPOO BABY | F52: M | G52: 500 | H52: 250 | I52: =IF(OR(L52="entregado",K52="despacho",J52="en proceso"),"","ingreso") | J52: =IF(OR(L52="entregado",K52="despacho"),"", IF(AND(ELABORACION!F52<>"-",ELABORACION!F52<>"PENDIENTE ELAB"),"en proceso","")) | K52: =IF(L52="entregado","",IF(EXPEDICION!L52="listo para entregar","despacho","")) | L52: =IF(EXPEDICION!L52="entregado", "entregado", "") -> entregado | M52: =EXPEDICION!M52 -> F26023
A53: 25298 | B53: 46042 | C53: P01203 | D53: BIOESENCIA | E53: SERUM PROBIOTICOS | F53: M | G53: 1000 | H53: 30 | I53: =IF(OR(L53="entregado",K53="despacho",J53="en proceso"),"","ingreso") | J53: =IF(OR(L53="entregado",K53="despacho"),"", IF(AND(ELABORACION!F53<>"-",ELABORACION!F53<>"PENDIENTE ELAB"),"en proceso","")) | K53: =IF(L53="entregado","",IF(EXPEDICION!L53="listo para entregar","despacho","")) | L53: =IF(EXPEDICION!L53="entregado", "entregado", "") -> entregado | M53: =EXPEDICION!M53 -> F26022
A54: 26013 | B54: 46073 | D54: OSSPRET | E54: CREMA DE ORDEÑE | F54: M | G54: 300 | H54: 1000 | I54: =IF(OR(L54="entregado",K54="despacho",J54="en proceso"),"","ingreso") | J54: =IF(OR(L54="entregado",K54="despacho"),"", IF(AND(ELABORACION!F54<>"-",ELABORACION!F54<>"PENDIENTE ELAB"),"en proceso","")) | K54: =IF(L54="entregado","",IF(EXPEDICION!L54="listo para entregar","despacho","")) | L54: =IF(EXPEDICION!L54="entregado", "entregado", "") -> entregado | M54: =EXPEDICION!M54 -> M26004 /M26013
A55: 26014 | B55: 46073 | C55: P01256 | D55: BIOESENCIA | E55: UNGUENTO PROPOLEO | F55: M | G55: 1000 | H55: 70 | I55: =IF(OR(L55="entregado",K55="despacho",J55="en proceso"),"","ingreso") | J55: =IF(OR(L55="entregado",K55="despacho"),"", IF(AND(ELABORACION!F55<>"-",ELABORACION!F55<>"PENDIENTE ELAB"),"en proceso","")) | K55: =IF(L55="entregado","",IF(EXPEDICION!L55="listo para entregar","despacho","")) | L55: =IF(EXPEDICION!L55="entregado", "entregado", "") -> entregado | M55: =EXPEDICION!M55 -> M26018
A56: 26014 | B56: 46073 | C56: P01257 | D56: BIOESENCIA | E56: BAÑO BE KERATINA BE VEGAN | F56: M | G56: 1000 | H56: 250 | I56: =IF(OR(L56="entregado",K56="despacho",J56="en proceso"),"","ingreso") | J56: =IF(OR(L56="entregado",K56="despacho"),"", IF(AND(ELABORACION!F56<>"-",ELABORACION!F56<>"PENDIENTE ELAB"),"en proceso","")) | K56: =IF(L56="entregado","",IF(EXPEDICION!L56="listo para entregar","despacho","")) | L56: =IF(EXPEDICION!L56="entregado", "entregado", "") -> entregado | M56: =EXPEDICION!M56 -> 180302
A57: 26014 | B57: 46073 | C57: P01258 | D57: BIOESENCIA | E57: REPARADOR DE PUNTAS | F57: P | G57: 1000 | H57: 30 | I57: =IF(OR(L57="entregado",K57="despacho",J57="en proceso"),"","ingreso") | J57: =IF(OR(L57="entregado",K57="despacho"),"", IF(AND(ELABORACION!F57<>"-",ELABORACION!F57<>"PENDIENTE ELAB"),"en proceso","")) | K57: =IF(L57="entregado","",IF(EXPEDICION!L57="listo para entregar","despacho","")) | L57: =IF(EXPEDICION!L57="entregado", "entregado", "") -> entregado | M57: =EXPEDICION!M57 -> 100601
A58: 26014 | B58: 46073 | C58: P01259 | D58: BIOESENCIA | E58: BRUMA FACIAL ORIGENES | F58: P | G58: 1000 | H58: 125 | I58: =IF(OR(L58="entregado",K58="despacho",J58="en proceso"),"","ingreso") | J58: =IF(OR(L58="entregado",K58="despacho"),"", IF(AND(ELABORACION!F58<>"-",ELABORACION!F58<>"PENDIENTE ELAB"),"en proceso","")) | K58: =IF(L58="entregado","",IF(EXPEDICION!L58="listo para entregar","despacho","")) | L58: =IF(EXPEDICION!L58="entregado", "entregado", "") -> entregado | M58: =EXPEDICION!M58 -> 130302
A59: 26014 | B59: 46073 | C59: P01260 | D59: BIOESENCIA | E59: EMULSION CORPORAL PROBIOTICOS | F59: M | G59: 1000 | H59: 200 | I59: =IF(OR(L59="entregado",K59="despacho",J59="en proceso"),"","ingreso") | J59: =IF(OR(L59="entregado",K59="despacho"),"", IF(AND(ELABORACION!F59<>"-",ELABORACION!F59<>"PENDIENTE ELAB"),"en proceso","")) | K59: =IF(L59="entregado","",IF(EXPEDICION!L59="listo para entregar","despacho","")) | L59: =IF(EXPEDICION!L59="entregado", "entregado", "") -> entregado | M59: =EXPEDICION!M59 -> M26059
A60: 26014 | B60: 46073 | C60: P01261 | D60: BIOESENCIA | E60: CREMA DIA/NOCHE ULTRAHIDRATANTE VEGAN | F60: M | G60: 1000 | H60: 50 | I60: =IF(OR(L60="entregado",K60="despacho",J60="en proceso"),"","ingreso") | J60: =IF(OR(L60="entregado",K60="despacho"),"", IF(AND(ELABORACION!F60<>"-",ELABORACION!F60<>"PENDIENTE ELAB"),"en proceso","")) | K60: =IF(L60="entregado","",IF(EXPEDICION!L60="listo para entregar","despacho","")) | L60: =IF(EXPEDICION!L60="entregado", "entregado", "") -> entregado | M60: =EXPEDICION!M60 -> 120301
A61: 26015 | B61: 46076 | D61: AGUEDA REY - ALMA HAIR | E61: ACONDICIONADOR CON EXTRACTO DE CEBOLLA | F61: M | G61: 1050 | H61: 350 | I61: =IF(OR(L61="entregado",K61="despacho",J61="en proceso"),"","ingreso") | J61: =IF(OR(L61="entregado",K61="despacho"),"", IF(AND(ELABORACION!F61<>"-",ELABORACION!F61<>"PENDIENTE ELAB"),"en proceso","")) | K61: =IF(L61="entregado","",IF(EXPEDICION!L61="listo para entregar","despacho","")) | L61: =IF(EXPEDICION!L61="entregado", "entregado", "") -> entregado | M61: =EXPEDICION!M61 -> M26088
A62: 26016 | B62: 46076 | C62: 774 | D62: CAV | E62: CRISTAL LIQ (BRIGHT CRYSTAL) CAV EXPRESSION | F62: P | G62: 250 | H62: 30 | I62: =IF(OR(L62="entregado",K62="despacho",J62="en proceso"),"","ingreso") | J62: =IF(OR(L62="entregado",K62="despacho"),"", IF(AND(ELABORACION!F62<>"-",ELABORACION!F62<>"PENDIENTE ELAB"),"en proceso","")) | K62: =IF(L62="entregado","",IF(EXPEDICION!L62="listo para entregar","despacho","")) | L62: =IF(EXPEDICION!L62="entregado", "entregado", "") -> entregado | M62: =EXPEDICION!M62 -> M26040
A63: 26016 | B63: 46076 | C63: 774 | D63: CAV | E63: Protector C-Plex x150 Paso 3 | F63: P | G63: 300 | H63: 150 | I63: =IF(OR(L63="entregado",K63="despacho",J63="en proceso"),"","ingreso") | J63: =IF(OR(L63="entregado",K63="despacho"),"", IF(AND(ELABORACION!F63<>"-",ELABORACION!F63<>"PENDIENTE ELAB"),"en proceso","")) | K63: =IF(L63="entregado","",IF(EXPEDICION!L63="listo para entregar","despacho","")) | L63: =IF(EXPEDICION!L63="entregado", "entregado", "") -> entregado | M63: =EXPEDICION!M63 -> M26041
A64: 26017 | B64: 46076 | D64: WSABI | E64: CONTORNO DE OJOS | F64: P | G64: 480 | H64: 15 | I64: =IF(OR(L64="entregado",K64="despacho",J64="en proceso"),"","ingreso") | J64: =IF(OR(L64="entregado",K64="despacho"),"", IF(AND(ELABORACION!F64<>"-",ELABORACION!F64<>"PENDIENTE ELAB"),"en proceso","")) | K64: =IF(L64="entregado","",IF(EXPEDICION!L64="listo para entregar","despacho","")) | L64: =IF(EXPEDICION!L64="entregado", "entregado", "") -> entregado | M64: =EXPEDICION!M64 -> M26027
A65: 26017 | B65: 46076 | D65: WSABI | E65: LECHE DE LIMPIEZA | F65: P | G65: 500 | H65: 200 | I65: =IF(OR(L65="entregado",K65="despacho",J65="en proceso"),"","ingreso") | J65: =IF(OR(L65="entregado",K65="despacho"),"", IF(AND(ELABORACION!F65<>"-",ELABORACION!F65<>"PENDIENTE ELAB"),"en proceso","")) | K65: =IF(L65="entregado","",IF(EXPEDICION!L65="listo para entregar","despacho","")) | L65: =IF(EXPEDICION!L65="entregado", "entregado", "") -> entregado | M65: =EXPEDICION!M65 -> M26011
A66: 26017 | B66: 46076 | D66: WSABI | E66: SERUM ANTIOXIDANTE VIT C | F66: P | G66: 300 | H66: 30 | I66: =IF(OR(L66="entregado",K66="despacho",J66="en proceso"),"","ingreso") | J66: =IF(OR(L66="entregado",K66="despacho"),"", IF(AND(ELABORACION!F66<>"-",ELABORACION!F66<>"PENDIENTE ELAB"),"en proceso","")) | K66: =IF(L66="entregado","",IF(EXPEDICION!L66="listo para entregar","despacho","")) | L66: =IF(EXPEDICION!L66="entregado", "entregado", "") -> entregado | M66: =EXPEDICION!M66 -> M26026
A67: 26017 | B67: 46076 | D67: WSABI | E67: TONICO CORPORAL EQUILIBRIO | F67: P | G67: 1000 | H67: 200 | I67: =IF(OR(L67="entregado",K67="despacho",J67="en proceso"),"","ingreso") | J67: =IF(OR(L67="entregado",K67="despacho"),"", IF(AND(ELABORACION!F67<>"-",ELABORACION!F67<>"PENDIENTE ELAB"),"en proceso","")) | K67: =IF(L67="entregado","",IF(EXPEDICION!L67="listo para entregar","despacho","")) | L67: =IF(EXPEDICION!L67="entregado", "entregado", "") -> entregado | M67: =EXPEDICION!M67 -> M26012
A68: 26018 | B68: 46063 | C68: 15125 | D68: THELMA Y LOUISE | E68: SERUM ANTIAGE | F68: M | G68: 2100 | H68: 30 | I68: =IF(OR(L68="entregado",K68="despacho",J68="en proceso"),"","ingreso") | J68: =IF(OR(L68="entregado",K68="despacho"),"", IF(AND(ELABORACION!F68<>"-",ELABORACION!F68<>"PENDIENTE ELAB"),"en proceso","")) | K68: =IF(L68="entregado","",IF(EXPEDICION!L68="listo para entregar","despacho","")) | L68: =IF(EXPEDICION!L68="entregado", "entregado", "") -> entregado | M68: =EXPEDICION!M68 -> M26023
A69: 26018 | B69: 46063 | C69: 15125 | D69: THELMA Y LOUISE | E69: SERUM DESCONGESTIVO | F69: M | G69: 2100 | H69: 30 | I69: =IF(OR(L69="entregado",K69="despacho",J69="en proceso"),"","ingreso") | J69: =IF(OR(L69="entregado",K69="despacho"),"", IF(AND(ELABORACION!F69<>"-",ELABORACION!F69<>"PENDIENTE ELAB"),"en proceso","")) | K69: =IF(L69="entregado","",IF(EXPEDICION!L69="listo para entregar","despacho","")) | L69: =IF(EXPEDICION!L69="entregado", "entregado", "") -> entregado | M69: =EXPEDICION!M69 -> M26021
A70: 26019 | B70: 46076 | C70: 775 | D70: CAV | E70: Rebond C-Plex CAV x 500 ml (Paso 1) | F70: M | G70: 200 | H70: 500 | I70: =IF(OR(L70="entregado",K70="despacho",J70="en proceso"),"","ingreso") | J70: =IF(OR(L70="entregado",K70="despacho"),"", IF(AND(ELABORACION!F70<>"-",ELABORACION!F70<>"PENDIENTE ELAB"),"en proceso","")) | K70: =IF(L70="entregado","",IF(EXPEDICION!L70="listo para entregar","despacho","")) | L70: =IF(EXPEDICION!L70="entregado", "entregado", "") -> entregado | M70: =EXPEDICION!M70 -> M26062
A71: 26019 | B71: 46076 | C71: 775 | D71: CAV | E71: Finishing C-Plex CAV x 500 ml (Paso 2) | F71: M | G71: 400 | H71: 500 | I71: =IF(OR(L71="entregado",K71="despacho",J71="en proceso"),"","ingreso") | J71: =IF(OR(L71="entregado",K71="despacho"),"", IF(AND(ELABORACION!F71<>"-",ELABORACION!F71<>"PENDIENTE ELAB"),"en proceso","")) | K71: =IF(L71="entregado","",IF(EXPEDICION!L71="listo para entregar","despacho","")) | L71: =IF(EXPEDICION!L71="entregado", "entregado", "") -> entregado | M71: =EXPEDICION!M71 -> M26061
A72: 26020 | B72: 46077 | C72: 1704 | D72: LABORATORIO ONCE | E72: ALBA SERUM X 30 ML DRA ROSSI | F72: P | G72: 300 | H72: 30 | I72: =IF(OR(L72="entregado",K72="despacho",J72="en proceso"),"","ingreso") | J72: =IF(OR(L72="entregado",K72="despacho"),"", IF(AND(ELABORACION!F72<>"-",ELABORACION!F72<>"PENDIENTE ELAB"),"en proceso","")) -> en proceso | K72: =IF(L72="entregado","",IF(EXPEDICION!L72="listo para entregar","despacho","")) | L72: =IF(EXPEDICION!L72="entregado", "entregado", "") | M72: =EXPEDICION!M72
A73: 26021 | B73: 46078 | D73: UNICA | E73: CREMA CORPORAL HUMECTANTE KARITE | F73: M | G73: 500 | H73: 280 | I73: =IF(OR(L73="entregado",K73="despacho",J73="en proceso"),"","ingreso") | J73: =IF(OR(L73="entregado",K73="despacho"),"", IF(AND(ELABORACION!F73<>"-",ELABORACION!F73<>"PENDIENTE ELAB"),"en proceso","")) | K73: =IF(L73="entregado","",IF(EXPEDICION!L73="listo para entregar","despacho","")) | L73: =IF(EXPEDICION!L73="entregado", "entregado", "") -> entregado | M73: =EXPEDICION!M73 -> 110301
A74: 26022 | B74: 46078 | D74: OLANN | E74: Serum hialurónico 30 ml | F74: P | G74: 250 | H74: 30 | I74: =IF(OR(L74="entregado",K74="despacho",J74="en proceso"),"","ingreso") | J74: =IF(OR(L74="entregado",K74="despacho"),"", IF(AND(ELABORACION!F74<>"-",ELABORACION!F74<>"PENDIENTE ELAB"),"en proceso","")) | K74: =IF(L74="entregado","",IF(EXPEDICION!L74="listo para entregar","despacho","")) | L74: =IF(EXPEDICION!L74="entregado", "entregado", "") -> entregado | M74: =EXPEDICION!M74 -> M26065
A75: 26022 | B75: 46078 | D75: OLANN | E75: BRUMA FACIAL | F75: P | G75: 250 | H75: 100 | I75: =IF(OR(L75="entregado",K75="despacho",J75="en proceso"),"","ingreso") | J75: =IF(OR(L75="entregado",K75="despacho"),"", IF(AND(ELABORACION!F75<>"-",ELABORACION!F75<>"PENDIENTE ELAB"),"en proceso","")) | K75: =IF(L75="entregado","",IF(EXPEDICION!L75="listo para entregar","despacho","")) | L75: =IF(EXPEDICION!L75="entregado", "entregado", "") -> entregado | M75: =EXPEDICION!M75 -> M26060
A76: 26022 | B76: 46078 | D76: OLANN | E76: CREMA FACIAL DE DIA ULTRAHUMECTANTE | F76: P | G76: 250 | H76: 30 | I76: =IF(OR(L76="entregado",K76="despacho",J76="en proceso"),"","ingreso") | J76: =IF(OR(L76="entregado",K76="despacho"),"", IF(AND(ELABORACION!F76<>"-",ELABORACION!F76<>"PENDIENTE ELAB"),"en proceso","")) | K76: =IF(L76="entregado","",IF(EXPEDICION!L76="listo para entregar","despacho","")) | L76: =IF(EXPEDICION!L76="entregado", "entregado", "") -> entregado | M76: =EXPEDICION!M76 -> M26031
A77: 26022 | B77: 46078 | D77: OLANN | E77: CREMA FACIAL DE NOCHE TENSORA | F77: P | G77: 250 | H77: 30 | I77: =IF(OR(L77="entregado",K77="despacho",J77="en proceso"),"","ingreso") | J77: =IF(OR(L77="entregado",K77="despacho"),"", IF(AND(ELABORACION!F77<>"-",ELABORACION!F77<>"PENDIENTE ELAB"),"en proceso","")) | K77: =IF(L77="entregado","",IF(EXPEDICION!L77="listo para entregar","despacho","")) | L77: =IF(EXPEDICION!L77="entregado", "entregado", "") -> entregado | M77: =EXPEDICION!M77 -> M26032
A78: 26022 | B78: 46078 | D78: OLANN | E78: CONTORNO DE OJOS | F78: P | G78: 250 | H78: 30 | I78: =IF(OR(L78="entregado",K78="despacho",J78="en proceso"),"","ingreso") | J78: =IF(OR(L78="entregado",K78="despacho"),"", IF(AND(ELABORACION!F78<>"-",ELABORACION!F78<>"PENDIENTE ELAB"),"en proceso","")) | K78: =IF(L78="entregado","",IF(EXPEDICION!L78="listo para entregar","despacho","")) | L78: =IF(EXPEDICION!L78="entregado", "entregado", "") -> entregado | M78: =EXPEDICION!M78 -> M26033
A79: 26023 | B79: 46083 | D79: ECODERM - AGUAZU | E79: ESPUMA DE BAÑO ADULTO | F79: M | G79: 200 | H79: 200 | I79: =IF(OR(L79="entregado",K79="despacho",J79="en proceso"),"","ingreso") | J79: =IF(OR(L79="entregado",K79="despacho"),"", IF(AND(ELABORACION!F79<>"-",ELABORACION!F79<>"PENDIENTE ELAB"),"en proceso","")) | K79: =IF(L79="entregado","",IF(EXPEDICION!L79="listo para entregar","despacho","")) | L79: =IF(EXPEDICION!L79="entregado", "entregado", "") -> entregado | M79: =EXPEDICION!M79 -> M26034
A80: 26023 | B80: 46083 | D80: ECODERM - AGUAZU | E80: ESPUMA DE BAÑO BALLENA | F80: M | G80: 200 | H80: 200 | I80: =IF(OR(L80="entregado",K80="despacho",J80="en proceso"),"","ingreso") | J80: =IF(OR(L80="entregado",K80="despacho"),"", IF(AND(ELABORACION!F80<>"-",ELABORACION!F80<>"PENDIENTE ELAB"),"en proceso","")) | K80: =IF(L80="entregado","",IF(EXPEDICION!L80="listo para entregar","despacho","")) | L80: =IF(EXPEDICION!L80="entregado", "entregado", "") -> entregado | M80: =EXPEDICION!M80 -> M26034
A81: 26023 | B81: 46083 | D81: ECODERM - AGUAZU | E81: ESPUMA DE BAÑO BALLENA X500 | F81: M | G81: 100 | H81: 500 | I81: =IF(OR(L81="entregado",K81="despacho",J81="en proceso"),"","ingreso") | J81: =IF(OR(L81="entregado",K81="despacho"),"", IF(AND(ELABORACION!F81<>"-",ELABORACION!F81<>"PENDIENTE ELAB"),"en proceso","")) | K81: =IF(L81="entregado","",IF(EXPEDICION!L81="listo para entregar","despacho","")) | L81: =IF(EXPEDICION!L81="entregado", "entregado", "") -> entregado | M81: =EXPEDICION!M81 -> M26034
A82: 26023 | B82: 46083 | D82: ECODERM - AGUAZU | E82: ESPUMA DE BAÑO ADULTO X500 | F82: M | G82: 100 | H82: 500 | I82: =IF(OR(L82="entregado",K82="despacho",J82="en proceso"),"","ingreso") | J82: =IF(OR(L82="entregado",K82="despacho"),"", IF(AND(ELABORACION!F82<>"-",ELABORACION!F82<>"PENDIENTE ELAB"),"en proceso","")) | K82: =IF(L82="entregado","",IF(EXPEDICION!L82="listo para entregar","despacho","")) | L82: =IF(EXPEDICION!L82="entregado", "entregado", "") -> entregado | M82: =EXPEDICION!M82 -> M26034
A83: 26023 | B83: 46083 | D83: ECODERM - AGUAZU | E83: BALSAMO HERBAL | F83: M | G83: 300 | H83: 30 | I83: =IF(OR(L83="entregado",K83="despacho",J83="en proceso"),"","ingreso") | J83: =IF(OR(L83="entregado",K83="despacho"),"", IF(AND(ELABORACION!F83<>"-",ELABORACION!F83<>"PENDIENTE ELAB"),"en proceso","")) | K83: =IF(L83="entregado","",IF(EXPEDICION!L83="listo para entregar","despacho","")) | L83: =IF(EXPEDICION!L83="entregado", "entregado", "") -> entregado | M83: =EXPEDICION!M83 -> M26044
A84: 26023 | B84: 46083 | D84: ECODERM - DUGA | E84: ACONDICIONADOR INFANTIL | F84: P | G84: 300 | H84: 125 | I84: =IF(OR(L84="entregado",K84="despacho",J84="en proceso"),"","ingreso") | J84: =IF(OR(L84="entregado",K84="despacho"),"", IF(AND(ELABORACION!F84<>"-",ELABORACION!F84<>"PENDIENTE ELAB"),"en proceso","")) | K84: =IF(L84="entregado","",IF(EXPEDICION!L84="listo para entregar","despacho","")) | L84: =IF(EXPEDICION!L84="entregado", "entregado", "") -> entregado | M84: =EXPEDICION!M84 -> M26078
A85: 26024 | B85: 46083 | C85: 15134 | D85: THELMA Y LOUISE | E85: ALCOHOL EN GEL SANDIA FARMACITY KIDS | F85: M | G85: 6000 | H85: 25 | I85: =IF(OR(L85="entregado",K85="despacho",J85="en proceso"),"","ingreso") | J85: =IF(OR(L85="entregado",K85="despacho"),"", IF(AND(ELABORACION!F85<>"-",ELABORACION!F85<>"PENDIENTE ELAB"),"en proceso","")) | K85: =IF(L85="entregado","",IF(EXPEDICION!L85="listo para entregar","despacho","")) | L85: =IF(EXPEDICION!L85="entregado", "entregado", "") -> entregado | M85: =EXPEDICION!M85
A86: 26024 | B86: 46083 | C86: 15134 | D86: THELMA Y LOUISE | E86: ALCOHOL EN GEL CHICLE FARMACITY KIDS | F86: M | G86: 6000 | H86: 25 | I86: =IF(OR(L86="entregado",K86="despacho",J86="en proceso"),"","ingreso") | J86: =IF(OR(L86="entregado",K86="despacho"),"", IF(AND(ELABORACION!F86<>"-",ELABORACION!F86<>"PENDIENTE ELAB"),"en proceso","")) | K86: =IF(L86="entregado","",IF(EXPEDICION!L86="listo para entregar","despacho","")) | L86: =IF(EXPEDICION!L86="entregado", "entregado", "") -> entregado | M86: =EXPEDICION!M86 -> 120302
A87: 26025 | B87: 46083 | C87: 15133 | D87: THELMA Y LOUISE | E87: ALCOHOL EN GEL CHICLE TYL | F87: M | G87: 2000 | H87: 25 | I87: =IF(OR(L87="entregado",K87="despacho",J87="en proceso"),"","ingreso") | J87: =IF(OR(L87="entregado",K87="despacho"),"", IF(AND(ELABORACION!F87<>"-",ELABORACION!F87<>"PENDIENTE ELAB"),"en proceso","")) | K87: =IF(L87="entregado","",IF(EXPEDICION!L87="listo para entregar","despacho","")) | L87: =IF(EXPEDICION!L87="entregado", "entregado", "") -> entregado | M87: =EXPEDICION!M87 -> 160303
A88: 26025 | B88: 46083 | C88: 15133 | D88: THELMA Y LOUISE | E88: ALCOHOL EN GEL FRUTOS ROJOS TYL | F88: M | G88: 2000 | H88: 25 | I88: =IF(OR(L88="entregado",K88="despacho",J88="en proceso"),"","ingreso") | J88: =IF(OR(L88="entregado",K88="despacho"),"", IF(AND(ELABORACION!F88<>"-",ELABORACION!F88<>"PENDIENTE ELAB"),"en proceso","")) | K88: =IF(L88="entregado","",IF(EXPEDICION!L88="listo para entregar","despacho","")) | L88: =IF(EXPEDICION!L88="entregado", "entregado", "") -> entregado | M88: =EXPEDICION!M88
A89: 26025 | B89: 46083 | C89: 15133 | D89: THELMA Y LOUISE | E89: ALCOHOL EN GEL DURAZNO TYL | F89: M | G89: 2000 | H89: 25 | I89: =IF(OR(L89="entregado",K89="despacho",J89="en proceso"),"","ingreso") | J89: =IF(OR(L89="entregado",K89="despacho"),"", IF(AND(ELABORACION!F89<>"-",ELABORACION!F89<>"PENDIENTE ELAB"),"en proceso","")) | K89: =IF(L89="entregado","",IF(EXPEDICION!L89="listo para entregar","despacho","")) | L89: =IF(EXPEDICION!L89="entregado", "entregado", "") -> entregado | M89: =EXPEDICION!M89
A90: 26025 | B90: 46083 | C90: 15133 | D90: THELMA Y LOUISE | E90: ALCOHOL EN GEL COCO TYL | F90: M | G90: 2000 | H90: 25 | I90: =IF(OR(L90="entregado",K90="despacho",J90="en proceso"),"","ingreso") | J90: =IF(OR(L90="entregado",K90="despacho"),"", IF(AND(ELABORACION!F90<>"-",ELABORACION!F90<>"PENDIENTE ELAB"),"en proceso","")) | K90: =IF(L90="entregado","",IF(EXPEDICION!L90="listo para entregar","despacho","")) | L90: =IF(EXPEDICION!L90="entregado", "entregado", "") -> entregado | M90: =EXPEDICION!M90
A91: 26025 | B91: 46083 | C91: 15133 | D91: THELMA Y LOUISE | E91: ALCOHOL EN GEL VAINILLA TYL | F91: M | G91: 2000 | H91: 25 | I91: =IF(OR(L91="entregado",K91="despacho",J91="en proceso"),"","ingreso") | J91: =IF(OR(L91="entregado",K91="despacho"),"", IF(AND(ELABORACION!F91<>"-",ELABORACION!F91<>"PENDIENTE ELAB"),"en proceso","")) | K91: =IF(L91="entregado","",IF(EXPEDICION!L91="listo para entregar","despacho","")) | L91: =IF(EXPEDICION!L91="entregado", "entregado", "") -> entregado | M91: =EXPEDICION!M91
A92: 26026 | B92: 46083 | D92: DERMION / FRANCO | E92: SERUM NIACINAMIDA | F92: P | G92: 500 | H92: 30 | I92: =IF(OR(L92="entregado",K92="despacho",J92="en proceso"),"","ingreso") | J92: =IF(OR(L92="entregado",K92="despacho"),"", IF(AND(ELABORACION!F92<>"-",ELABORACION!F92<>"PENDIENTE ELAB"),"en proceso","")) | K92: =IF(L92="entregado","",IF(EXPEDICION!L92="listo para entregar","despacho","")) | L92: =IF(EXPEDICION!L92="entregado", "entregado", "") -> entregado | M92: =EXPEDICION!M92 -> M26010
A93: 26027 | B93: 46083 | D93: THE GLOW FACTOR | E93: CREMA CLARITÉ | F93: P | G93: 1000 | H93: 30 | I93: =IF(OR(L93="entregado",K93="despacho",J93="en proceso"),"","ingreso") | J93: =IF(OR(L93="entregado",K93="despacho"),"", IF(AND(ELABORACION!F93<>"-",ELABORACION!F93<>"PENDIENTE ELAB"),"en proceso","")) | K93: =IF(L93="entregado","",IF(EXPEDICION!L93="listo para entregar","despacho","")) | L93: =IF(EXPEDICION!L93="entregado", "entregado", "") -> entregado | M93: =EXPEDICION!M93 -> M26025
A94: 26028 | B94: 46086 | C94: 777 | D94: CAV | E94: SHAMPOO MAXLISS X400ML | F94: M | G94: 200 | H94: 400 | I94: =IF(OR(L94="entregado",K94="despacho",J94="en proceso"),"","ingreso") | J94: =IF(OR(L94="entregado",K94="despacho"),"", IF(AND(ELABORACION!F94<>"-",ELABORACION!F94<>"PENDIENTE ELAB"),"en proceso","")) | K94: =IF(L94="entregado","",IF(EXPEDICION!L94="listo para entregar","despacho","")) | L94: =IF(EXPEDICION!L94="entregado", "entregado", "") -> entregado | M94: =EXPEDICION!M94 -> M26038
A95: 26028 | B95: 46086 | C95: 777 | D95: CAV | E95: CONDITIONER MAXLISS X400G | F95: M | G95: 200 | H95: 400 | I95: =IF(OR(L95="entregado",K95="despacho",J95="en proceso"),"","ingreso") | J95: =IF(OR(L95="entregado",K95="despacho"),"", IF(AND(ELABORACION!F95<>"-",ELABORACION!F95<>"PENDIENTE ELAB"),"en proceso","")) | K95: =IF(L95="entregado","",IF(EXPEDICION!L95="listo para entregar","despacho","")) | L95: =IF(EXPEDICION!L95="entregado", "entregado", "") -> entregado | M95: =EXPEDICION!M95 -> M26039
A96: 26028 | B96: 46086 | C96: 777 | D96: CAV | E96: VITAMIN SHOCK X150G | F96: P | G96: 700 | H96: 150 | I96: =IF(OR(L96="entregado",K96="despacho",J96="en proceso"),"","ingreso") | J96: =IF(OR(L96="entregado",K96="despacho"),"", IF(AND(ELABORACION!F96<>"-",ELABORACION!F96<>"PENDIENTE ELAB"),"en proceso","")) | K96: =IF(L96="entregado","",IF(EXPEDICION!L96="listo para entregar","despacho","")) | L96: =IF(EXPEDICION!L96="entregado", "entregado", "") -> entregado | M96: =EXPEDICION!M96 -> M26066
A97: 26029 | B97: 46086 | C97: 1080 | D97: NIZA | E97: CLEAR ACNE LOTION | F97: P | G97: 300 | H97: 50 | I97: =IF(OR(L97="entregado",K97="despacho",J97="en proceso"),"","ingreso") | J97: =IF(OR(L97="entregado",K97="despacho"),"", IF(AND(ELABORACION!F97<>"-",ELABORACION!F97<>"PENDIENTE ELAB"),"en proceso","")) | K97: =IF(L97="entregado","",IF(EXPEDICION!L97="listo para entregar","despacho","")) | L97: =IF(EXPEDICION!L97="entregado", "entregado", "") -> entregado | M97: =EXPEDICION!M97 -> M26085
A98: 26029 | B98: 46086 | C98: 1080 | D98: NIZA | E98: SIGNATURE AGE REVERSE | F98: P | G98: 500 | H98: 30 | I98: =IF(OR(L98="entregado",K98="despacho",J98="en proceso"),"","ingreso") | J98: =IF(OR(L98="entregado",K98="despacho"),"", IF(AND(ELABORACION!F98<>"-",ELABORACION!F98<>"PENDIENTE ELAB"),"en proceso","")) | K98: =IF(L98="entregado","",IF(EXPEDICION!L98="listo para entregar","despacho","")) | L98: =IF(EXPEDICION!L98="entregado", "entregado", "") -> entregado | M98: =EXPEDICION!M98 -> M26086
A99: 26030 | B99: 46086 | D99: THE CURIOUS SKIN | E99: SERUM BOOSTER Telangyn | F99: P | G99: 500 | H99: 15 | I99: =IF(OR(L99="entregado",K99="despacho",J99="en proceso"),"","ingreso") | J99: =IF(OR(L99="entregado",K99="despacho"),"", IF(AND(ELABORACION!F99<>"-",ELABORACION!F99<>"PENDIENTE ELAB"),"en proceso","")) | K99: =IF(L99="entregado","",IF(EXPEDICION!L99="listo para entregar","despacho","")) | L99: =IF(EXPEDICION!L99="entregado", "entregado", "") -> entregado | M99: =EXPEDICION!M99 -> Y26046
A100: 26030 | B100: 46086 | D100: THE CURIOUS SKIN | E100: CARROT OIL | F100: P | G100: 500 | H100: 50 | I100: =IF(OR(L100="entregado",K100="despacho",J100="en proceso"),"","ingreso") | J100: =IF(OR(L100="entregado",K100="despacho"),"", IF(AND(ELABORACION!F100<>"-",ELABORACION!F100<>"PENDIENTE ELAB"),"en proceso","")) | K100: =IF(L100="entregado","",IF(EXPEDICION!L100="listo para entregar","despacho","")) | L100: =IF(EXPEDICION!L100="entregado", "entregado", "") -> entregado | M100: =EXPEDICION!M100 -> Y26047
...

Sheet ELABORACION
A1: Fecha | B1: N° OC | C1: CLIENTE | D1: PRODUCTO | E1: KG | F1: ESTADO | G1: Graneles | H1: RESPONSABLE | I1: FECHA | J1: N°LOTE | K1: OBSERVACIONES
A2: =PEDIDOS!B2 -> 46035 | B2: =PEDIDOS!C2 -> 163 | C2: =PEDIDOS!D2 -> THE MINIMAL CO | D2: =PEDIDOS!E2 -> MILKY TONER | E2: =PEDIDOS!G2*PEDIDOS!H2/1000 -> 90 | F2: APROBADO | H2: NICOLAS | I2: =EXPEDICION!K2-7 -> 46069 | J2: =PEDIDOS!M2 -> F26021
A3: =PEDIDOS!B3 -> 46035 | B3: =PEDIDOS!C3 -> 14297 | C3: =PEDIDOS!D3 -> JACTANS | D3: =PEDIDOS!E3 -> JS-941 AGUA MICELAR BIFASCIA | E3: =PEDIDOS!G3*PEDIDOS!H3/1000 -> 105 | F3: APROBADO | H3: Nicolas | I3: =EXPEDICION!K3-7 -> 46073 | J3: =PEDIDOS!M3 -> F26031
A4: =PEDIDOS!B4 -> 46035 | B4: =PEDIDOS!C4 -> 15074 | C4: =PEDIDOS!D4 -> THELMA Y LOUISE | D4: =PEDIDOS!E4 -> AGUA TERMAL | E4: =PEDIDOS!G4*PEDIDOS!H4/1000 -> 294 | F4: APROBADO | H4: Cristian | I4: =EXPEDICION!K4-7 -> 46076 | J4: =PEDIDOS!M4 -> F26041
A5: =PEDIDOS!B5 -> 46035 | B5: =PEDIDOS!C5 | C5: =PEDIDOS!D5 -> LIORA | D5: =PEDIDOS!E5 -> CREMA PARA PEINAR RULOS | E5: =PEDIDOS!G5*PEDIDOS!H5/1000 -> 51 | F5: APROBADO | H5: Cristian | I5: =EXPEDICION!K5-7 -> 46154 | J5: =PEDIDOS!M5 -> Y26039 | K5: Falta fragancia
A6: =PEDIDOS!B6 -> 46042 | B6: =PEDIDOS!C6 -> P01203 | C6: =PEDIDOS!D6 -> BIOESENCIA | D6: =PEDIDOS!E6 -> SERUM ORIGENES | E6: =PEDIDOS!G6*PEDIDOS!H6/1000 -> 48 | F6: APROBADO | H6: Nicolás | I6: =EXPEDICION!K6-7 -> 46070 | J6: =PEDIDOS!M6 -> 240201
A7: =PEDIDOS!B7 -> 46042 | B7: =PEDIDOS!C7 | C7: =PEDIDOS!D7 -> WSABI | D7: =PEDIDOS!E7 -> SERUM INTIMO | E7: =PEDIDOS!G7*PEDIDOS!H7/1000 -> 9 | F7: APROBADO | H7: Santino | I7: =EXPEDICION!K7-7 -> 46080 | J7: =PEDIDOS!M7 -> F26049
A8: =PEDIDOS!B8 -> 46042 | B8: =PEDIDOS!C8 | C8: =PEDIDOS!D8 -> MERMER | D8: =PEDIDOS!E8 -> ACEITE CORPORAL LAVANDA | E8: =PEDIDOS!G8*PEDIDOS!H8/1000 -> 60 | F8: APROBADO | H8: NICOLAS | I8: =EXPEDICION!K8-7 -> 46043 | J8: =PEDIDOS!M8 -> E26087
A9: =PEDIDOS!B9 -> 46042 | B9: =PEDIDOS!C9 | C9: =PEDIDOS!D9 -> MERMER | D9: =PEDIDOS!E9 -> ACEITE CORPORAL ALMENDRA | E9: =PEDIDOS!G9*PEDIDOS!H9/1000 -> 60 | F9: APROBADO | H9: NICOLAS | I9: =EXPEDICION!K9-7 -> 46043 | J9: =PEDIDOS!M9 -> E26088
A10: =PEDIDOS!B10 -> 46042 | B10: =PEDIDOS!C10 | C10: =PEDIDOS!D10 -> MERMER | D10: =PEDIDOS!E10 -> ACEITE CORPORAL ROSAS | E10: =PEDIDOS!G10*PEDIDOS!H10/1000 -> 60 | F10: APROBADO | H10: CRISTIAN | I10: =EXPEDICION!K10-7 -> 46043 | J10: =PEDIDOS!M10 -> E26089
A11: =PEDIDOS!B11 -> 46042 | B11: =PEDIDOS!C11 | C11: =PEDIDOS!D11 -> MERMER | D11: =PEDIDOS!E11 -> ACEITE CORPORAL SESAMO | E11: =PEDIDOS!G11*PEDIDOS!H11/1000 -> 60 | F11: APROBADO | H11: CRISTIAN | I11: =EXPEDICION!K11-7 -> 46043 | J11: =PEDIDOS!M11 -> E26090
A12: =PEDIDOS!B12 -> 46042 | B12: =PEDIDOS!C12 | C12: =PEDIDOS!D12 -> MERMER | D12: =PEDIDOS!E12 -> ACEITE CORPORAL INCIENSO | E12: =PEDIDOS!G12*PEDIDOS!H12/1000 -> 60 | F12: APROBADO | H12: CRISTIAN | I12: =EXPEDICION!K12-7 -> 46043 | J12: =PEDIDOS!M12 -> E26091
A13: =PEDIDOS!B13 -> 46042 | B13: =PEDIDOS!C13 | C13: =PEDIDOS!D13 -> MERMER | D13: =PEDIDOS!E13 -> ACEITE CORPORAL ARNICA | E13: =PEDIDOS!G13*PEDIDOS!H13/1000 -> 60 | F13: APROBADO | H13: NICOLAS | I13: =EXPEDICION!K13-7 -> 46043 | J13: =PEDIDOS!M13 -> E26092
A14: =PEDIDOS!B14 -> 46042 | B14: =PEDIDOS!C14 | C14: =PEDIDOS!D14 -> MERMER | D14: =PEDIDOS!E14 -> LOCION CAPILAR | E14: =PEDIDOS!G14*PEDIDOS!H14/1000 -> 40 | F14: APROBADO | H14: Nicolás | I14: =EXPEDICION!K14-7 -> 46104 | J14: =PEDIDOS!M14 -> M26042
A15: =PEDIDOS!B15 -> 46042 | B15: =PEDIDOS!C15 | C15: =PEDIDOS!D15 -> MERMER | D15: =PEDIDOS!E15 -> SERUM CAPILAR | E15: =PEDIDOS!G15*PEDIDOS!H15/1000 -> 40 | F15: APROBADO | H15: Santino | I15: =EXPEDICION!K15-7 -> 46105 | J15: =PEDIDOS!M15 -> M26030
A16: =PEDIDOS!B16 -> 46049 | B16: =PEDIDOS!C16 -> 1708 | C16: =PEDIDOS!D16 -> LABORATORIO ONCE | D16: =PEDIDOS!E16 -> SERUM ACIDO HIALURONICO + NIACINAMIDA | E16: =PEDIDOS!G16*PEDIDOS!H16/1000 -> 49.59 | F16: APROBADO | H16: Cristian | I16: =EXPEDICION!K16-7 -> 46076 | J16: =PEDIDOS!M16 -> F26048
A17: =PEDIDOS!B17 -> 46050 | B17: =PEDIDOS!C17 -> 15098 | C17: =PEDIDOS!D17 -> THELMA Y LOUISE | D17: =PEDIDOS!E17 -> CREMA BIFASICA CHERRY | E17: =PEDIDOS!G17*PEDIDOS!H17/1000 -> 262.4 | F17: APROBADO | H17: Cristian | I17: =EXPEDICION!K17-7 -> -7 | J17: =PEDIDOS!M17
... A24: =PEDIDOS!B24 -> 46043 | B24: =PEDIDOS!C24 -> 103 | C24: =PEDIDOS!D24 -> UNICA | D24: =PEDIDOS!E24 -> CREMA ENEBRO | E24: =PEDIDOS!G24*PEDIDOS!H24/1000 -> 45 | F24: APROBADO | H24: Nicolás | I24: =EXPEDICION!K24-7 -> 46094 | J24: =PEDIDOS!M24 -> 200301
A25: =PEDIDOS!B25 -> 46066 | B25: =PEDIDOS!C25 -> 15114 | C25: =PEDIDOS!D25 -> THELMA Y LOUISE | D25: =PEDIDOS!E25 -> SERUM BIFASICO JOJOBA-POMELO | E25: =PEDIDOS!G25*PEDIDOS!H25/1000 -> 90.72 | F25: APROBADO | H25: Valentin | I25: 46087 | J25: =PEDIDOS!M25 -> M26024
A26: =PEDIDOS!B26 -> 46066 | B26: =PEDIDOS!C26 -> 15114 | C26: =PEDIDOS!D26 -> THELMA Y LOUISE | D26: =PEDIDOS!E26 -> SERUM BIFASICO PEPINO-HAMAMELIS | E26: =PEDIDOS!G26*PEDIDOS!H26/1000 -> 90.72 | F26: APROBADO | H26: Nicolás | I26: =EXPEDICION!K26-7 -> 46100 | J26: =PEDIDOS!M26 -> M26083
A27: =PEDIDOS!B27 -> 46066 | B27: =PEDIDOS!C27 -> 15114 | C27: =PEDIDOS!D27 -> THELMA Y LOUISE | D27: =PEDIDOS!E27 -> SERUM BIFASICO LAVANDA-BLUEBERRY | E27: =PEDIDOS!G27*PEDIDOS!H27/1000 -> 90.72 | F27: APROBADO | H27: Cristián | I27: =EXPEDICION!K27-7 -> 46086 | J27: =PEDIDOS!M27 -> M26022
A28: =PEDIDOS!B28 -> 46066 | B28: =PEDIDOS!C28 -> 15114 | C28: =PEDIDOS!D28 -> THELMA Y LOUISE | D28: =PEDIDOS!E28 -> SERUM BIFASICO ROSA MOSQUETA-ROSAS | E28: =PEDIDOS!G28*PEDIDOS!H28/1000 -> 90.72 | F28: APROBADO | H28: Nicolas | I28: =EXPEDICION!K28-7 -> 46101 | J28: =PEDIDOS!M28 -> M26084
A29: =PEDIDOS!B29 -> 46071 | B29: =PEDIDOS!C29 -> 772 | C29: =PEDIDOS!D29 -> CAV | D29: =PEDIDOS!E29 -> SHAMPOO BIO MOLECULAR X400ML VITAMIN SHOCK | E29: =PEDIDOS!G29*PEDIDOS!H29/1000 -> 280 | F29: APROBADO | H29: Cristian | I29: =EXPEDICION!K29-7 -> 46080 | J29: =PEDIDOS!M29 -> E26064
A30: =PEDIDOS!B30 -> 46071 | B30: =PEDIDOS!C30 -> 772 | C30: =PEDIDOS!D30 -> CAV | D30: =PEDIDOS!E30 -> SERUM BIO MOLUECULAR X30ML VITAMIN SHOCK | E30: =PEDIDOS!G30*PEDIDOS!H30/1000 -> 9 | F30: APROBADO | H30: Nicolás | I30: =EXPEDICION!K30-7 -> 46087 | J30: =PEDIDOS!M30 -> M26009
A31: =PEDIDOS!B31 -> 46071 | B31: =PEDIDOS!C31 -> 772 | C31: =PEDIDOS!D31 -> CAV | D31: =PEDIDOS!E31 -> BALSAMO X400ML BIOMIC C/ ACIDO HIAL + CAPIMAX | E31: =PEDIDOS!G31*PEDIDOS!H31/1000 -> 160 | F31: APROBADO | H31: Cristian | I31: =EXPEDICION!K31-7 -> -7 | J31: =PEDIDOS!M31
A32: =PEDIDOS!B32 -> 46071 | B32: =PEDIDOS!C32 -> 772 | C32: =PEDIDOS!D32 -> CAV | D32: =PEDIDOS!E32 -> MASCARA BIO MOLECULAR VITAMIN SHOCK X300ML | E32: =PEDIDOS!G32*PEDIDOS!H32/1000 -> 210 | F32: APROBADO | H32: Cristian | I32: =EXPEDICION!K32-7 -> 46090 | J32: =PEDIDOS!M32 -> M26045
A33: =PEDIDOS!B33 -> 46071 | B33: =PEDIDOS!C33 -> 14329 | C33: =PEDIDOS!D33 -> JACTANS - DISNEY | D33: =PEDIDOS!E33 -> DSH-41823-Shampoo infantil fco pvc x45ml | E33: =PEDIDOS!G33*PEDIDOS!H33/1000 -> 135 | F33: APROBADO | H33: Santino | I33: =EXPEDICION!K33-7 -> 46079 | J33: =PEDIDOS!M33 -> M26002
A34: =PEDIDOS!B34 -> 46071 | B34: =PEDIDOS!C34 -> 14329 | C34: =PEDIDOS!D34 -> JACTANS - DISNEY | D34: =PEDIDOS!E34 -> DES-41823-Espuma de Baño infantil fco pvc x45ml | E34: =PEDIDOS!G34*PEDIDOS!H34/1000 -> 135 | F34: APROBADO | H34: Santino | I34: =EXPEDICION!K34-7 -> 46078 | J34: =PEDIDOS!M34 -> M26001
A35: =PEDIDOS!B35 -> 46071 | B35: =PEDIDOS!C35 | C35: =PEDIDOS!D35 -> BL COSMETICS | D35: =PEDIDOS!E35 -> ALISADO EXPERT | E35: =PEDIDOS!G35*PEDIDOS!H35/1000 -> 150 | F35: APROBADO | H35: Cristian | I35: =EXPEDICION!K35-7 -> 46078 | J35: =PEDIDOS!M35 -> M26007
A36: =PEDIDOS!B36 -> 46071 | B36: =PEDIDOS!C36 | C36: =PEDIDOS!D36 -> BL COSMETICS | D36: =PEDIDOS!E36 -> ALISADO EXPERT X1KG | E36: =PEDIDOS!G36*PEDIDOS!H36/1000 -> 500 | F36: APROBADO | H36: Cristian | I36: =EXPEDICION!K36-7 -> 46080 | J36: =PEDIDOS!M36 -> M26007
A37: =PEDIDOS!B37 -> 46071 | B37: =PEDIDOS!C37 | C37: =PEDIDOS!D37 -> BL COSMETICS | D37: =PEDIDOS!E37 -> ALISADO KERATIN | E37: =PEDIDOS!G37*PEDIDOS!H37/1000 -> 300 | F37: APROBADO | H37: Cristian | I37: =EXPEDICION!K37-7 -> 46083 | J37: =PEDIDOS!M37 -> M26008
... A44: =PEDIDOS!B44 -> 46071 | B44: =PEDIDOS!C44 -> TCL 2025-02-28 | C44: =PEDIDOS!D44 -> THE CHEMIST LOOK | D44: =PEDIDOS!E44 -> BOOSTER MUNAP-18 | E44: =PEDIDOS!G44*PEDIDOS!H44/1000 -> 45 | F44: APROBADO | H44: cristian | I44: =EXPEDICION!K44-7 -> 46161 | J44: =PEDIDOS!M44 -> Y26017
A45: =PEDIDOS!B45 -> 46071 | B45: =PEDIDOS!C45 -> TCL 2025-02-28 | C45: =PEDIDOS!D45 -> THE CHEMIST LOOK | D45: =PEDIDOS!E45 -> TAN BOOSTER | E45: =PEDIDOS!G45*PEDIDOS!H45/1000 -> 15 | F45: - | I45: =EXPEDICION!K45-7 -> -7 | J45: =PEDIDOS!M45
A46: =PEDIDOS!B46 -> 46071 | B46: =PEDIDOS!C46 -> TCL 2025-02-28 | C46: =PEDIDOS!D46 -> THE CHEMIST LOOK | D46: =PEDIDOS!E46 -> BOOSTER RETIN | E46: =PEDIDOS!G46*PEDIDOS!H46/1000 -> 30 | F46: APROBADO | H46: nicolas | I46: =EXPEDICION!K46-7 -> 46135 | J46: =PEDIDOS!M46 -> A26018
A47: =PEDIDOS!B47 -> 46071 | B47: =PEDIDOS!C47 -> TCL 2025-02-28 | C47: =PEDIDOS!D47 -> THE CHEMIST LOOK | D47: =PEDIDOS!E47 -> 2ND SKIN | E47: =PEDIDOS!G47*PEDIDOS!H47/1000 -> 50 | F47: - | I47: =EXPEDICION!K47-7 -> -7 | J47: =PEDIDOS!M47
A48: =PEDIDOS!B48 -> 46071 | B48: =PEDIDOS!C48 -> 14331 | C48: =PEDIDOS!D48 -> JACTANS | D48: =PEDIDOS!E48 -> JS-736 BRUMA FIJADORA FACIAL | E48: =PEDIDOS!G48*PEDIDOS!H48/1000 -> 60 | F48: APROBADO | I48: =EXPEDICION!K48-7 -> 46157 | J48: =PEDIDOS!M48 -> Y26022
A49: =PEDIDOS!B49 -> 46072 | B49: =PEDIDOS!C49 | C49: =PEDIDOS!D49 -> KALA | D49: =PEDIDOS!E49 -> AGUA DE ROSAS | E49: =PEDIDOS!G49*PEDIDOS!H49/1000 -> 58.5 | F49: APROBADO | H49: Nicolás | I49: =EXPEDICION!K49-7 -> 46079 | J49: =PEDIDOS!M49 -> F26057
A50: =PEDIDOS!B50 -> 46073 | B50: =PEDIDOS!C50 | C50: =PEDIDOS!D50 -> INTENCIONAL | D50: =PEDIDOS!E50 -> CREMA DE ORDEÑE | E50: =PEDIDOS!G50*PEDIDOS!H50/1000 -> 500 | F50: APROBADO | H50: Nicolas | I50: =EXPEDICION!K50-7 -> 46087 | J50: =PEDIDOS!M50 -> F26062
A51: =PEDIDOS!B51 -> 46073 | B51: =PEDIDOS!C51 -> P01256 | C51: =PEDIDOS!D51 -> BIOESENCIA | D51: =PEDIDOS!E51 -> CREMA BABA DE CARACOL | E51: =PEDIDOS!G51*PEDIDOS!H51/1000 -> 50 | F51: APROBADO | H51: Nicolas | I51: =EXPEDICION!K51-7 -> 46076 | J51: =PEDIDOS!M51 -> 270201
A52: =PEDIDOS!B52 -> 46042 | B52: =PEDIDOS!C52 -> P01203 | C52: =PEDIDOS!D52 -> BIOESENCIA | D52: =PEDIDOS!E52 -> SHAMPOO BABY | E52: =PEDIDOS!G52*PEDIDOS!H52/1000 -> 125 | F52: APROBADO | H52: Cristian | I52: =EXPEDICION!K52-7 -> 46066 | J52: =PEDIDOS!M52 -> F26023
A53: =PEDIDOS!B53 -> 46042 | B53: =PEDIDOS!C53 -> P01203 | C53: =PEDIDOS!D53 -> BIOESENCIA | D53: =PEDIDOS!E53 -> SERUM PROBIOTICOS | E53: =PEDIDOS!G53*PEDIDOS!H53/1000 -> 30 | F53: APROBADO | H53: Nicolas | I53: =EXPEDICION!K53-7 -> 46066 | J53: =PEDIDOS!M53 -> F26022
A54: =PEDIDOS!B54 -> 46073 | B54: =PEDIDOS!C54 | C54: =PEDIDOS!D54 -> OSSPRET | D54: =PEDIDOS!E54 -> CREMA DE ORDEÑE | E54: =PEDIDOS!G54*PEDIDOS!H54/1000 -> 300 | F54: APROBADO | H54: Cristian | I54: =EXPEDICION!K54-7 -> 46083 | J54: =PEDIDOS!M54 -> M26004 /M26013
A55: =PEDIDOS!B55 -> 46073 | B55: =PEDIDOS!C55 -> P01256 | C55: =PEDIDOS!D55 -> BIOESENCIA | D55: =PEDIDOS!E55 -> UNGUENTO PROPOLEO | E55: =PEDIDOS!G55*PEDIDOS!H55/1000 -> 70 | F55: APROBADO | H55: Nicolas | I55: =EXPEDICION!K55-7 -> 46084 | J55: =PEDIDOS!M55 -> M26018
A56: =PEDIDOS!B56 -> 46073 | B56: =PEDIDOS!C56 -> P01257 | C56: =PEDIDOS!D56 -> BIOESENCIA | D56: =PEDIDOS!E56 -> BAÑO BE KERATINA BE VEGAN | E56: =PEDIDOS!G56*PEDIDOS!H56/1000 -> 250 | F56: APROBADO | H56: Cristian | I56: =EXPEDICION!K56-7 -> 46105 | J56: =PEDIDOS!M56 -> 180302
A57: =PEDIDOS!B57 -> 46073 | B57: =PEDIDOS!C57 -> P01258 | C57: =PEDIDOS!D57 -> BIOESENCIA | D57: =PEDIDOS!E57 -> REPARADOR DE PUNTAS | E57: =PEDIDOS!G57*PEDIDOS!H57/1000 -> 30 | F57: APROBADO | H57: Nicolas | I57: =EXPEDICION!K57-7 -> 46176 | J57: =PEDIDOS!M57 -> 100601
A58: =PEDIDOS!B58 -> 46073 | B58: =PEDIDOS!C58 -> P01259 | C58: =PEDIDOS!D58 -> BIOESENCIA | D58: =PEDIDOS!E58 -> BRUMA FACIAL ORIGENES | E58: =PEDIDOS!G58*PEDIDOS!H58/1000 -> 125 | F58: APROBADO | H58: Nicolás | I58: =EXPEDICION!K58-7 -> 46092 | J58: =PEDIDOS!M58 -> 130302
A59: =PEDIDOS!B59 -> 46073 | B59: =PEDIDOS!C59 -> P01260 | C59: =PEDIDOS!D59 -> BIOESENCIA | D59: =PEDIDOS!E59 -> EMULSION CORPORAL PROBIOTICOS | E59: =PEDIDOS!G59*PEDIDOS!H59/1000 -> 200 | F59: APROBADO | H59: Cristian | I59: =EXPEDICION!K59-7 -> 46092 | J59: =PEDIDOS!M59 -> M26059
A60: =PEDIDOS!B60 -> 46073 | B60: =PEDIDOS!C60 -> P01261 | C60: =PEDIDOS!D60 -> BIOESENCIA | D60: =PEDIDOS!E60 -> CREMA DIA/NOCHE ULTRAHIDRATANTE VEGAN | E60: =PEDIDOS!G60*PEDIDOS!H60/1000 -> 50 | F60: APROBADO | H60: Nicolas | I60: =EXPEDICION!K60-7 -> 46087 | J60: =PEDIDOS!M60 -> 120301
... A71: =PEDIDOS!B71 -> 46076 | B71: =PEDIDOS!C71 -> 775 | C71: =PEDIDOS!D71 -> CAV | D71: =PEDIDOS!E71 -> Finishing C-Plex CAV x 500 ml (Paso 2) | E71: =PEDIDOS!G71*PEDIDOS!H71/1000 -> 200 | F71: APROBADO | H71: Cristian | I71: =EXPEDICION!K71-7 -> 46094 | J71: =PEDIDOS!M71 -> M26061
A72: =PEDIDOS!B72 -> 46077 | B72: =PEDIDOS!C72 -> 1704 | C72: =PEDIDOS!D72 -> LABORATORIO ONCE | D72: =PEDIDOS!E72 -> ALBA SERUM X 30 ML DRA ROSSI | E72: =PEDIDOS!G72*PEDIDOS!H72/1000 -> 9 | F72: APROBADO | I72: =EXPEDICION!K72-7 -> -7 | J72: =PEDIDOS!M72
A73: =PEDIDOS!B73 -> 46078 | B73: =PEDIDOS!C73 | C73: =PEDIDOS!D73 -> UNICA | D73: =PEDIDOS!E73 -> CREMA CORPORAL HUMECTANTE KARITE | E73: =PEDIDOS!G73*PEDIDOS!H73/1000 -> 140 | F73: APROBADO | H73: Cristian | I73: =EXPEDICION!K73-7 -> 46094 | J73: =PEDIDOS!M73 -> 110301
A74: =PEDIDOS!B74 -> 46078 | B74: =PEDIDOS!C74 | C74: =PEDIDOS!D74 -> OLANN | D74: =PEDIDOS!E74 -> Serum hialurónico 30 ml | E74: =PEDIDOS!G74*PEDIDOS!H74/1000 -> 7.5 | F74: APROBADO | H74: Cristian | I74: =EXPEDICION!K74-7 -> 46129 | J74: =PEDIDOS!M74 -> M26065
A75: =PEDIDOS!B75 -> 46078 | B75: =PEDIDOS!C75 | C75: =PEDIDOS!D75 -> OLANN | D75: =PEDIDOS!E75 -> BRUMA FACIAL | E75: =PEDIDOS!G75*PEDIDOS!H75/1000 -> 25 | F75: APROBADO | H75: Cristian | I75: =EXPEDICION!K75-7 -> 46129 | J75: =PEDIDOS!M75 -> M26060
A76: =PEDIDOS!B76 -> 46078 | B76: =PEDIDOS!C76 | C76: =PEDIDOS!D76 -> OLANN | D76: =PEDIDOS!E76 -> CREMA FACIAL DE DIA ULTRAHUMECTANTE | E76: =PEDIDOS!G76*PEDIDOS!H76/1000 -> 7.5 | F76: APROBADO | H76: Cristian | I76: =EXPEDICION!K76-7 -> 46111 | J76: =PEDIDOS!M76 -> M26031
A77: =PEDIDOS!B77 -> 46078 | B77: =PEDIDOS!C77 | C77: =PEDIDOS!D77 -> OLANN | D77: =PEDIDOS!E77 -> CREMA FACIAL DE NOCHE TENSORA | E77: =PEDIDOS!G77*PEDIDOS!H77/1000 -> 7.5 | F77: APROBADO | H77: Cristian | I77: =EXPEDICION!K77-7 -> 46111 | J77: =PEDIDOS!M77 -> M26032
A78: =PEDIDOS!B78 -> 46078 | B78: =PEDIDOS!C78 | C78: =PEDIDOS!D78 -> OLANN | D78: =PEDIDOS!E78 -> CONTORNO DE OJOS | E78: =PEDIDOS!G78*PEDIDOS!H78/1000 -> 7.5 | F78: APROBADO | H78: Nicolas | I78: =EXPEDICION!K78-7 -> 46129 | J78: =PEDIDOS!M78 -> M26033
A79: =PEDIDOS!B79 -> 46083 | B79: =PEDIDOS!C79 | C79: =PEDIDOS!D79 -> ECODERM - AGUAZU | D79: =PEDIDOS!E79 -> ESPUMA DE BAÑO ADULTO | E79: =PEDIDOS!G79*PEDIDOS!H79/1000 -> 40 | F79: APROBADO | H79: Cristian | I79: =EXPEDICION!K79-7 -> 46092 | J79: =PEDIDOS!M79 -> M26034
A80: =PEDIDOS!B80 -> 46083 | B80: =PEDIDOS!C80 | C80: =PEDIDOS!D80 -> ECODERM - AGUAZU | D80: =PEDIDOS!E80 -> ESPUMA DE BAÑO BALLENA | E80: =PEDIDOS!G80*PEDIDOS!H80/1000 -> 40 | F80: APROBADO | H80: Cristian | I80: =EXPEDICION!K80-7 -> 46092 | J80: =PEDIDOS!M80 -> M26034
A81: =PEDIDOS!B81 -> 46083 | B81: =PEDIDOS!C81 | C81: =PEDIDOS!D81 -> ECODERM - AGUAZU | D81: =PEDIDOS!E81 -> ESPUMA DE BAÑO BALLENA X500 | E81: =PEDIDOS!G81*PEDIDOS!H81/1000 -> 50 | F81: APROBADO | H81: Cristian | I81: =EXPEDICION!K81-7 -> 46092 | J81: =PEDIDOS!M81 -> M26034
A82: =PEDIDOS!B82 -> 46083 | B82: =PEDIDOS!C82 | C82: =PEDIDOS!D82 -> ECODERM - AGUAZU | D82: =PEDIDOS!E82 -> ESPUMA DE BAÑO ADULTO X500 | E82: =PEDIDOS!G82*PEDIDOS!H82/1000 -> 50 | F82: APROBADO | H82: Cristian | I82: =EXPEDICION!K82-7 -> 46092 | J82: =PEDIDOS!M82 -> M26034
A83: =PEDIDOS!B83 -> 46083 | B83: =PEDIDOS!C83 | C83: =PEDIDOS!D83 -> ECODERM - AGUAZU | D83: =PEDIDOS!E83 -> BALSAMO HERBAL | E83: =PEDIDOS!G83*PEDIDOS!H83/1000 -> 9 | F83: APROBADO | H83: Nicolás | I83: =EXPEDICION!K83-7 -> 46092 | J83: =PEDIDOS!M83 -> M26044
A84: =PEDIDOS!B84 -> 46083 | B84: =PEDIDOS!C84 | C84: =PEDIDOS!D84 -> ECODERM - DUGA | D84: =PEDIDOS!E84 -> ACONDICIONADOR INFANTIL | E84: =PEDIDOS!G84*PEDIDOS!H84/1000 -> 37.5 | F84: APROBADO | H84: Nicolas | I84: =EXPEDICION!K84-7 -> 46100 | J84: =PEDIDOS!M84 -> M26078
... A120: =PEDIDOS!B120 -> 46076 | B120: =PEDIDOS!C120 -> 1716 | C120: =PEDIDOS!D120 -> LABORATORIO ONCE | D120: =PEDIDOS!E120 -> SERUM CONCENTRADO AH | E120: =PEDIDOS!G120*PEDIDOS!H120/1000 -> 45 | F120: APROBADO | H120: Nicolás | I120: =EXPEDICION!K120-7 -> 46094 | J120: =PEDIDOS!M120 -> M26063
A121: =PEDIDOS!B121 -> 46076 | B121: =PEDIDOS!C121 -> 1715 | C121: =PEDIDOS!D121 -> LABORATORIO ONCE | D121: =PEDIDOS!E121 -> GEL UNIESFERAS VITAMINA C | E121: =PEDIDOS!G121*PEDIDOS!H121/1000 -> 100 | F121: APROBADO | I121: =EXPEDICION!K121-7 -> 46090 | J121: =PEDIDOS!M121 -> F26061
A122: =PEDIDOS!B122 -> 46168 | B122: =PEDIDOS!C122 | C122: =PEDIDOS!D122 -> AGUEDA REY - IHC CAPILARES | D122: =PEDIDOS!E122 -> Shampoo Fortalecedor Anticaida D: 250203-3 | E122: =PEDIDOS!G122*PEDIDOS!H122/1000 -> 200 | F122: APROBADO | H122: Cristian | I122: =EXPEDICION!K122-7 -> 46170 | J122: =PEDIDOS!M122 -> A26025
A123: =PEDIDOS!B123 -> 46168 | B123: =PEDIDOS!C123 | C123: =PEDIDOS!D123 -> AGUEDA REY - IHC CAPILARES | D123: =PEDIDOS!E123 -> Shampoo Anti Caspa D250204-3 | E123: =PEDIDOS!G123*PEDIDOS!H123/1000 -> 200 | F123: APROBADO | H123: Cristian | I123: =EXPEDICION!K123-7 -> 46170 | J123: =PEDIDOS!M123 -> A26026
A124: =PEDIDOS!B124 -> 46168 | B124: =PEDIDOS!C124 | C124: =PEDIDOS!D124 -> AGUEDA REY - IHC CAPILARES | D124: =PEDIDOS!E124 -> Shampoo Anti Sebo D250205-3 | E124: =PEDIDOS!G124*PEDIDOS!H124/1000 -> 200 | F124: APROBADO | H124: Cristian | I124: =EXPEDICION!K124-7 -> 46170 | J124: =PEDIDOS!M124 -> A26024
A125: =PEDIDOS!B125 -> 46168 | B125: =PEDIDOS!C125 | C125: =PEDIDOS!D125 -> AGUEDA REY - IHC CAPILARES | D125: =PEDIDOS!E125 -> Shampo Engrosador D250210-3 | E125: =PEDIDOS!G125*PEDIDOS!H125/1000 -> 200 | F125: APROBADO | H125: Cristian | I125: =EXPEDICION!K125-7 -> 46170 | J125: =PEDIDOS!M125 -> A26041
A126: =PEDIDOS!B126 -> 46168 | B126: =PEDIDOS!C126 | C126: =PEDIDOS!D126 -> AGUEDA REY - IHC CAPILARES | D126: =PEDIDOS!E126 -> Acondicionador Biotina D: 250207-3 | E126: =PEDIDOS!G126*PEDIDOS!H126/1000 -> 200 | F126: APROBADO | H126: Nicolas | I126: =EXPEDICION!K126-7 -> 46170 | J126: =PEDIDOS!M126 -> A26040
A127: =PEDIDOS!B127 -> 46162 | B127: =PEDIDOS!C127 | C127: =PEDIDOS!D127 -> LABORATORIO ONCE | D127: =PEDIDOS!E127 -> SERUM HOME PEEL SERUM PEPITAS DE UVA | E127: =PEDIDOS!G127*PEDIDOS!H127/1000 -> 30 | F127: APROBADO | H127: Cristian | I127: =EXPEDICION!K127-7 -> 46170 | J127: =PEDIDOS!M127 -> A26010
A128: =PEDIDOS!B128 -> 46097 | B128: =PEDIDOS!C128 | C128: =PEDIDOS!D128 -> BL COSMETICS | D128: =PEDIDOS!E128 -> GEL ANTIFRIZZ | E128: =PEDIDOS!G128*PEDIDOS!H128/1000 -> 13.5 | F128: APROBADO | H128: Nicolas | I128: =EXPEDICION!K128-7 -> 46134 | J128: =PEDIDOS!M128 -> A26043
A129: =PEDIDOS!B129 -> 46097 | B129: =PEDIDOS!C129 | C129: =PEDIDOS!D129 -> BL COSMETICS | D129: =PEDIDOS!E129 -> SHAMPOO CONTROL LISS | E129: =PEDIDOS!G129*PEDIDOS!H129/1000 -> 900 | F129: APROBADO | H129: Cristian | I129: =EXPEDICION!K129-7 -> 46121 | J129: =PEDIDOS!M129 -> M26098
A130: =PEDIDOS!B130 -> 46097 | B130: =PEDIDOS!C130 | C130: =PEDIDOS!D130 -> BL COSMETICS | D130: =PEDIDOS!E130 -> ACONDICIONADOR CONTROL LISS | E130: =PEDIDOS!G130*PEDIDOS!H130/1000 -> 900 | F130: APROBADO | H130: Cristian | I130: =EXPEDICION!K130-7 -> 46121 | J130: =PEDIDOS!M130 -> M26099
A131: =PEDIDOS!B131 -> 46097 | B131: =PEDIDOS!C131 | C131: =PEDIDOS!D131 -> BL COSMETICS | D131: =PEDIDOS!E131 -> SERUM ARGAN (nuevo) | E131: =PEDIDOS!G131*PEDIDOS!H131/1000 -> 90 | F131: APROBADO | H131: Nicolas | I131: =EXPEDICION!K131-7 -> 46122 | J131: =PEDIDOS!M131 -> A26042
A132: =PEDIDOS!B132 -> 46098 | B132: =PEDIDOS!C132 | C132: =PEDIDOS!D132 -> AGUEDA REY - IKIGAI | D132: =PEDIDOS!E132 -> Serum VITAMINA C Cod 230345 | E132: =PEDIDOS!G132*PEDIDOS!H132/1000 -> 30 | F132: APROBADO | H132: Nicolas | I132: =EXPEDICION!K132-7 -> 46140 | J132: =PEDIDOS!M132 -> A26091
A133: =PEDIDOS!B133 -> 46098 | B133: =PEDIDOS!C133 | C133: =PEDIDOS!D133 -> ORIGINAL BLACK | D133: =PEDIDOS!E133 -> AFTER SHAVE VIOLETA | E133: =PEDIDOS!G133*PEDIDOS!H133/1000 -> 3200 | F133: APROBADO | H133: Nicolas | I133: =EXPEDICION!K133-7 -> -7 | J133: =PEDIDOS!M133
... A184: =PEDIDOS!B184 -> 46112 | B184: =PEDIDOS!C184 -> 15226 | C184: =PEDIDOS!D184 -> THELMA Y LOUISE | D184: =PEDIDOS!E184 -> SANITIZANTE ROSA - FRUTILLA | E184: =PEDIDOS!G184*PEDIDOS!H184/1000 -> 45 | F184: APROBADO | H184: cristian | I184: =EXPEDICION!K184-7 -> 46149 | J184: =PEDIDOS!M184
A185: =PEDIDOS!B185 -> 46113 | B185: =PEDIDOS!C185 -> 14362 | C185: =PEDIDOS!D185 -> JACTANS - DISNEY | D185: =PEDIDOS!E185 -> DP-50051-Perfume infantil fco mini goya x5ml 1980AN | E185: =PEDIDOS!G185*PEDIDOS!H185/1000 -> 5 | F185: - | I185: =EXPEDICION!K185-7 -> -7 | J185: =PEDIDOS!M185
A186: =PEDIDOS!B186 -> 46113 | B186: =PEDIDOS!C186 -> 14362 | C186: =PEDIDOS!D186 -> JACTANS - DISNEY | D186: =PEDIDOS!E186 -> DP-50068-Perfume infantil fco mini goya x5ml 0297TS | E186: =PEDIDOS!G186*PEDIDOS!H186/1000 -> 5 | F186: - | I186: =EXPEDICION!K186-7 -> -7 | J186: =PEDIDOS!M186
A187: =PEDIDOS!B187 -> 46113 | B187: =PEDIDOS!C187 -> 14362 | C187: =PEDIDOS!D187 -> JACTANS - DISNEY | D187: =PEDIDOS!E187 -> DP-50082-Perfume infantil fco mini goya x5ml 0280BD | E187: =PEDIDOS!G187*PEDIDOS!H187/1000 -> 5 | F187: - | I187: =EXPEDICION!K187-7 -> -7 | J187: =PEDIDOS!M187
A188: =PEDIDOS!B188 -> 46113 | B188: =PEDIDOS!C188 -> 14362 | C188: =PEDIDOS!D188 -> JACTANS - DISNEY | D188: =PEDIDOS!E188 -> DP-50099-Perfume infantil fco mini goya x5ml 0296LS | E188: =PEDIDOS!G188*PEDIDOS!H188/1000 -> 5 | F188: - | I188: =EXPEDICION!K188-7 -> -7 | J188: =PEDIDOS!M188
A189: =PEDIDOS!B189 -> 46113 | B189: =PEDIDOS!C189 -> 14362 | C189: =PEDIDOS!D189 -> JACTANS - DISNEY | D189: =PEDIDOS!E189 -> DP-50846-Perf inf fco Frutilla roja x50ml 0390FR | E189: =PEDIDOS!G189*PEDIDOS!H189/1000 -> 100 | F189: APROBADO | H189: cristian | I189: =EXPEDICION!K189-7 -> 46190 | J189: =PEDIDOS!M189 -> J26015
A190: =PEDIDOS!B190 -> 46113 | B190: =PEDIDOS!C190 -> 14362 | C190: =PEDIDOS!D190 -> JACTANS - DISNEY | D190: =PEDIDOS!E190 -> DP-50853-Perfume infantil fco True star x50ml 0368CT | E190: =PEDIDOS!G190*PEDIDOS!H190/1000 -> 75 | F190: - | I190: =EXPEDICION!K190-7 -> 46195 | J190: =PEDIDOS!M190 -> J26041
A191: =PEDIDOS!B191 -> 46113 | B191: =PEDIDOS!C191 -> 14362 | C191: =PEDIDOS!D191 -> JACTANS - DISNEY | D191: =PEDIDOS!E191 -> DP-50624-Perf inf Fco manzanita roja x25ml 0364AL | E191: =PEDIDOS!G191*PEDIDOS!H191/1000 -> 37.5 | F191: APROBADO | H191: cristian | I191: =EXPEDICION!K191-7 -> 46154 | J191: =PEDIDOS!M191 -> A26084
A192: =PEDIDOS!B192 -> 46113 | B192: =PEDIDOS!C192 -> 14362 | C192: =PEDIDOS!D192 -> JACTANS - DISNEY | D192: =PEDIDOS!E192 -> DP-50990-Perfume inf. fco Mariana x50ml 0369RD | E192: =PEDIDOS!G192*PEDIDOS!H192/1000 -> 100 | F192: APROBADO | H192: nicolas | I192: =EXPEDICION!K192-7 -> 46132 | J192: =PEDIDOS!M192 -> A26080
A193: =PEDIDOS!B193 -> 46113 | B193: =PEDIDOS!C193 -> 14362 | C193: =PEDIDOS!D193 -> JACTANS - DISNEY | D193: =PEDIDOS!E193 -> DP-1943-Perfume inf. Fco Candela x50ml 0301BG | E193: =PEDIDOS!G193*PEDIDOS!H193/1000 -> 75 | F193: APROBADO | H193: cristian | I193: =EXPEDICION!K193-7 -> 46174 | J193: =PEDIDOS!M193 -> Y26067
A194: =PEDIDOS!B194 -> 46113 | B194: =PEDIDOS!C194 -> 14362 | C194: =PEDIDOS!D194 -> JACTANS - DISNEY | D194: =PEDIDOS!E194 -> DP-50617-Perfume inf. fco silueta pvc x45ml 0368PB | E194: =PEDIDOS!G194*PEDIDOS!H194/1000 -> 67.5 | F194: APROBADO | H194: cristian | I194: =EXPEDICION!K194-7 -> 46147 | J194: =PEDIDOS!M194 -> Y26007
A195: =PEDIDOS!B195 -> 46113 | B195: =PEDIDOS!C195 -> 14362 | C195: =PEDIDOS!D195 -> JACTANS - DISNEY | D195: =PEDIDOS!E195 -> DP-50815-Perfume inf. fco silueta pvc x45ML 0367AG | E195: =PEDIDOS!G195*PEDIDOS!H195/1000 -> 67.5 | F195: APROBADO | H195: cristian | I195: =EXPEDICION!K195-7 -> 46148 | J195: =PEDIDOS!M195 -> Y26008
A196: =PEDIDOS!B196 -> 46113 | B196: =PEDIDOS!C196 -> 14362 | C196: =PEDIDOS!D196 -> JACTANS - DISNEY | D196: =PEDIDOS!E196 -> DP-50853-Perfume infantil fco True star x50ml 0368CT | E196: =PEDIDOS!G196*PEDIDOS!H196/1000 -> 100 | F196: APROBADO | H196: cristian | I196: =EXPEDICION!K196-7 -> 46169 | J196: =PEDIDOS!M196 -> Y26066
A197: =PEDIDOS!B197 -> 46113 | B197: =PEDIDOS!C197 -> 14362 | C197: =PEDIDOS!D197 -> JACTANS - DISNEY | D197: =PEDIDOS!E197 -> DP-50891-Perfume inf Fco penelope x50ml 0390FR | E197: =PEDIDOS!G197*PEDIDOS!H197/1000 -> 100 | F197: APROBADO | H197: cristian | I197: =EXPEDICION!K197-7 -> 46182 | J197: =PEDIDOS!M197 -> J26016
A198: =PEDIDOS!B198 -> 46113 | B198: =PEDIDOS!C198 | C198: =PEDIDOS!D198 -> BLE LIPS | D198: =PEDIDOS!E198 -> LIP INJECTION | E198: =PEDIDOS!G198*PEDIDOS!H198/1000 -> 2.7 | F198: APROBADO | H198: Natalia | I198: =EXPEDICION!K198-7 -> 46127 | J198: =PEDIDOS!M198 -> A26047
A199: =PEDIDOS!B199 -> 46113 | B199: =PEDIDOS!C199 | C199: =PEDIDOS!D199 -> BLE LIPS | D199: =PEDIDOS!E199 -> LIP INJECTION | E199: =PEDIDOS!G199*PEDIDOS!H199/1000 -> 2.7 | F199: APROBADO | H199: Natalia | I199: =EXPEDICION!K199-7 -> 46149 | J199: =PEDIDOS!M199 -> A26088
A200: =PEDIDOS!B200 -> 46119 | B200: =PEDIDOS!C200 | C200: =PEDIDOS!D200 -> BIOESENCIA | D200: =PEDIDOS!E200 -> AGUA MICELAR PROBIOTICS | E200: =PEDIDOS!G200*PEDIDOS!H200/1000 -> 200 | F200: APROBADO | H200: Santino | I200: =EXPEDICION!K200-7 -> 46132 | J200: =PEDIDOS!M200 -> A26032
A201: =PEDIDOS!B201 -> 46119 | B201: =PEDIDOS!C201 | C201: =PEDIDOS!D201 -> BIOESENCIA | D201: =PEDIDOS!E201 -> CREMA FACIAL PROBIOTICS | E201: =PEDIDOS!G201*PEDIDOS!H201/1000 -> 50 | F201: APROBADO | H201: Santino | I201: =EXPEDICION!K201-7 -> 46127 | J201: =PEDIDOS!M201 -> A26044
A202: =PEDIDOS!B202 -> 46119 | B202: =PEDIDOS!C202 | C202: =PEDIDOS!D202 -> BIOESENCIA | D202: =PEDIDOS!E202 -> CREMA EXFOLIANTE PROBIOTICS | E202: =PEDIDOS!G202*PEDIDOS!H202/1000 -> 50 | F202: APROBADO | H202: Cristian | I202: =EXPEDICION!K202-7 -> 46162 | J202: =PEDIDOS!M202 -> A26044
... A240: =PEDIDOS!B240 -> 46127 | B240: =PEDIDOS!C240 -> 15255 | C240: =PEDIDOS!D240 -> THELMA Y LOUISE | D240: =PEDIDOS!E240 -> AGUA TERMAL | E240: =PEDIDOS!G240*PEDIDOS!H240/1000 -> 504 | F240: APROBADO | H240: Nicolás | I240: =EXPEDICION!K240-7 -> 46154 | J240: =PEDIDOS!M240 -> Y26026
A241: =PEDIDOS!B241 -> 46127 | B241: =PEDIDOS!C241 -> 15255 | C241: =PEDIDOS!D241 -> THELMA Y LOUISE | D241: =PEDIDOS!E241 -> DESENRREDANTE BIFASICO | E241: =PEDIDOS!G241*PEDIDOS!H241/1000 -> 336 | F241: APROBADO | I241: =EXPEDICION!K241-7 -> 46146 | J241: =PEDIDOS!M241 -> Y26016
A242: =PEDIDOS!B242 -> 46127 | B242: =PEDIDOS!C242 | C242: =PEDIDOS!D242 -> ECODERM - DUGA | D242: =PEDIDOS!E242 -> SHAMPOO INFANTIL | E242: =PEDIDOS!G242*PEDIDOS!H242/1000 -> 60 | F242: APROBADO | H242: Nicolas | I242: =EXPEDICION!K242-7 -> 46135 | J242: =PEDIDOS!M242 -> A26038
A243: =PEDIDOS!B243 -> 46127 | B243: =PEDIDOS!C243 | C243: =PEDIDOS!D243 -> ECODERM - DUGA | D243: =PEDIDOS!E243 -> CREMA INFANTIL | E243: =PEDIDOS!G243*PEDIDOS!H243/1000 -> 60 | F243: APROBADO | H243: Nicolas | I243: =EXPEDICION!K243-7 -> 46135 | J243: =PEDIDOS!M243 -> A26033
A244: =PEDIDOS!B244 -> 46129 | B244: =PEDIDOS!C244 | C244: =PEDIDOS!D244 -> LUCENT | D244: =PEDIDOS!E244 -> CREMA HANDS AND FEET | E244: =PEDIDOS!G244*PEDIDOS!H244/1000 -> 125 | F244: APROBADO | H244: Nicolas | I244: =EXPEDICION!K244-7 -> 46134 | J244: =PEDIDOS!M244 -> A26087
...

Sheet EXPEDICION
A1: Nº | B1: Fecha | C1: N° OC | D1: CLIENTE | E1: PRODUCTO | F1: Q PEDIDA | G1: Q envasada | H1: S | I1: Nv Svcio | J1: CANTIDAD CAJAS | K1: FECHA | L1: ESTADO | M1: N° DE LOTE | N1: N° REMITO | O1: OBSERVACIÓN
A2: =PEDIDOS!A2 -> 25293 | B2: =PEDIDOS!B2 -> 46035 | C2: =PEDIDOS!C2 -> 163 | D2: =PEDIDOS!D2 -> THE MINIMAL CO | E2: =PEDIDOS!E2 -> MILKY TONER | F2: =PEDIDOS!G2 -> 900 | G2: =25*35+24 -> 899 | H2: =PEDIDOS!F2 -> P | I2: =IF(G2<>"",-(F2-G2)/F2+1, "") -> 0.99888889 | J2: 25 x 35u + 1 x 24u | K2: 46076 | L2: =IF(N2<>"","ENTREGADO",IF(K2<>"","LISTO PARA ENTREGAR","EN PROCESO" )) -> ENTREGADO | M2: F26021 | N2: 3351
A3: =PEDIDOS!A3 -> 25294 | B3: =PEDIDOS!B3 -> 46035 | C3: =PEDIDOS!C3 -> 14297 | D3: =PEDIDOS!D3 -> JACTANS | E3: =PEDIDOS!E3 -> JS-941 AGUA MICELAR BIFASCIA | F3: =PEDIDOS!G3 -> 1000 | G3: 1011 | H3: =PEDIDOS!F3 -> P | I3: =IF(G3<>"",-(F3-G3)/F3+1, "") -> 1.011 | J3: 50X20 1X11 | K3: 46080 | L3: =IF(N3<>"","ENTREGADO",IF(K3<>"","LISTO PARA ENTREGAR","EN PROCESO" )) -> ENTREGADO | M3: F26031 | N3: 3376
A4: =PEDIDOS!A4 -> 25295 | B4: =PEDIDOS!B4 -> 46035 | C4: =PEDIDOS!C4 -> 15074 | D4: =PEDIDOS!D4 -> THELMA Y LOUISE | E4: =PEDIDOS!E4 -> AGUA TERMAL | F4: =PEDIDOS!G4 -> 2940 | G4: 2912 | H4: =PEDIDOS!F4 -> P | I4: =IF(G4<>"",-(F4-G4)/F4+1, "") -> 0.99047619 | J4: 64x45 1x32 | K4: 46083 | L4: =IF(N4<>"","ENTREGADO",IF(K4<>"","LISTO PARA ENTREGAR","EN PROCESO" )) -> ENTREGADO | M4: F26041 | N4: 3368
A5: =PEDIDOS!A5 -> 25296 | B5: =PEDIDOS!B5 -> 46035 | C5: =PEDIDOS!C5 | D5: =PEDIDOS!D5 -> LIORA | E5: =PEDIDOS!E5 -> CREMA PARA PEINAR RULOS | F5: =PEDIDOS!G5 -> 170 | G5: 147 | H5: =PEDIDOS!F5 -> P | I5: =IF(G5<>"",-(F5-G5)/F5+1, "") -> 0.86470588 | J5: 7X21U | K5: 46161 | L5: =IF(N5<>"","ENTREGADO",IF(K5<>"","LISTO PARA ENTREGAR","EN PROCESO" )) -> ENTREGADO | M5: Y26039 | N5: 3496
A6: =PEDIDOS!A6 -> 25298 | B6: =PEDIDOS!B6 -> 46042 | C6: =PEDIDOS!C6 -> P01203 | D6: =PEDIDOS!D6 -> BIOESENCIA | E6: =PEDIDOS!E6 -> SERUM ORIGENES | F6: =PEDIDOS!G6 -> 1600 | G6: =6*220+79+203 -> 1602 | H6: =PEDIDOS!F6 -> P | I6: =IF(G6<>"",-(F6-G6)/F6+1, "") -> 1.00125 | J6: 6 x 220u + 1 x 79 / 1 x 203u | K6: 46077 | L6: =IF(N6<>"","ENTREGADO",IF(K6<>"","LISTO PARA ENTREGAR","EN PROCESO" )) -> ENTREGADO | M6: 240201 | N6: 240226 /310326
A7: =PEDIDOS!A7 -> 25299 | B7: =PEDIDOS!B7 -> 46042 | C7: =PEDIDOS!C7 | D7: =PEDIDOS!D7 -> WSABI | E7: =PEDIDOS!E7 -> SERUM INTIMO | F7: =PEDIDOS!G7 -> 300 | G7: 293 | H7: =PEDIDOS!F7 -> P | I7: =IF(G7<>"",-(F7-G7)/F7+1, "") -> 0.97666667 | J7: 8X34 1X21 | K7: 46087 | L7: =IF(N7<>"","ENTREGADO",IF(K7<>"","LISTO PARA ENTREGAR","EN PROCESO" )) -> ENTREGADO | M7: F26049 | N7: 3371
A8: =PEDIDOS!A8 -> 25300 | B8: =PEDIDOS!B8 -> 46042 | C8: =PEDIDOS!C8 | D8: =PEDIDOS!D8 -> MERMER | E8: =PEDIDOS!E8 -> ACEITE CORPORAL LAVANDA | F8: =PEDIDOS!G8 -> 300 | G8: 509 | H8: =PEDIDOS!F8 -> P | I8: =IF(G8<>"",-(F8-G8)/F8+1, "") -> 1.6966667 | J8: 16 x 30u + 1 x 29u | K8: 46050 | L8: =IF(N8<>"","ENTREGADO",IF(K8<>"","LISTO PARA ENTREGAR","EN PROCESO" )) -> ENTREGADO | M8: E26087 | N8: 2997
A9: =PEDIDOS!A9 -> 25300 | B9: =PEDIDOS!B9 -> 46042 | C9: =PEDIDOS!C9 | D9: =PEDIDOS!D9 -> MERMER | E9: =PEDIDOS!E9 -> ACEITE CORPORAL ALMENDRA | F9: =PEDIDOS!G9 -> 300 | G9: 306 | H9: =PEDIDOS!F9 -> P | I9: =IF(G9<>"",-(F9-G9)/F9+1, "") -> 1.02 | J9: 17X18 | K9: 46050 | L9: =IF(N9<>"","ENTREGADO",IF(K9<>"","LISTO PARA ENTREGAR","EN PROCESO" )) -> ENTREGADO | M9: E26088 | N9: 2997
A10: =PEDIDOS!A10 -> 25300 | B10: =PEDIDOS!B10 -> 46042 | C10: =PEDIDOS!C10 | D10: =PEDIDOS!D10 -> MERMER | E10: =PEDIDOS!E10 -> ACEITE CORPORAL ROSAS | F10: =PEDIDOS!G10 -> 300 | G10: 303 | H10: =PEDIDOS!F10 -> P | I10: =IF(G10<>"",-(F10-G10)/F10+1, "") -> 1.01 | J10: 16X18 1X15 | K10: 46050 | L10: =IF(N10<>"","ENTREGADO",IF(K10<>"","LISTO PARA ENTREGAR","EN PROCESO" )) -> ENTREGADO | M10: E26089 | N10: 2997
A11: =PEDIDOS!A11 -> 25300 | B11: =PEDIDOS!B11 -> 46042 | C11: =PEDIDOS!C11 | D11: =PEDIDOS!D11 -> MERMER | E11: =PEDIDOS!E11 -> ACEITE CORPORAL SESAMO | F11: =PEDIDOS!G11 -> 300 | G11: 312 | H11: =PEDIDOS!F11 -> P | I11: =IF(G11<>"",-(F11-G11)/F11+1, "") -> 1.04 | J11: 17X18 1X6 | K11: 46050 | L11: =IF(N11<>"","ENTREGADO",IF(K11<>"","LISTO PARA ENTREGAR","EN PROCESO" )) -> ENTREGADO | M11: E26090 | N11: 2997
A12: =PEDIDOS!A12 -> 25300 | B12: =PEDIDOS!B12 -> 46042 | C12: =PEDIDOS!C12 | D12: =PEDIDOS!D12 -> MERMER | E12: =PEDIDOS!E12 -> ACEITE CORPORAL INCIENSO | F12: =PEDIDOS!G12 -> 300 | G12: 306 | H12: =PEDIDOS!F12 -> P | I12: =IF(G12<>"",-(F12-G12)/F12+1, "") -> 1.02 | J12: 17X18 | K12: 46050 | L12: =IF(N12<>"","ENTREGADO",IF(K12<>"","LISTO PARA ENTREGAR","EN PROCESO" )) -> ENTREGADO | M12: E26091 | N12: 2997
A13: =PEDIDOS!A13 -> 25300 | B13: =PEDIDOS!B13 -> 46042 | C13: =PEDIDOS!C13 | D13: =PEDIDOS!D13 -> MERMER | E13: =PEDIDOS!E13 -> ACEITE CORPORAL ARNICA | F13: =PEDIDOS!G13 -> 300 | G13: 304 | H13: =PEDIDOS!F13 -> P | I13: =IF(G13<>"",-(F13-G13)/F13+1, "") -> 1.0133333 | J13: 16X18 1X16 | K13: 46050 | L13: =IF(N13<>"","ENTREGADO",IF(K13<>"","LISTO PARA ENTREGAR","EN PROCESO" )) -> ENTREGADO | M13: E26092 | N13: 2997
A14: =PEDIDOS!A14 -> 25300 | B14: =PEDIDOS!B14 -> 46042 | C14: =PEDIDOS!C14 | D14: =PEDIDOS!D14 -> MERMER | E14: =PEDIDOS!E14 -> LOCION CAPILAR | F14: =PEDIDOS!G14 -> 400 | G14: =8*46+32 -> 400 | H14: =PEDIDOS!F14 -> P | I14: =IF(G14<>"",-(F14-G14)/F14+1, "") -> 1 | J14: 8 x 46 + 1 x 32 | K14: 46111 | L14: =IF(N14<>"","ENTREGADO",IF(K14<>"","LISTO PARA ENTREGAR","EN PROCESO" )) -> ENTREGADO | M14: M26042 | N14: 4312
A15: =PEDIDOS!A15 -> 25300 | B15: =PEDIDOS!B15 -> 46042 | C15: =PEDIDOS!C15 | D15: =PEDIDOS!D15 -> MERMER | E15: =PEDIDOS!E15 -> SERUM CAPILAR | F15: =PEDIDOS!G15 -> 400 | G15: =9*45+10 -> 415 | H15: =PEDIDOS!F15 -> P | I15: =IF(G15<>"",-(F15-G15)/F15+1, "") -> 1.0375 | J15: 9 x 45 + 1 x 10 | K15: 46112 | L15: =IF(N15<>"","ENTREGADO",IF(K15<>"","LISTO PARA ENTREGAR","EN PROCESO" )) -> ENTREGADO | M15: M26030 | N15: 3412
A16: =PEDIDOS!A16 -> 25301 | B16: =PEDIDOS!B16 -> 46049 | C16: =PEDIDOS!C16 -> 1708 | D16: =PEDIDOS!D16 -> LABORATORIO ONCE | E16: =PEDIDOS!E16 -> SERUM ACIDO HIALURONICO + NIACINAMIDA | F16: =PEDIDOS!G16 -> 1653 | G16: 1549 | H16: =PEDIDOS!F16 -> P | I16: =IF(G16<>"",-(F16-G16)/F16+1, "") -> 0.93708409 | J16: 17X90U Y 1X19U | K16: 46083 | L16: =IF(N16<>"","ENTREGADO",IF(K16<>"","LISTO PARA ENTREGAR","EN PROCESO" )) -> ENTREGADO | M16: F26048 | N16: 3362
A17: =PEDIDOS!A17 -> 25302 | B17: =PEDIDOS!B17 -> 46050 | C17: =PEDIDOS!C17 -> 15098 | D17: =PEDIDOS!D17 -> THELMA Y LOUISE | E17: =PEDIDOS!E17 -> CREMA BIFASICA CHERRY | F17: =PEDIDOS!G17 -> 1640 | G17: =37*37+22 -> 1391 | H17: =PEDIDOS!F17 -> M | I17: =IF(G17<>"",-(F17-G17)/F17+1, "") -> 0.84817073 | J17: 37X37 1X22 | L17: =IF(N17<>"","ENTREGADO",IF(K17<>"","LISTO PARA ENTREGAR","EN PROCESO" )) -> ENTREGADO | N17: 7
A18: =PEDIDOS!A18 -> 25303 | B18: =PEDIDOS!B18 -> 46052 | C18: =PEDIDOS!C18 | D18: =PEDIDOS!D18 -> ALL BEAUTY | E18: =PEDIDOS!E18 -> SERUM ACIDO HIALURONICO | F18: =PEDIDOS!G18 -> 1000 | G18: =13*70+15 -> 925 | H18: =PEDIDOS!F18 -> P | I18: =IF(G18<>"",-(F18-G18)/F18+1, "") -> 0.925 | J18: 13 x 70u + 1 x 15u | K18: 46077 | L18: =IF(N18<>"","ENTREGADO",IF(K18<>"","LISTO PARA ENTREGAR","EN PROCESO" )) -> ENTREGADO | M18: E26083 | N18: 3353
A19: =PEDIDOS!A19 -> 25304 | B19: =PEDIDOS!B19 -> 46044 | C19: =PEDIDOS!C19 | D19: =PEDIDOS!D19 -> DWUAM | E19: =PEDIDOS!E19 -> BASE DE MAQUILLAJE TONO 1 | F19: =PEDIDOS!G19 -> 500 | G19: 419 | H19: =PEDIDOS!F19 -> P | I19: =IF(G19<>"",-(F19-G19)/F19+1, "") -> 0.838 | K19: 46051 | L19: =IF(N19<>"","ENTREGADO",IF(K19<>"","LISTO PARA ENTREGAR","EN PROCESO" )) -> ENTREGADO | M19: E26104 | N19: 3001
A20: =PEDIDOS!A20 -> 26001 | B20: =PEDIDOS!B20 -> 46071 | C20: =PEDIDOS!C20 -> 6433 | D20: =PEDIDOS!D20 -> HEBURN | E20: =PEDIDOS!E20 -> BRUMA FIJADORA de MAQUILLAJE x 125 cc | F20: =PEDIDOS!G20 -> 600 | G20: 490 | H20: =PEDIDOS!F20 -> P | I20: =IF(G20<>"",-(F20-G20)/F20+1, "") -> 0.81666667 | J20: 8x42 1x28/ 3x42 | K20: 46086 | L20: =IF(N20<>"","ENTREGADO",IF(K20<>"","LISTO PARA ENTREGAR","EN PROCESO" )) -> ENTREGADO | M20: M26003 | N20: 3396
A21: =PEDIDOS!A21 -> 26002 | B21: =PEDIDOS!B21 -> 46052 | C21: =PEDIDOS!C21 | D21: =PEDIDOS!D21 -> ALL BEAUTY | E21: =PEDIDOS!E21 -> CREMA FACIAL HIDRATANTE X 50gr (DIA) | F21: =PEDIDOS!G21 -> 1000 | G21: =34*24+15+60+42 -> 933 | H21: =PEDIDOS!F21 -> P | I21: =IF(G21<>"",-(F21-G21)/F21+1, "") -> 0.933 | J21: 36 x 24 + 1 x 15u + 1 x 60u + 1 x 42u | K21: 46079 | L21: =IF(N21<>"","ENTREGADO",IF(K21<>"","LISTO PARA ENTREGAR","EN PROCESO" )) -> ENTREGADO | M21: F26040 | N21: 3353
A22: =PEDIDOS!A22 -> 26002 | B22: =PEDIDOS!B22 -> 46052 | C22: =PEDIDOS!C22 | D22: =PEDIDOS!D22 -> ALL BEAUTY | E22: =PEDIDOS!E22 -> UNGÜENTO POMADA OLEO 30 + 1 X 10gr | F22: =PEDIDOS!G22 -> 1000 | G22: =374*2+233 -> 981 | H22: =PEDIDOS!F22 -> P | I22: =IF(G22<>"",-(F22-G22)/F22+1, "") -> 0.981 | J22: 2 x 374u + 1 x 233u | K22: 46085 | L22: =IF(N22<>"","ENTREGADO",IF(K22<>"","LISTO PARA ENTREGAR","EN PROCESO" )) -> ENTREGADO | M22: F26045 | N22: 3366
A23: =PEDIDOS!A23 -> 26002 | B23: =PEDIDOS!B23 -> 46052 | C23: =PEDIDOS!C23 | D23: =PEDIDOS!D23 -> ALL BEAUTY | E23: =PEDIDOS!E23 -> CREMA DE ORDEÑE X 300gr | F23: =PEDIDOS!G23 -> 1500 | G23: 1483 | H23: =PEDIDOS!F23 -> M | I23: =IF(G23<>"",-(F23-G23)/F23+1, "") -> 0.98866667 | J23: 74X20 1X3 | K23: 46080 | L23: =IF(N23<>"","ENTREGADO",IF(K23<>"","LISTO PARA ENTREGAR","EN PROCESO" )) -> ENTREGADO | M23: F26039 | N23: 3366
A24: =PEDIDOS!A24 -> 26003 | B24: =PEDIDOS!B24 -> 46043 | C24: =PEDIDOS!C24 -> 103 | D24: =PEDIDOS!D24 -> UNICA | E24: =PEDIDOS!E24 -> CREMA ENEBRO | F24: =PEDIDOS!G24 -> 500 | G24: =9*50+55 -> 505 | H24: =PEDIDOS!F24 -> M | I24: =IF(G24<>"",-(F24-G24)/F24+1, "") -> 1.01 | J24: 9 x 50u + 1 x 55u | K24: 46101 | L24: =IF(N24<>"","ENTREGADO",IF(K24<>"","LISTO PARA ENTREGAR","EN PROCESO" )) -> ENTREGADO | M24: 200301 | N24: 250326
A25: =PEDIDOS!A25 -> 26004 | B25: =PEDIDOS!B25 -> 46066 | C25: =PEDIDOS!C25 -> 15114 | D25: =PEDIDOS!D25 -> THELMA Y LOUISE | E25: =PEDIDOS!E25 -> SERUM BIFASICO JOJOBA-POMELO | F25: =PEDIDOS!G25 -> 3024 | G25: =30*100+15 -> 3015 | H25: =PEDIDOS!F25 -> M | I25: =IF(G25<>"",-(F25-G25)/F25+1, "") -> 0.99702381 | J25: 30 x 100u + 1 x 15u | K25: 46099 | L25: =IF(N25<>"","ENTREGADO",IF(K25<>"","LISTO PARA ENTREGAR","EN PROCESO" )) -> ENTREGADO | M25: M26024 | N25: 3402
A26: =PEDIDOS!A26 -> 26004 | B26: =PEDIDOS!B26 -> 46066 | C26: =PEDIDOS!C26 -> 15114 | D26: =PEDIDOS!D26 -> THELMA Y LOUISE | E26: =PEDIDOS!E26 -> SERUM BIFASICO PEPINO-HAMAMELIS | F26: =PEDIDOS!G26 -> 3024 | G26: =29*100+103 -> 3003 | H26: =PEDIDOS!F26 -> M | I26: =IF(G26<>"",-(F26-G26)/F26+1, "") -> 0.99305556 | J26: 29 x 100u + 1 x 103u | K26: 46107 | L26: =IF(N26<>"","ENTREGADO",IF(K26<>"","LISTO PARA ENTREGAR","EN PROCESO" )) -> ENTREGADO | M26: M26083 | N26: 3413
A27: =PEDIDOS!A27 -> 26004 | B27: =PEDIDOS!B27 -> 46066 | C27: =PEDIDOS!C27 -> 15114 | D27: =PEDIDOS!D27 -> THELMA Y LOUISE | E27: =PEDIDOS!E27 -> SERUM BIFASICO LAVANDA-BLUEBERRY | F27: =PEDIDOS!G27 -> 3024 | G27: =30*100+16 -> 3016 | H27: =PEDIDOS!F27 -> M | I27: =IF(G27<>"",-(F27-G27)/F27+1, "") -> 0.9973545 | J27: 30 x 100u + 1 x 16u | K27: 46093 | L27: =IF(N27<>"","ENTREGADO",IF(K27<>"","LISTO PARA ENTREGAR","EN PROCESO" )) -> ENTREGADO | M27: M26022 | N27: 3387
A28: =PEDIDOS!A28 -> 26004 | B28: =PEDIDOS!B28 -> 46066 | C28: =PEDIDOS!C28 -> 15114 | D28: =PEDIDOS!D28 -> THELMA Y LOUISE | E28: =PEDIDOS!E28 -> SERUM BIFASICO ROSA MOSQUETA-ROSAS | F28: =PEDIDOS!G28 -> 3024 | G28: =30*100+13 -> 3013 | H28: =PEDIDOS!F28 -> M | I28: =IF(G28<>"",-(F28-G28)/F28+1, "") -> 0.99636243 | J28: 30 x 100u + 1 x 13u | K28: 46108 | L28: =IF(N28<>"","ENTREGADO",IF(K28<>"","LISTO PARA ENTREGAR","EN PROCESO" )) -> ENTREGADO | M28: M26084 | N28: 3413
A29: =PEDIDOS!A29 -> 26005 | B29: =PEDIDOS!B29 -> 46071 | C29: =PEDIDOS!C29 -> 772 | D29: =PEDIDOS!D29 -> CAV | E29: =PEDIDOS!E29 -> SHAMPOO BIO MOLECULAR X400ML VITAMIN SHOCK | F29: =PEDIDOS!G29 -> 700 | G29: =10*12+7 -> 127 | H29: =PEDIDOS!F29 -> M | I29: =IF(G29<>"",-(F29-G29)/F29+1, "") -> 0.18142857 | J29: 10 x 12u + 1 x 7u | K29: 46087 | L29: =IF(N29<>"","ENTREGADO",IF(K29<>"","LISTO PARA ENTREGAR","EN PROCESO" )) -> ENTREGADO | M29: E26064 | N29: 3403
A30: =PEDIDOS!A30 -> 26005 | B30: =PEDIDOS!B30 -> 46071 | C30: =PEDIDOS!C30 -> 772 | D30: =PEDIDOS!D30 -> CAV | E30: =PEDIDOS!E30 -> SERUM BIO MOLUECULAR X30ML VITAMIN SHOCK | F30: =PEDIDOS!G30 -> 300 | G30: =70+65+2*82+47 -> 346 | H30: =PEDIDOS!F30 -> P | I30: =IF(G30<>"",-(F30-G30)/F30+1, "") -> 1.1533333 | J30: 1 x 70 + 1 x 65u + 2 x 82u + 1 x 47u | K30: 46094 | L30: =IF(N30<>"","ENTREGADO",IF(K30<>"","LISTO PARA ENTREGAR","EN PROCESO" )) -> ENTREGADO | M30: M26009 | N30: 3386
A31: =PEDIDOS!A31 -> 26005 | B31: =PEDIDOS!B31 -> 46071 | C31: =PEDIDOS!C31 -> 772 | D31: =PEDIDOS!D31 -> CAV | E31: =PEDIDOS!E31 -> BALSAMO X400ML BIOMIC C/ ACIDO HIAL + CAPIMAX | F31: =PEDIDOS!G31 -> 400 | H31: =PEDIDOS!F31 -> M | I31: =IF(G31<>"",-(F31-G31)/F31+1, "") | L31: =IF(N31<>"","ENTREGADO",IF(K31<>"","LISTO PARA ENTREGAR","EN PROCESO" )) -> EN PROCESO
A32: =PEDIDOS!A32 -> 26005 | B32: =PEDIDOS!B32 -> 46071 | C32: =PEDIDOS!C32 -> 772 | D32: =PEDIDOS!D32 -> CAV | E32: =PEDIDOS!E32 -> MASCARA BIO MOLECULAR VITAMIN SHOCK X300ML | F32: =PEDIDOS!G32 -> 700 | G32: =238+21*15 -> 553 | H32: =PEDIDOS!F32 -> M | I32: =IF(G32<>"",-(F32-G32)/F32+1, "") -> 0.79 | J32: 15x15 1x13u/21X15 | K32: 46097 | L32: =IF(N32<>"","ENTREGADO",IF(K32<>"","LISTO PARA ENTREGAR","EN PROCESO" )) -> ENTREGADO | M32: M26045 | N32: 3386 / 3388
A33: =PEDIDOS!A33 -> 26006 | B33: =PEDIDOS!B33 -> 46071 | C33: =PEDIDOS!C33 -> 14329 | D33: =PEDIDOS!D33 -> JACTANS - DISNEY | E33: =PEDIDOS!E33 -> DSH-41823-Shampoo infantil fco pvc x45ml | F33: =PEDIDOS!G33 -> 3000 | G33: =26*110+29 -> 2889 | H33: =PEDIDOS!F33 -> M | I33: =IF(G33<>"",-(F33-G33)/F33+1, "") -> 0.963 | J33: 26x110 1x29 | K33: 46086 | L33: =IF(N33<>"","ENTREGADO",IF(K33<>"","LISTO PARA ENTREGAR","EN PROCESO" )) -> ENTREGADO | M33: M26002 | N33: 3381
A34: =PEDIDOS!A34 -> 26006 | B34: =PEDIDOS!B34 -> 46071 | C34: =PEDIDOS!C34 -> 14329 | D34: =PEDIDOS!D34 -> JACTANS - DISNEY | E34: =PEDIDOS!E34 -> DES-41823-Espuma de Baño infantil fco pvc x45ml | F34: =PEDIDOS!G34 -> 3000 | G34: 2885 | H34: =PEDIDOS!F34 -> M | I34: =IF(G34<>"",-(F34-G34)/F34+1, "") -> 0.96166667 | J34: 26X110 1X25 | K34: 46085 | L34: =IF(N34<>"","ENTREGADO",IF(K34<>"","LISTO PARA ENTREGAR","EN PROCESO" )) -> ENTREGADO | M34: M26001 | N34: 3381
A35: =PEDIDOS!A35 -> 26007 | B35: =PEDIDOS!B35 -> 46071 | C35: =PEDIDOS!C35 | D35: =PEDIDOS!D35 -> BL COSMETICS | E35: =PEDIDOS!E35 -> ALISADO EXPERT | F35: =PEDIDOS!G35 -> 500 | G35: 500 | H35: =PEDIDOS!F35 -> M | I35: =IF(G35<>"",-(F35-G35)/F35+1, "") -> 1 | J35: 18x27 1x14 | K35: 46085 | L35: =IF(N35<>"","ENTREGADO",IF(K35<>"","LISTO PARA ENTREGAR","EN PROCESO" )) -> ENTREGADO | M35: M26007 | N35: 3378
A36: =PEDIDOS!A36 -> 26007 | B36: =PEDIDOS!B36 -> 46071 | C36: =PEDIDOS!C36 | D36: =PEDIDOS!D36 -> BL COSMETICS | E36: =PEDIDOS!E36 -> ALISADO EXPERT X1KG | F36: =PEDIDOS!G36 -> 500 | G36: 460 | H36: =PEDIDOS!F36 -> M | I36: =IF(G36<>"",-(F36-G36)/F36+1, "") -> 0.92 | J36: 46X10 | K36: 46087 | L36: =IF(N36<>"","ENTREGADO",IF(K36<>"","LISTO PARA ENTREGAR","EN PROCESO" )) -> ENTREGADO | M36: M26007 | N36: 3378
A37: =PEDIDOS!A37 -> 26007 | B37: =PEDIDOS!B37 -> 46071 | C37: =PEDIDOS!C37 | D37: =PEDIDOS!D37 -> BL COSMETICS | E37: =PEDIDOS!E37 -> ALISADO KERATIN | F37: =PEDIDOS!G37 -> 1000 | G37: 1003 | H37: =PEDIDOS!F37 -> M | I37: =IF(G37<>"",-(F37-G37)/F37+1, "") -> 1.003 | J37: 35X28 1X23 | K37: 46090 | L37: =IF(N37<>"","ENTREGADO",IF(K37<>"","LISTO PARA ENTREGAR","EN PROCESO" )) -> ENTREGADO | M37: M26008 | N37: 3378
A38: =PEDIDOS!A38 -> 26008 | B38: =PEDIDOS!B38 -> 46071 | C38: =PEDIDOS!C38 -> P00147 | D38: =PEDIDOS!D38 -> LURE | E38: =PEDIDOS!E38 -> GOLD MASK | F38: =PEDIDOS!G38 -> 600 | G38: 585 | H38: =PEDIDOS!F38 -> M | I38: =IF(G38<>"",-(F38-G38)/F38+1, "") -> 0.975 | J38: 10X36/ 6X36 1X9 | K38: 46080 | L38: =IF(N38<>"","ENTREGADO",IF(K38<>"","LISTO PARA ENTREGAR","EN PROCESO" )) -> ENTREGADO | M38: F26025 | N38: 3357 / 3361
A39: =PEDIDOS!A39 -> 26009 | B39: =PEDIDOS!B39 -> 46071 | C39: =PEDIDOS!C39 -> TCL 2025-02-28 | D39: =PEDIDOS!D39 -> THE CHEMIST LOOK | E39: =PEDIDOS!E39 -> MANCHAS 5ML - PIGMENT PROTOCOL | F39: =PEDIDOS!G39 -> 1000 | G39: =250+87+20 -> 357 | H39: =PEDIDOS!F39 -> P | I39: =IF(G39<>"",-(F39-G39)/F39+1, "") -> 0.357 | J39: 1 x 250u + 1 x 87u + 1 x 20u | K39: 46100 | L39: =IF(N39<>"","ENTREGADO",IF(K39<>"","LISTO PARA ENTREGAR","EN PROCESO" )) -> ENTREGADO | M39: M26015 | N39: 3397
A40: =PEDIDOS!A40 -> 26009 | B40: =PEDIDOS!B40 -> 46071 | C40: =PEDIDOS!C40 -> TCL 2025-02-28 | D40: =PEDIDOS!D40 -> THE CHEMIST LOOK | E40: =PEDIDOS!E40 -> MANCHAS 30ML - PIGMENT PROTOCOL | F40: =PEDIDOS!G40 -> 2000 | G40: =18*110+10 -> 1990 | H40: =PEDIDOS!F40 -> P | I40: =IF(G40<>"",-(F40-G40)/F40+1, "") -> 0.995 | J40: 18 x 110u + 1 x 10u | K40: 46100 | L40: =IF(N40<>"","ENTREGADO",IF(K40<>"","LISTO PARA ENTREGAR","EN PROCESO" )) -> ENTREGADO | M40: M26015 | N40: 3397
A41: =PEDIDOS!A41 -> 26009 | B41: =PEDIDOS!B41 -> 46071 | C41: =PEDIDOS!C41 -> TCL 2025-02-28 | D41: =PEDIDOS!D41 -> THE CHEMIST LOOK | E41: =PEDIDOS!E41 -> BOOSTER VIT C/GLUT | F41: =PEDIDOS!G41 -> 3000 | G41: =18*158+54 -> 2898 | H41: =PEDIDOS!F41 -> P | I41: =IF(G41<>"",-(F41-G41)/F41+1, "") -> 0.966 | J41: 18 x 158u + 1 x 44u + 1 x 10 | K41: 46087 | L41: =IF(N41<>"","ENTREGADO",IF(K41<>"","LISTO PARA ENTREGAR","EN PROCESO" )) -> ENTREGADO | M41: F26059 | N41: 3377
A42: =PEDIDOS!A42 -> 26009 | B42: =PEDIDOS!B42 -> 46071 | C42: =PEDIDOS!C42 -> TCL 2025-02-28 | D42: =PEDIDOS!D42 -> THE CHEMIST LOOK | E42: =PEDIDOS!E42 -> BOOSTER NIACI/ZN | F42: =PEDIDOS!G42 -> 3500 | G42: =20*158+10+2*158+60 -> 3546 | H42: =PEDIDOS!F42 -> P | I42: =IF(G42<>"",-(F42-G42)/F42+1, "") -> 1.0131429 | J42: 20 x 158u + 1 x 10u / 2 x 158u + 1 x 60u | K42: 46087 | L42: =IF(N42<>"","ENTREGADO",IF(K42<>"","LISTO PARA ENTREGAR","EN PROCESO" )) -> ENTREGADO | M42: F26058 | N42: 3377
A43: =PEDIDOS!A43 -> 26009 | B43: =PEDIDOS!B43 -> 46071 | C43: =PEDIDOS!C43 -> TCL 2025-02-28 | D43: =PEDIDOS!D43 -> THE CHEMIST LOOK | E43: =PEDIDOS!E43 -> BOOSTER HYALU-A/SI | F43: =PEDIDOS!G43 -> 2400 | G43: =15*158+37+10 -> 2417 | H43: =PEDIDOS!F43 -> P | I43: =IF(G43<>"",-(F43-G43)/F43+1, "") -> 1.0070833 | J43: 15 x 158u + 1 x 37u + 1 x 10u | K43: 46090 | L43: =IF(N43<>"","ENTREGADO",IF(K43<>"","LISTO PARA ENTREGAR","EN PROCESO" )) -> ENTREGADO | M43: F26060 | N43: 3377
A44: =PEDIDOS!A44 -> 26009 | B44: =PEDIDOS!B44 -> 46071 | C44: =PEDIDOS!C44 -> TCL 2025-02-28 | D44: =PEDIDOS!D44 -> THE CHEMIST LOOK | E44: =PEDIDOS!E44 -> BOOSTER MUNAP-18 | F44: =PEDIDOS!G44 -> 3000 | G44: =7*160+91 -> 1211 | H44: =PEDIDOS!F44 -> P | I44: =IF(G44<>"",-(F44-G44)/F44+1, "") -> 0.40366667 | J44: 7 x 160 + 1 x 91 | K44: 46168 | L44: =IF(N44<>"","ENTREGADO",IF(K44<>"","LISTO PARA ENTREGAR","EN PROCESO" )) -> ENTREGADO | M44: Y26017 | N44: 3496
A45: =PEDIDOS!A45 -> 26009 | B45: =PEDIDOS!B45 -> 46071 | C45: =PEDIDOS!C45 -> TCL 2025-02-28 | D45: =PEDIDOS!D45 -> THE CHEMIST LOOK | E45: =PEDIDOS!E45 -> TAN BOOSTER | F45: =PEDIDOS!G45 -> 500 | H45: =PEDIDOS!F45 -> P | I45: =IF(G45<>"",-(F45-G45)/F45+1, "") | L45: =IF(N45<>"","ENTREGADO",IF(K45<>"","LISTO PARA ENTREGAR","EN PROCESO" )) -> EN PROCESO
A46: =PEDIDOS!A46 -> 26009 | B46: =PEDIDOS!B46 -> 46071 | C46: =PEDIDOS!C46 -> TCL 2025-02-28 | D46: =PEDIDOS!D46 -> THE CHEMIST LOOK | E46: =PEDIDOS!E46 -> BOOSTER RETIN | F46: =PEDIDOS!G46 -> 2000 | G46: =4*160+136+10+160*2+80 -> 1186 | H46: =PEDIDOS!F46 -> P | I46: =IF(G46<>"",-(F46-G46)/F46+1, "") -> 0.593 | J46: 4 x 160 + 1 x 136 + 10 / 2 x 160 + 1 x 80 | K46: 46142 | L46: =IF(N46<>"","ENTREGADO",IF(K46<>"","LISTO PARA ENTREGAR","EN PROCESO" )) -> ENTREGADO | M46: A26018 | N46: 3450
A47: =PEDIDOS!A47 -> 26009 | B47: =PEDIDOS!B47 -> 46071 | C47: =PEDIDOS!C47 -> TCL 2025-02-28 | D47: =PEDIDOS!D47 -> THE CHEMIST LOOK | E47: =PEDIDOS!E47 -> 2ND SKIN | F47: =PEDIDOS!G47 -> 1000 | H47: =PEDIDOS!F47 -> P | I47: =IF(G47<>"",-(F47-G47)/F47+1, "") | L47: =IF(N47<>"","ENTREGADO",IF(K47<>"","LISTO PARA ENTREGAR","EN PROCESO" )) -> EN PROCESO
A48: =PEDIDOS!A48 -> 26010 | B48: =PEDIDOS!B48 -> 46071 | C48: =PEDIDOS!C48 -> 14331 | D48: =PEDIDOS!D48 -> JACTANS | E48: =PEDIDOS!E48 -> JS-736 BRUMA FIJADORA FACIAL | F48: =PEDIDOS!G48 -> 2000 | G48: 1528 | H48: =PEDIDOS!F48 -> M | I48: =IF(G48<>"",-(F48-G48)/F48+1, "") -> 0.764 | J48: 25X60 1X28 | K48: 46164 | L48: =IF(N48<>"","ENTREGADO",IF(K48<>"","LISTO PARA ENTREGAR","EN PROCESO" )) -> ENTREGADO | M48: Y26022 | N48: 3494
A49: =PEDIDOS!A49 -> 26011 | B49: =PEDIDOS!B49 -> 46072 | C49: =PEDIDOS!C49 | D49: =PEDIDOS!D49 -> KALA | E49: =PEDIDOS!E49 -> AGUA DE ROSAS | F49: =PEDIDOS!G49 -> 650 | G49: =20*24+15+3*37+33 -> 639 | H49: =PEDIDOS!F49 -> M | I49: =IF(G49<>"",-(F49-G49)/F49+1, "") -> 0.98307692 | J49: 20 x 24u + 1 x 15u + 3 x 37u + 1 x 33u | K49: 46086 | L49: =IF(N49<>"","ENTREGADO",IF(K49<>"","LISTO PARA ENTREGAR","EN PROCESO" )) -> ENTREGADO | M49: F26057 | N49: 3372
A50: =PEDIDOS!A50 -> 26012 | B50: =PEDIDOS!B50 -> 46073 | C50: =PEDIDOS!C50 | D50: =PEDIDOS!D50 -> INTENCIONAL | E50: =PEDIDOS!E50 -> CREMA DE ORDEÑE | F50: =PEDIDOS!G50 -> 2000 | G50: 1998 | H50: =PEDIDOS!F50 -> M | I50: =IF(G50<>"",-(F50-G50)/F50+1, "") -> 0.999 | J50: 111x18 | K50: 46094 | L50: =IF(N50<>"","ENTREGADO",IF(K50<>"","LISTO PARA ENTREGAR","EN PROCESO" )) -> ENTREGADO | M50: F26062 | N50: 3391
A51: =PEDIDOS!A51 -> 26014 | B51: =PEDIDOS!B51 -> 46073 | C51: =PEDIDOS!C51 -> P01256 | D51: =PEDIDOS!D51 -> BIOESENCIA | E51: =PEDIDOS!E51 -> CREMA BABA DE CARACOL | F51: =PEDIDOS!G51 -> 1000 | G51: 1013 | H51: =PEDIDOS!F51 -> M | I51: =IF(G51<>"",-(F51-G51)/F51+1, "") -> 1.013 | J51: 5x170 1x165 | K51: 46083 | L51: =IF(N51<>"","ENTREGADO",IF(K51<>"","LISTO PARA ENTREGAR","EN PROCESO" )) -> ENTREGADO | M51: 270201 | N51: 46085
A52: =PEDIDOS!A52 -> 25298 | B52: =PEDIDOS!B52 -> 46042 | C52: =PEDIDOS!C52 -> P01203 | D52: =PEDIDOS!D52 -> BIOESENCIA | E52: =PEDIDOS!E52 -> SHAMPOO BABY | F52: =PEDIDOS!G52 -> 500 | G52: 486 | H52: =PEDIDOS!F52 -> M | I52: =IF(G52<>"",-(F52-G52)/F52+1, "") -> 0.972 | J52: 6X72 1X54 | K52: 46073 | L52: =IF(N52<>"","ENTREGADO",IF(K52<>"","LISTO PARA ENTREGAR","EN PROCESO" )) -> ENTREGADO | M52: F26023 | N52: 3352 | O52: NO ALCANZO EL GRANEL PARA COMPLETAR PEDIDO
A53: =PEDIDOS!A53 -> 25298 | B53: =PEDIDOS!B53 -> 46042 | C53: =PEDIDOS!C53 -> P01203 | D53: =PEDIDOS!D53 -> BIOESENCIA | E53: =PEDIDOS!E53 -> SERUM PROBIOTICOS | F53: =PEDIDOS!G53 -> 1000 | G53: 1001 | H53: =PEDIDOS!F53 -> M | I53: =IF(G53<>"",-(F53-G53)/F53+1, "") -> 1.001 | J53: 3X286 1X143 | K53: 46073 | L53: =IF(N53<>"","ENTREGADO",IF(K53<>"","LISTO PARA ENTREGAR","EN PROCESO" )) -> ENTREGADO | M53: F26022 | N53: 3352
A54: =PEDIDOS!A54 -> 26013 | B54: =PEDIDOS!B54 -> 46073 | C54: =PEDIDOS!C54 | D54: =PEDIDOS!D54 -> OSSPRET | E54: =PEDIDOS!E54 -> CREMA DE ORDEÑE | F54: =PEDIDOS!G54 -> 300 | G54: 300 | H54: =PEDIDOS!F54 -> M | I54: =IF(G54<>"",-(F54-G54)/F54+1, "") -> 1 | J54: 15x20 | K54: 46090 | L54: =IF(N54<>"","ENTREGADO",IF(K54<>"","LISTO PARA ENTREGAR","EN PROCESO" )) -> ENTREGADO | M54: M26004 /M26013 | N54: 3375
A55: =PEDIDOS!A55 -> 26014 | B55: =PEDIDOS!B55 -> 46073 | C55: =PEDIDOS!C55 -> P01256 | D55: =PEDIDOS!D55 -> BIOESENCIA | E55: =PEDIDOS!E55 -> UNGUENTO PROPOLEO | F55: =PEDIDOS!G55 -> 1000 | G55: =4*230+24 -> 944 | H55: =PEDIDOS!F55 -> M | I55: =IF(G55<>"",-(F55-G55)/F55+1, "") -> 0.944 | J55: 4 x 230u + 1 x 24u | K55: 46091 | L55: =IF(N55<>"","ENTREGADO",IF(K55<>"","LISTO PARA ENTREGAR","EN PROCESO" )) -> ENTREGADO | M55: M26018 | N55: 3379
A56: =PEDIDOS!A56 -> 26014 | B56: =PEDIDOS!B56 -> 46073 | C56: =PEDIDOS!C56 -> P01257 | D56: =PEDIDOS!D56 -> BIOESENCIA | E56: =PEDIDOS!E56 -> BAÑO BE KERATINA BE VEGAN | F56: =PEDIDOS!G56 -> 1000 | G56: =14*60+43+60+58 -> 1001 | H56: =PEDIDOS!F56 -> M | I56: =IF(G56<>"",-(F56-G56)/F56+1, "") -> 1.001 | J56: 14X60 1X43 / 1 x 60 + 1 x 58 | K56: 46112 | L56: =IF(N56<>"","ENTREGADO",IF(K56<>"","LISTO PARA ENTREGAR","EN PROCESO" )) -> ENTREGADO | M56: 180302 | N56: 310326 /7426
A57: =PEDIDOS!A57 -> 26014 | B57: =PEDIDOS!B57 -> 46073 | C57: =PEDIDOS!C57 -> P01258 | D57: =PEDIDOS!D57 -> BIOESENCIA | E57: =PEDIDOS!E57 -> REPARADOR DE PUNTAS | F57: =PEDIDOS!G57 -> 1000 | G57: 982 | H57: =PEDIDOS!F57 -> P | I57: =IF(G57<>"",-(F57-G57)/F57+1, "") -> 0.982 | J57: 2 x 232 + 1 x 86/1 x 240 1 x 192 | K57: 46183 | L57: =IF(N57<>"","ENTREGADO",IF(K57<>"","LISTO PARA ENTREGAR","EN PROCESO" )) -> ENTREGADO | M57: 100601 | N57: 120526
A58: =PEDIDOS!A58 -> 26014 | B58: =PEDIDOS!B58 -> 46073 | C58: =PEDIDOS!C58 -> P01259 | D58: =PEDIDOS!D58 -> BIOESENCIA | E58: =PEDIDOS!E58 -> BRUMA FACIAL ORIGENES | F58: =PEDIDOS!G58 -> 1000 | G58: 1004 | H58: =PEDIDOS!F58 -> P | I58: =IF(G58<>"",-(F58-G58)/F58+1, "") -> 1.004 | J58: 12x77 1x80 | K58: 46099 | L58: =IF(N58<>"","ENTREGADO",IF(K58<>"","LISTO PARA ENTREGAR","EN PROCESO" )) -> ENTREGADO | M58: 130302 | N58: 180326
A59: =PEDIDOS!A59 -> 26014 | B59: =PEDIDOS!B59 -> 46073 | C59: =PEDIDOS!C59 -> P01260 | D59: =PEDIDOS!D59 -> BIOESENCIA | E59: =PEDIDOS!E59 -> EMULSION CORPORAL PROBIOTICOS | F59: =PEDIDOS!G59 -> 1000 | G59: 987 | H59: =PEDIDOS!F59 -> M | I59: =IF(G59<>"",-(F59-G59)/F59+1, "") -> 0.987 | J59: 19x51 1x18 | K59: 46099 | L59: =IF(N59<>"","ENTREGADO",IF(K59<>"","LISTO PARA ENTREGAR","EN PROCESO" )) -> ENTREGADO | M59: M26059 | N59: 3394
A60: =PEDIDOS!A60 -> 26014 | B60: =PEDIDOS!B60 -> 46073 | C60: =PEDIDOS!C60 -> P01261 | D60: =PEDIDOS!D60 -> BIOESENCIA | E60: =PEDIDOS!E60 -> CREMA DIA/NOCHE ULTRAHIDRATANTE VEGAN | F60: =PEDIDOS!G60 -> 1000 | G60: 923 | H60: =PEDIDOS!F60 -> M | I60: =IF(G60<>"",-(F60-G60)/F60+1, "") -> 0.923 | J60: 5X170 1X73 | K60: 46094 | L60: =IF(N60<>"","ENTREGADO",IF(K60<>"","LISTO PARA ENTREGAR","EN PROCESO" )) -> ENTREGADO | M60: 120301 | N60: 180326
A61: =PEDIDOS!A61 -> 26015 | B61: =PEDIDOS!B61 -> 46076 | C61: =PEDIDOS!C61 | D61: =PEDIDOS!D61 -> AGUEDA REY - ALMA HAIR | E61: =PEDIDOS!E61 -> ACONDICIONADOR CON EXTRACTO DE CEBOLLA | F61: =PEDIDOS!G61 -> 1050 | G61: 1020 | H61: =PEDIDOS!F61 -> M | I61: =IF(G61<>"",-(F61-G61)/F61+1, "") -> 0.97142857 | J61: 72X14 1X12 | K61: 46118 | L61: =IF(N61<>"","ENTREGADO",IF(K61<>"","LISTO PARA ENTREGAR","EN PROCESO" )) -> ENTREGADO | M61: M26088 | N61: Nestor
A62: =PEDIDOS!A62 -> 26016 | B62: =PEDIDOS!B62 -> 46076 | C62: =PEDIDOS!C62 -> 774 | D62: =PEDIDOS!D62 -> CAV | E62: =PEDIDOS!E62 -> CRISTAL LIQ (BRIGHT CRYSTAL) CAV EXPRESSION | F62: =PEDIDOS!G62 -> 250 | G62: =82+18+82+67 -> 249 | H62: =PEDIDOS!F62 -> P | I62: =IF(G62<>"",-(F62-G62)/F62+1, "") -> 0.996 | J62: 1 x 82u + 1 x 18u / 1 x 82u + 1 x 67u | K62: 46094 | L62: =IF(N62<>"","ENTREGADO",IF(K62<>"","LISTO PARA ENTREGAR","EN PROCESO" )) -> ENTREGADO | M62: M26040 | N62: 3386 / 3403
A63: =PEDIDOS!A63 -> 26016 | B63: =PEDIDOS!B63 -> 46076 | C63: =PEDIDOS!C63 -> 774 | D63: =PEDIDOS!D63 -> CAV | E63: =PEDIDOS!E63 -> Protector C-Plex x150 Paso 3 | F63: =PEDIDOS!G63 -> 300 | G63: =7*36+20 -> 272 | H63: =PEDIDOS!F63 -> P | I63: =IF(G63<>"",-(F63-G63)/F63+1, "") -> 0.90666667 | J63: 7 x 36u + 1 x 20u | K63: 46094 | L63: =IF(N63<>"","ENTREGADO",IF(K63<>"","LISTO PARA ENTREGAR","EN PROCESO" )) -> ENTREGADO | M63: M26041 | N63: 3388
A64: =PEDIDOS!A64 -> 26017 | B64: =PEDIDOS!B64 -> 46076 | C64: =PEDIDOS!C64 | D64: =PEDIDOS!D64 -> WSABI | E64: =PEDIDOS!E64 -> CONTORNO DE OJOS | F64: =PEDIDOS!G64 -> 480 | G64: =10*48 -> 480 | H64: =PEDIDOS!F64 -> P | I64: =IF(G64<>"",-(F64-G64)/F64+1, "") -> 1 | J64: 10 x 48u | K64: 46098 | L64: =IF(N64<>"","ENTREGADO",IF(K64<>"","LISTO PARA ENTREGAR","EN PROCESO" )) -> ENTREGADO | M64: M26027 | N64: 3393
A65: =PEDIDOS!A65 -> 26017 | B65: =PEDIDOS!B65 -> 46076 | C65: =PEDIDOS!C65 | D65: =PEDIDOS!D65 -> WSABI | E65: =PEDIDOS!E65 -> LECHE DE LIMPIEZA | F65: =PEDIDOS!G65 -> 500 | G65: 496 | H65: =PEDIDOS!F65 -> P | I65: =IF(G65<>"",-(F65-G65)/F65+1, "") -> 0.992 | J65: 24x20u y1x16u | K65: 46092 | L65: =IF(N65<>"","ENTREGADO",IF(K65<>"","LISTO PARA ENTREGAR","EN PROCESO" )) -> ENTREGADO | M65: M26011 | N65: 3393
A66: =PEDIDOS!A66 -> 26017 | B66: =PEDIDOS!B66 -> 46076 | C66: =PEDIDOS!C66 | D66: =PEDIDOS!D66 -> WSABI | E66: =PEDIDOS!E66 -> SERUM ANTIOXIDANTE VIT C | F66: =PEDIDOS!G66 -> 300 | G66: =8*34+36 -> 308 | H66: =PEDIDOS!F66 -> P | I66: =IF(G66<>"",-(F66-G66)/F66+1, "") -> 1.0266667 | J66: 8 x 34u + 1 x 36u | K66: 46098 | L66: =IF(N66<>"","ENTREGADO",IF(K66<>"","LISTO PARA ENTREGAR","EN PROCESO" )) -> ENTREGADO | M66: M26026 | N66: 3393
A67: =PEDIDOS!A67 -> 26017 | B67: =PEDIDOS!B67 -> 46076 | C67: =PEDIDOS!C67 | D67: =PEDIDOS!D67 -> WSABI | E67: =PEDIDOS!E67 -> TONICO CORPORAL EQUILIBRIO | F67: =PEDIDOS!G67 -> 1000 | G67: 1002 | H67: =PEDIDOS!F67 -> P | I67: =IF(G67<>"",-(F67-G67)/F67+1, "") -> 1.002 | J67: 41x24 1x18 | K67: 46093 | L67: =IF(N67<>"","ENTREGADO",IF(K67<>"","LISTO PARA ENTREGAR","EN PROCESO" )) -> ENTREGADO | M67: M26012 | N67: 3393
A68: =PEDIDOS!A68 -> 26018 | B68: =PEDIDOS!B68 -> 46063 | C68: =PEDIDOS!C68 -> 15125 | D68: =PEDIDOS!D68 -> THELMA Y LOUISE | E68: =PEDIDOS!E68 -> SERUM ANTIAGE | F68: =PEDIDOS!G68 -> 2100 | G68: =20*100+87 -> 2087 | H68: =PEDIDOS!F68 -> M | I68: =IF(G68<>"",-(F68-G68)/F68+1, "") -> 0.99380952 | J68: 20 x 100u + 1 x 87u | K68: 46090 | L68: =IF(N68<>"","ENTREGADO",IF(K68<>"","LISTO PARA ENTREGAR","EN PROCESO" )) -> ENTREGADO | M68: M26023 | N68: 3387
A69: =PEDIDOS!A69 -> 26018 | B69: =PEDIDOS!B69 -> 46063 | C69: =PEDIDOS!C69 -> 15125 | D69: =PEDIDOS!D69 -> THELMA Y LOUISE | E69: =PEDIDOS!E69 -> SERUM DESCONGESTIVO | F69: =PEDIDOS!G69 -> 2100 | G69: =20*100+87 -> 2087 | H69: =PEDIDOS!F69 -> M | I69: =IF(G69<>"",-(F69-G69)/F69+1, "") -> 0.99380952 | J69: 20 x 100u + 1 x 87u | K69: 46092 | L69: =IF(N69<>"","ENTREGADO",IF(K69<>"","LISTO PARA ENTREGAR","EN PROCESO" )) -> ENTREGADO | M69: M26021 | N69: 3387
A70: =PEDIDOS!A70 -> 26019 | B70: =PEDIDOS!B70 -> 46076 | C70: =PEDIDOS!C70 -> 775 | D70: =PEDIDOS!D70 -> CAV | E70: =PEDIDOS!E70 -> Rebond C-Plex CAV x 500 ml (Paso 1) | F70: =PEDIDOS!G70 -> 200 | G70: =16*9+5 -> 149 | H70: =PEDIDOS!F70 -> M | I70: =IF(G70<>"",-(F70-G70)/F70+1, "") -> 0.745 | J70: 16 x 9 + 1 x 5u | K70: 46101 | L70: =IF(N70<>"","ENTREGADO",IF(K70<>"","LISTO PARA ENTREGAR","EN PROCESO" )) -> ENTREGADO | M70: M26062 | N70: 3403
A71: =PEDIDOS!A71 -> 26019 | B71: =PEDIDOS!B71 -> 46076 | C71: =PEDIDOS!C71 -> 775 | D71: =PEDIDOS!D71 -> CAV | E71: =PEDIDOS!E71 -> Finishing C-Plex CAV x 500 ml (Paso 2) | F71: =PEDIDOS!G71 -> 400 | G71: =38*9+2 -> 344 | H71: =PEDIDOS!F71 -> M | I71: =IF(G71<>"",-(F71-G71)/F71+1, "") -> 0.86 | J71: 38 x 9u + 1 x 2u | K71: 46101 | L71: =IF(N71<>"","ENTREGADO",IF(K71<>"","LISTO PARA ENTREGAR","EN PROCESO" )) -> ENTREGADO | M71: M26061 | N71: 3403
A72: =PEDIDOS!A72 -> 26020 | B72: =PEDIDOS!B72 -> 46077 | C72: =PEDIDOS!C72 -> 1704 | D72: =PEDIDOS!D72 -> LABORATORIO ONCE | E72: =PEDIDOS!E72 -> ALBA SERUM X 30 ML DRA ROSSI | F72: =PEDIDOS!G72 -> 300 | H72: =PEDIDOS!F72 -> P | I72: =IF(G72<>"",-(F72-G72)/F72+1, "") | L72: =IF(N72<>"","ENTREGADO",IF(K72<>"","LISTO PARA ENTREGAR","EN PROCESO" )) -> EN PROCESO
A73: =PEDIDOS!A73 -> 26021 | B73: =PEDIDOS!B73 -> 46078 | C73: =PEDIDOS!C73 | D73: =PEDIDOS!D73 -> UNICA | E73: =PEDIDOS!E73 -> CREMA CORPORAL HUMECTANTE KARITE | F73: =PEDIDOS!G73 -> 500 | G73: 486 | H73: =PEDIDOS!F73 -> M | I73: =IF(G73<>"",-(F73-G73)/F73+1, "") -> 0.972 | J73: 37x13 1X5 | K73: 46101 | L73: =IF(N73<>"","ENTREGADO",IF(K73<>"","LISTO PARA ENTREGAR","EN PROCESO" )) -> ENTREGADO | M73: 110301 | N73: 250326
A74: =PEDIDOS!A74 -> 26022 | B74: =PEDIDOS!B74 -> 46078 | C74: =PEDIDOS!C74 | D74: =PEDIDOS!D74 -> OLANN | E74: =PEDIDOS!E74 -> Serum hialurónico 30 ml | F74: =PEDIDOS!G74 -> 250 | G74: =2*110+33 -> 253 | H74: =PEDIDOS!F74 -> P | I74: =IF(G74<>"",-(F74-G74)/F74+1, "") -> 1.012 | J74: 2 x 110 + 1 x 33 | K74: 46136 | L74: =IF(N74<>"","ENTREGADO",IF(K74<>"","LISTO PARA ENTREGAR","EN PROCESO" )) -> ENTREGADO | M74: M26065 | N74: 3455
A75: =PEDIDOS!A75 -> 26022 | B75: =PEDIDOS!B75 -> 46078 | C75: =PEDIDOS!C75 | D75: =PEDIDOS!D75 -> OLANN | E75: =PEDIDOS!E75 -> BRUMA FACIAL | F75: =PEDIDOS!G75 -> 250 | G75: =6*45 -> 270 | H75: =PEDIDOS!F75 -> P | I75: =IF(G75<>"",-(F75-G75)/F75+1, "") -> 1.08 | J75: 6 x 45 | K75: 46136 | L75: =IF(N75<>"","ENTREGADO",IF(K75<>"","LISTO PARA ENTREGAR","EN PROCESO" )) -> ENTREGADO | M75: M26060 | N75: 3455
A76: =PEDIDOS!A76 -> 26022 | B76: =PEDIDOS!B76 -> 46078 | C76: =PEDIDOS!C76 | D76: =PEDIDOS!D76 -> OLANN | E76: =PEDIDOS!E76 -> CREMA FACIAL DE DIA ULTRAHUMECTANTE | F76: =PEDIDOS!G76 -> 250 | G76: =3*60+55 -> 235 | H76: =PEDIDOS!F76 -> P | I76: =IF(G76<>"",-(F76-G76)/F76+1, "") -> 0.94 | J76: 3 x 60 + 1 x 55 | K76: 46118 | L76: =IF(N76<>"","ENTREGADO",IF(K76<>"","LISTO PARA ENTREGAR","EN PROCESO" )) -> ENTREGADO | M76: M26031 | N76: 3458
A77: =PEDIDOS!A77 -> 26022 | B77: =PEDIDOS!B77 -> 46078 | C77: =PEDIDOS!C77 | D77: =PEDIDOS!D77 -> OLANN | E77: =PEDIDOS!E77 -> CREMA FACIAL DE NOCHE TENSORA | F77: =PEDIDOS!G77 -> 250 | G77: =3*60+57 -> 237 | H77: =PEDIDOS!F77 -> P | I77: =IF(G77<>"",-(F77-G77)/F77+1, "") -> 0.948 | J77: 3 x 60 + 1 x 57 | K77: 46118 | L77: =IF(N77<>"","ENTREGADO",IF(K77<>"","LISTO PARA ENTREGAR","EN PROCESO" )) -> ENTREGADO | M77: M26032 | N77: 3458
A78: =PEDIDOS!A78 -> 26022 | B78: =PEDIDOS!B78 -> 46078 | C78: =PEDIDOS!C78 | D78: =PEDIDOS!D78 -> OLANN | E78: =PEDIDOS!E78 -> CONTORNO DE OJOS | F78: =PEDIDOS!G78 -> 250 | G78: =2*100+60 -> 260 | H78: =PEDIDOS!F78 -> P | I78: =IF(G78<>"",-(F78-G78)/F78+1, "") -> 1.04 | J78: 2 x 100 + 1 x 60 | K78: 46136 | L78: =IF(N78<>"","ENTREGADO",IF(K78<>"","LISTO PARA ENTREGAR","EN PROCESO" )) -> ENTREGADO | M78: M26033 | N78: 3455
A79: =PEDIDOS!A79 -> 26023 | B79: =PEDIDOS!B79 -> 46083 | C79: =PEDIDOS!C79 | D79: =PEDIDOS!D79 -> ECODERM - AGUAZU | E79: =PEDIDOS!E79 -> ESPUMA DE BAÑO ADULTO | F79: =PEDIDOS!G79 -> 200 | G79: =6*30+20 -> 200 | H79: =PEDIDOS!F79 -> M | I79: =IF(G79<>"",-(F79-G79)/F79+1, "") -> 1 | J79: 6 x 30 + 1 x 20u | K79: 46099 | L79: =IF(N79<>"","ENTREGADO",IF(K79<>"","LISTO PARA ENTREGAR","EN PROCESO" )) -> ENTREGADO | M79: M26034 | N79: 3398
A80: =PEDIDOS!A80 -> 26023 | B80: =PEDIDOS!B80 -> 46083 | C80: =PEDIDOS!C80 | D80: =PEDIDOS!D80 -> ECODERM - AGUAZU | E80: =PEDIDOS!E80 -> ESPUMA DE BAÑO BALLENA | F80: =PEDIDOS!G80 -> 200 | G80: =6*30+16 -> 196 | H80: =PEDIDOS!F80 -> M | I80: =IF(G80<>"",-(F80-G80)/F80+1, "") -> 0.98 | J80: 6 x 30u + 1 x 16 | K80: 46099 | L80: =IF(N80<>"","ENTREGADO",IF(K80<>"","LISTO PARA ENTREGAR","EN PROCESO" )) -> ENTREGADO | M80: M26034 | N80: 3398
A81: =PEDIDOS!A81 -> 26023 | B81: =PEDIDOS!B81 -> 46083 | C81: =PEDIDOS!C81 | D81: =PEDIDOS!D81 -> ECODERM - AGUAZU | E81: =PEDIDOS!E81 -> ESPUMA DE BAÑO BALLENA X500 | F81: =PEDIDOS!G81 -> 100 | G81: =9*11 -> 99 | H81: =PEDIDOS!F81 -> M | I81: =IF(G81<>"",-(F81-G81)/F81+1, "") -> 0.99 | J81: 9 x 11u | K81: 46099 | L81: =IF(N81<>"","ENTREGADO",IF(K81<>"","LISTO PARA ENTREGAR","EN PROCESO" )) -> ENTREGADO | M81: M26034 | N81: 3398
A82: =PEDIDOS!A82 -> 26023 | B82: =PEDIDOS!B82 -> 46083 | C82: =PEDIDOS!C82 | D82: =PEDIDOS!D82 -> ECODERM - AGUAZU | E82: =PEDIDOS!E82 -> ESPUMA DE BAÑO ADULTO X500 | F82: =PEDIDOS!G82 -> 100 | G82: =9*11 -> 99 | H82: =PEDIDOS!F82 -> M | I82: =IF(G82<>"",-(F82-G82)/F82+1, "") -> 0.99 | J82: 9 x 11u | K82: 46099 | L82: =IF(N82<>"","ENTREGADO",IF(K82<>"","LISTO PARA ENTREGAR","EN PROCESO" )) -> ENTREGADO | M82: M26034 | N82: 3398
A83: =PEDIDOS!A83 -> 26023 | B83: =PEDIDOS!B83 -> 46083 | C83: =PEDIDOS!C83 | D83: =PEDIDOS!D83 -> ECODERM - AGUAZU | E83: =PEDIDOS!E83 -> BALSAMO HERBAL | F83: =PEDIDOS!G83 -> 300 | G83: 282 | H83: =PEDIDOS!F83 -> M | I83: =IF(G83<>"",-(F83-G83)/F83+1, "") -> 0.94 | J83: 3X80 1X42 | K83: 46099 | L83: =IF(N83<>"","ENTREGADO",IF(K83<>"","LISTO PARA ENTREGAR","EN PROCESO" )) -> ENTREGADO | M83: M26044 | N83: 3398
A84: =PEDIDOS!A84 -> 26023 | B84: =PEDIDOS!B84 -> 46083 | C84: =PEDIDOS!C84 | D84: =PEDIDOS!D84 -> ECODERM - DUGA | E84: =PEDIDOS!E84 -> ACONDICIONADOR INFANTIL | F84: =PEDIDOS!G84 -> 300 | G84: =6*42+28 -> 280 | H84: =PEDIDOS!F84 -> P | I84: =IF(G84<>"",-(F84-G84)/F84+1, "") -> 0.93333333 | J84: 6 x 42u + 1 x 28u | K84: 46107 | L84: =IF(N84<>"","ENTREGADO",IF(K84<>"","LISTO PARA ENTREGAR","EN PROCESO" )) -> ENTREGADO | M84: M26078 | N84: 3406
A85: =PEDIDOS!A85 -> 26024 | B85: =PEDIDOS!B85 -> 46083 | C85: =PEDIDOS!C85 -> 15134 | D85: =PEDIDOS!D85 -> THELMA Y LOUISE | E85: =PEDIDOS!E85 -> ALCOHOL EN GEL SANDIA FARMACITY KIDS | F85: =PEDIDOS!G85 -> 6000 | G85: =27*216+78 -> 5910 | H85: =PEDIDOS!F85 -> M | I85: =IF(G85<>"",-(F85-G85)/F85+1, "") -> 0.985 | J85: 19X216 / 8x216 1x78 | K85: 46094 | L85: =IF(N85<>"","ENTREGADO",IF(K85<>"","LISTO PARA ENTREGAR","EN PROCESO" )) -> ENTREGADO | N85: 170326
A86: =PEDIDOS!A86 -> 26024 | B86: =PEDIDOS!B86 -> 46083 | C86: =PEDIDOS!C86 -> 15134 | D86: =PEDIDOS!D86 -> THELMA Y LOUISE | E86: =PEDIDOS!E86 -> ALCOHOL EN GEL CHICLE FARMACITY KIDS | F86: =PEDIDOS!G86 -> 6000 | G86: 5798 | H86: =PEDIDOS!F86 -> M | I86: =IF(G86<>"",-(F86-G86)/F86+1, "") -> 0.96633333 | J86: 3x234/21x234 1x182 | K86: 46098 | L86: =IF(N86<>"","ENTREGADO",IF(K86<>"","LISTO PARA ENTREGAR","EN PROCESO" )) -> ENTREGADO | M86: 120302 | N86: 170326
A87: =PEDIDOS!A87 -> 26025 | B87: =PEDIDOS!B87 -> 46083 | C87: =PEDIDOS!C87 -> 15133 | D87: =PEDIDOS!D87 -> THELMA Y LOUISE | E87: =PEDIDOS!E87 -> ALCOHOL EN GEL CHICLE TYL | F87: =PEDIDOS!G87 -> 2000 | G87: 1989 | H87: =PEDIDOS!F87 -> M | I87: =IF(G87<>"",-(F87-G87)/F87+1, "") -> 0.9945 | J87: 8X234 1X117 | K87: 46101 | L87: =IF(N87<>"","ENTREGADO",IF(K87<>"","LISTO PARA ENTREGAR","EN PROCESO" )) -> ENTREGADO | M87: 160303 | N87: 200326
A88: =PEDIDOS!A88 -> 26025 | B88: =PEDIDOS!B88 -> 46083 | C88: =PEDIDOS!C88 -> 15133 | D88: =PEDIDOS!D88 -> THELMA Y LOUISE | E88: =PEDIDOS!E88 -> ALCOHOL EN GEL FRUTOS ROJOS TYL | F88: =PEDIDOS!G88 -> 2000 | G88: =8*216+201 -> 1929 | H88: =PEDIDOS!F88 -> M | I88: =IF(G88<>"",-(F88-G88)/F88+1, "") -> 0.9645 | J88: 8x216 1x201 | K88: 46093 | L88: =IF(N88<>"","ENTREGADO",IF(K88<>"","LISTO PARA ENTREGAR","EN PROCESO" )) -> ENTREGADO | N88: 130325
A89: =PEDIDOS!A89 -> 26025 | B89: =PEDIDOS!B89 -> 46083 | C89: =PEDIDOS!C89 -> 15133 | D89: =PEDIDOS!D89 -> THELMA Y LOUISE | E89: =PEDIDOS!E89 -> ALCOHOL EN GEL DURAZNO TYL | F89: =PEDIDOS!G89 -> 2000 | G89: =8*216+202 -> 1930 | H89: =PEDIDOS!F89 -> M | I89: =IF(G89<>"",-(F89-G89)/F89+1, "") -> 0.965 | J89: 8x216 1x202 | K89: 46101 | L89: =IF(N89<>"","ENTREGADO",IF(K89<>"","LISTO PARA ENTREGAR","EN PROCESO" )) -> ENTREGADO | N89: 200326
A90: =PEDIDOS!A90 -> 26025 | B90: =PEDIDOS!B90 -> 46083 | C90: =PEDIDOS!C90 -> 15133 | D90: =PEDIDOS!D90 -> THELMA Y LOUISE | E90: =PEDIDOS!E90 -> ALCOHOL EN GEL COCO TYL | F90: =PEDIDOS!G90 -> 2000 | G90: =10*216+109 -> 2269 | H90: =PEDIDOS!F90 -> M | I90: =IF(G90<>"",-(F90-G90)/F90+1, "") -> 1.1345 | J90: 10x216 1x109 | K90: 46101 | L90: =IF(N90<>"","ENTREGADO",IF(K90<>"","LISTO PARA ENTREGAR","EN PROCESO" )) -> ENTREGADO | N90: 10426
A91: =PEDIDOS!A91 -> 26025 | B91: =PEDIDOS!B91 -> 46083 | C91: =PEDIDOS!C91 -> 15133 | D91: =PEDIDOS!D91 -> THELMA Y LOUISE | E91: =PEDIDOS!E91 -> ALCOHOL EN GEL VAINILLA TYL | F91: =PEDIDOS!G91 -> 2000 | G91: =9*216+39 -> 1983 | H91: =PEDIDOS!F91 -> M | I91: =IF(G91<>"",-(F91-G91)/F91+1, "") -> 0.9915 | J91: 9x216 1x39 | K91: 46101 | L91: =IF(N91<>"","ENTREGADO",IF(K91<>"","LISTO PARA ENTREGAR","EN PROCESO" )) -> ENTREGADO | N91: 200326
A92: =PEDIDOS!A92 -> 26026 | B92: =PEDIDOS!B92 -> 46083 | C92: =PEDIDOS!C92 | D92: =PEDIDOS!D92 -> DERMION / FRANCO | E92: =PEDIDOS!E92 -> SERUM NIACINAMIDA | F92: =PEDIDOS!G92 -> 500 | G92: =4*112+57 -> 505 | H92: =PEDIDOS!F92 -> P | I92: =IF(G92<>"",-(F92-G92)/F92+1, "") -> 1.01 | J92: 4x112 1x57 | K92: 46085 | L92: =IF(N92<>"","ENTREGADO",IF(K92<>"","LISTO PARA ENTREGAR","EN PROCESO" )) -> ENTREGADO | M92: M26010 | N92: 3369
A93: =PEDIDOS!A93 -> 26027 | B93: =PEDIDOS!B93 -> 46083 | C93: =PEDIDOS!C93 | D93: =PEDIDOS!D93 -> THE GLOW FACTOR | E93: =PEDIDOS!E93 -> CREMA CLARITÉ | F93: =PEDIDOS!G93 -> 1000 | G93: =63*16+26+12 -> 1046 | H93: =PEDIDOS!F93 -> P | I93: =IF(G93<>"",-(F93-G93)/F93+1, "") -> 1.046 | J93: 1x26 / 63 x 16u + 1 x 12u | K93: 46098 | L93: =IF(N93<>"","ENTREGADO",IF(K93<>"","LISTO PARA ENTREGAR","EN PROCESO" )) -> ENTREGADO | M93: M26025 | N93: 3380 / 3393
A94: =PEDIDOS!A94 -> 26028 | B94: =PEDIDOS!B94 -> 46086 | C94: =PEDIDOS!C94 -> 777 | D94: =PEDIDOS!D94 -> CAV | E94: =PEDIDOS!E94 -> SHAMPOO MAXLISS X400ML | F94: =PEDIDOS!G94 -> 200 | G94: =16*12+9 -> 201 | H94: =PEDIDOS!F94 -> M | I94: =IF(G94<>"",-(F94-G94)/F94+1, "") -> 1.005 | J94: 16 x 12 + 1 x 9u | K94: 46097 | L94: =IF(N94<>"","ENTREGADO",IF(K94<>"","LISTO PARA ENTREGAR","EN PROCESO" )) -> ENTREGADO | M94: M26038 | N94: 3403
A95: =PEDIDOS!A95 -> 26028 | B95: =PEDIDOS!B95 -> 46086 | C95: =PEDIDOS!C95 -> 777 | D95: =PEDIDOS!D95 -> CAV | E95: =PEDIDOS!E95 -> CONDITIONER MAXLISS X400G | F95: =PEDIDOS!G95 -> 200 | G95: =17*12+8 -> 212 | H95: =PEDIDOS!F95 -> M | I95: =IF(G95<>"",-(F95-G95)/F95+1, "") -> 1.06 | J95: 17 x 12u + 1 x 8 | K95: 46101 | L95: =IF(N95<>"","ENTREGADO",IF(K95<>"","LISTO PARA ENTREGAR","EN PROCESO" )) -> ENTREGADO | M95: M26039 | N95: 3403
A96: =PEDIDOS!A96 -> 26028 | B96: =PEDIDOS!B96 -> 46086 | C96: =PEDIDOS!C96 -> 777 | D96: =PEDIDOS!D96 -> CAV | E96: =PEDIDOS!E96 -> VITAMIN SHOCK X150G | F96: =PEDIDOS!G96 -> 700 | G96: =27*25 -> 675 | H96: =PEDIDOS!F96 -> P | I96: =IF(G96<>"",-(F96-G96)/F96+1, "") -> 0.96428571 | J96: 27 x 25u | K96: 46112 | L96: =IF(N96<>"","ENTREGADO",IF(K96<>"","LISTO PARA ENTREGAR","EN PROCESO" )) -> ENTREGADO | M96: M26066 | N96: 3415
A97: =PEDIDOS!A97 -> 26029 | B97: =PEDIDOS!B97 -> 46086 | C97: =PEDIDOS!C97 -> 1080 | D97: =PEDIDOS!D97 -> NIZA | E97: =PEDIDOS!E97 -> CLEAR ACNE LOTION | F97: =PEDIDOS!G97 -> 300 | G97: =12*24+12 -> 300 | H97: =PEDIDOS!F97 -> P | I97: =IF(G97<>"",-(F97-G97)/F97+1, "") -> 1 | J97: 12 x 24u + 1 x 12u | K97: 46113 | L97: =IF(N97<>"","ENTREGADO",IF(K97<>"","LISTO PARA ENTREGAR","EN PROCESO" )) -> ENTREGADO | M97: M26085 | N97: 3417
A98: =PEDIDOS!A98 -> 26029 | B98: =PEDIDOS!B98 -> 46086 | C98: =PEDIDOS!C98 -> 1080 | D98: =PEDIDOS!D98 -> NIZA | E98: =PEDIDOS!E98 -> SIGNATURE AGE REVERSE | F98: =PEDIDOS!G98 -> 500 | G98: =18*28+21 -> 525 | H98: =PEDIDOS!F98 -> P | I98: =IF(G98<>"",-(F98-G98)/F98+1, "") -> 1.05 | J98: 18 x 28u + 1 x 21 | K98: 46113 | L98: =IF(N98<>"","ENTREGADO",IF(K98<>"","LISTO PARA ENTREGAR","EN PROCESO" )) -> ENTREGADO | M98: M26086 | N98: 3417
A99: =PEDIDOS!A99 -> 26030 | B99: =PEDIDOS!B99 -> 46086 | C99: =PEDIDOS!C99 | D99: =PEDIDOS!D99 -> THE CURIOUS SKIN | E99: =PEDIDOS!E99 -> SERUM BOOSTER Telangyn | F99: =PEDIDOS!G99 -> 500 | G99: =10*48+22 -> 502 | H99: =PEDIDOS!F99 -> P | I99: =IF(G99<>"",-(F99-G99)/F99+1, "") -> 1.004 | J99: 10 x 48 + 1 x 22 | K99: 46171 | L99: =IF(N99<>"","ENTREGADO",IF(K99<>"","LISTO PARA ENTREGAR","EN PROCESO" )) -> ENTREGADO | M99: Y26046 | N99: 3506
A100: =PEDIDOS!A100 -> 26030 | B100: =PEDIDOS!B100 -> 46086 | C100: =PEDIDOS!C100 | D100: =PEDIDOS!D100 -> THE CURIOUS SKIN | E100: =PEDIDOS!E100 -> CARROT OIL | F100: =PEDIDOS!G100 -> 500 | G100: =20*24+22 -> 502 | H100: =PEDIDOS!F100 -> P | I100: =IF(G100<>"",-(F100-G100)/F100+1, "") -> 1.004 | J100: 20 x 24 + 1 x 22 | K100: 46171 | L100: =IF(N100<>"","ENTREGADO",IF(K100<>"","LISTO PARA ENTREGAR","EN PROCESO" )) -> ENTREGADO | M100: Y26047 | N100: 3506
...

Sheet INGRESOS
A1: FECHA | B1: N°OC | C1: CLIENTE | D1: PRODUCTO | E1: Q | H1: ME | I1: FECHA ME | J1: MP | K1: FECHA MP | L1: OBSERVACIONES
A2: =PEDIDOS!B2 -> 46035 | B2: =PEDIDOS!C2 -> 163 | C2: =PEDIDOS!D2 -> THE MINIMAL CO | D2: =PEDIDOS!E2 -> MILKY TONER | E2: =PEDIDOS!G2 -> 900 | H2: COMPLETO | I2: 46040
A3: =PEDIDOS!B3 -> 46035 | B3: =PEDIDOS!C3 -> 14297 | C3: =PEDIDOS!D3 -> JACTANS | D3: =PEDIDOS!E3 -> JS-941 AGUA MICELAR BIFASCIA | E3: =PEDIDOS!G3 -> 1000 | H3: COMPLETO | I3: 46038
A4: =PEDIDOS!B4 -> 46035 | B4: =PEDIDOS!C4 -> 15074 | C4: =PEDIDOS!D4 -> THELMA Y LOUISE | D4: =PEDIDOS!E4 -> AGUA TERMAL | E4: =PEDIDOS!G4 -> 2940 | H4: COMPLETO | I4: 46044
A5: =PEDIDOS!B5 -> 46035 | B5: =PEDIDOS!C5 | C5: =PEDIDOS!D5 -> LIORA | D5: =PEDIDOS!E5 -> CREMA PARA PEINAR RULOS | E5: =PEDIDOS!G5 -> 170 | H5: COMPLETO | I5: 30/02/2026
A6: =PEDIDOS!B6 -> 46042 | B6: =PEDIDOS!C6 -> P01203 | C6: =PEDIDOS!D6 -> BIOESENCIA | D6: =PEDIDOS!E6 -> SERUM ORIGENES | E6: =PEDIDOS!G6 -> 1600 | H6: COMPLETO | I6: 46027
A7: =PEDIDOS!B7 -> 46042 | B7: =PEDIDOS!C7 | C7: =PEDIDOS!D7 -> WSABI | D7: =PEDIDOS!E7 -> SERUM INTIMO | E7: =PEDIDOS!G7 -> 300 | H7: COMPLETO | I7: 46071
A8: =PEDIDOS!B8 -> 46042 | B8: =PEDIDOS!C8 | C8: =PEDIDOS!D8 -> MERMER | D8: =PEDIDOS!E8 -> ACEITE CORPORAL LAVANDA | E8: =PEDIDOS!G8 -> 300 | H8: COMPLETO | I8: 46042
A9: =PEDIDOS!B9 -> 46042 | B9: =PEDIDOS!C9 | C9: =PEDIDOS!D9 -> MERMER | D9: =PEDIDOS!E9 -> ACEITE CORPORAL ALMENDRA | E9: =PEDIDOS!G9 -> 300 | H9: COMPLETO | I9: 46042
A10: =PEDIDOS!B10 -> 46042 | B10: =PEDIDOS!C10 | C10: =PEDIDOS!D10 -> MERMER | D10: =PEDIDOS!E10 -> ACEITE CORPORAL ROSAS | E10: =PEDIDOS!G10 -> 300 | H10: COMPLETO | I10: 46042
A11: =PEDIDOS!B11 -> 46042 | B11: =PEDIDOS!C11 | C11: =PEDIDOS!D11 -> MERMER | D11: =PEDIDOS!E11 -> ACEITE CORPORAL SESAMO | E11: =PEDIDOS!G11 -> 300 | H11: COMPLETO | I11: 46042
A12: =PEDIDOS!B12 -> 46042 | B12: =PEDIDOS!C12 | C12: =PEDIDOS!D12 -> MERMER | D12: =PEDIDOS!E12 -> ACEITE CORPORAL INCIENSO | E12: =PEDIDOS!G12 -> 300 | H12: COMPLETO | I12: 46042
A13: =PEDIDOS!B13 -> 46042 | B13: =PEDIDOS!C13 | C13: =PEDIDOS!D13 -> MERMER | D13: =PEDIDOS!E13 -> ACEITE CORPORAL ARNICA | E13: =PEDIDOS!G13 -> 300 | H13: COMPLETO | I13: 46042
A14: =PEDIDOS!B14 -> 46042 | B14: =PEDIDOS!C14 | C14: =PEDIDOS!D14 -> MERMER | D14: =PEDIDOS!E14 -> LOCION CAPILAR | E14: =PEDIDOS!G14 -> 400 | H14: COMPLETO | I14: 46042
A15: =PEDIDOS!B15 -> 46042 | B15: =PEDIDOS!C15 | C15: =PEDIDOS!D15 -> MERMER | D15: =PEDIDOS!E15 -> SERUM CAPILAR | E15: =PEDIDOS!G15 -> 400 | H15: COMPLETO | I15: 46042
A16: =PEDIDOS!B16 -> 46049 | B16: =PEDIDOS!C16 -> 1708 | C16: =PEDIDOS!D16 -> LABORATORIO ONCE | D16: =PEDIDOS!E16 -> SERUM ACIDO HIALURONICO + NIACINAMIDA | E16: =PEDIDOS!G16 -> 1653 | H16: COMPLETO | I16: 46035
A17: =PEDIDOS!B17 -> 46050 | B17: =PEDIDOS!C17 -> 15098 | C17: =PEDIDOS!D17 -> THELMA Y LOUISE | D17: =PEDIDOS!E17 -> CREMA BIFASICA CHERRY | E17: =PEDIDOS!G17 -> 1640 | H17: COMPLETO | I17: 46052
A18: =PEDIDOS!B18 -> 46052 | B18: =PEDIDOS!C18 | C18: =PEDIDOS!D18 -> ALL BEAUTY | D18: =PEDIDOS!E18 -> SERUM ACIDO HIALURONICO | E18: =PEDIDOS!G18 -> 1000 | H18: COMPLETO
A19: =PEDIDOS!B19 -> 46044 | B19: =PEDIDOS!C19 | C19: =PEDIDOS!D19 -> DWUAM | D19: =PEDIDOS!E19 -> BASE DE MAQUILLAJE TONO 1 | E19: =PEDIDOS!G19 -> 500 | H19: COMPLETO
A20: =PEDIDOS!B20 -> 46071 | B20: =PEDIDOS!C20 -> 6433 | C20: =PEDIDOS!D20 -> HEBURN | D20: =PEDIDOS!E20 -> BRUMA FIJADORA de MAQUILLAJE x 125 cc | E20: =PEDIDOS!G20 -> 600 | H20: COMPLETO
A21: =PEDIDOS!B21 -> 46052 | B21: =PEDIDOS!C21 | C21: =PEDIDOS!D21 -> ALL BEAUTY | D21: =PEDIDOS!E21 -> CREMA FACIAL HIDRATANTE X 50gr (DIA) | E21: =PEDIDOS!G21 -> 1000 | H21: COMPLETO | I21: 30/02/2026
A22: =PEDIDOS!B22 -> 46052 | B22: =PEDIDOS!C22 | C22: =PEDIDOS!D22 -> ALL BEAUTY | D22: =PEDIDOS!E22 -> UNGÜENTO POMADA OLEO 30 + 1 X 10gr | E22: =PEDIDOS!G22 -> 1000 | H22: COMPLETO | I22: 30/02/2026
A23: =PEDIDOS!B23 -> 46052 | B23: =PEDIDOS!C23 | C23: =PEDIDOS!D23 -> ALL BEAUTY | D23: =PEDIDOS!E23 -> CREMA DE ORDEÑE X 300gr | E23: =PEDIDOS!G23 -> 1500 | H23: COMPLETO | I23: 30/02/2026
A24: =PEDIDOS!B24 -> 46043 | B24: =PEDIDOS!C24 -> 103 | C24: =PEDIDOS!D24 -> UNICA | D24: =PEDIDOS!E24 -> CREMA ENEBRO | E24: =PEDIDOS!G24 -> 500 | H24: COMPLETO | I24: 46055
A25: =PEDIDOS!B25 -> 46066 | B25: =PEDIDOS!C25 -> 15114 | C25: =PEDIDOS!D25 -> THELMA Y LOUISE | D25: =PEDIDOS!E25 -> SERUM BIFASICO JOJOBA-POMELO | E25: =PEDIDOS!G25 -> 3024 | H25: COMPLETO | I25: 46084
A26: =PEDIDOS!B26 -> 46066 | B26: =PEDIDOS!C26 -> 15114 | C26: =PEDIDOS!D26 -> THELMA Y LOUISE | D26: =PEDIDOS!E26 -> SERUM BIFASICO PEPINO-HAMAMELIS | E26: =PEDIDOS!G26 -> 3024 | H26: COMPLETO | I26: 46084
A27: =PEDIDOS!B27 -> 46066 | B27: =PEDIDOS!C27 -> 15114 | C27: =PEDIDOS!D27 -> THELMA Y LOUISE | D27: =PEDIDOS!E27 -> SERUM BIFASICO LAVANDA-BLUEBERRY | E27: =PEDIDOS!G27 -> 3024 | H27: COMPLETO | I27: 46084
A28: =PEDIDOS!B28 -> 46066 | B28: =PEDIDOS!C28 -> 15114 | C28: =PEDIDOS!D28 -> THELMA Y LOUISE | D28: =PEDIDOS!E28 -> SERUM BIFASICO ROSA MOSQUETA-ROSAS | E28: =PEDIDOS!G28 -> 3024 | H28: COMPLETO | I28: 46084
A29: =PEDIDOS!B29 -> 46071 | B29: =PEDIDOS!C29 -> 772 | C29: =PEDIDOS!D29 -> CAV | D29: =PEDIDOS!E29 -> SHAMPOO BIO MOLECULAR X400ML VITAMIN SHOCK | E29: =PEDIDOS!G29 -> 700
A30: =PEDIDOS!B30 -> 46071 | B30: =PEDIDOS!C30 -> 772 | C30: =PEDIDOS!D30 -> CAV | D30: =PEDIDOS!E30 -> SERUM BIO MOLUECULAR X30ML VITAMIN SHOCK | E30: =PEDIDOS!G30 -> 300
A31: =PEDIDOS!B31 -> 46071 | B31: =PEDIDOS!C31 -> 772 | C31: =PEDIDOS!D31 -> CAV | D31: =PEDIDOS!E31 -> BALSAMO X400ML BIOMIC C/ ACIDO HIAL + CAPIMAX | E31: =PEDIDOS!G31 -> 400
A32: =PEDIDOS!B32 -> 46071 | B32: =PEDIDOS!C32 -> 772 | C32: =PEDIDOS!D32 -> CAV | D32: =PEDIDOS!E32 -> MASCARA BIO MOLECULAR VITAMIN SHOCK X300ML | E32: =PEDIDOS!G32 -> 700
A33: =PEDIDOS!B33 -> 46071 | B33: =PEDIDOS!C33 -> 14329 | C33: =PEDIDOS!D33 -> JACTANS - DISNEY | D33: =PEDIDOS!E33 -> DSH-41823-Shampoo infantil fco pvc x45ml | E33: =PEDIDOS!G33 -> 3000
A34: =PEDIDOS!B34 -> 46071 | B34: =PEDIDOS!C34 -> 14329 | C34: =PEDIDOS!D34 -> JACTANS - DISNEY | D34: =PEDIDOS!E34 -> DES-41823-Espuma de Baño infantil fco pvc x45ml | E34: =PEDIDOS!G34 -> 3000
A35: =PEDIDOS!B35 -> 46071 | B35: =PEDIDOS!C35 | C35: =PEDIDOS!D35 -> BL COSMETICS | D35: =PEDIDOS!E35 -> ALISADO EXPERT | E35: =PEDIDOS!G35 -> 500 | H35: COMPLETO | I35: 46076
A36: =PEDIDOS!B36 -> 46071 | B36: =PEDIDOS!C36 | C36: =PEDIDOS!D36 -> BL COSMETICS | D36: =PEDIDOS!E36 -> ALISADO EXPERT X1KG | E36: =PEDIDOS!G36 -> 500 | H36: COMPLETO | I36: 46076
A37: =PEDIDOS!B37 -> 46071 | B37: =PEDIDOS!C37 | C37: =PEDIDOS!D37 -> BL COSMETICS | D37: =PEDIDOS!E37 -> ALISADO KERATIN | E37: =PEDIDOS!G37 -> 1000 | H37: COMPLETO | I37: 46076
A38: =PEDIDOS!B38 -> 46071 | B38: =PEDIDOS!C38 -> P00147 | C38: =PEDIDOS!D38 -> LURE | D38: =PEDIDOS!E38 -> GOLD MASK | E38: =PEDIDOS!G38 -> 600 | H38: COMPLETO | I38: 46072
A39: =PEDIDOS!B39 -> 46071 | B39: =PEDIDOS!C39 -> TCL 2025-02-28 | C39: =PEDIDOS!D39 -> THE CHEMIST LOOK | D39: =PEDIDOS!E39 -> MANCHAS 5ML - PIGMENT PROTOCOL | E39: =PEDIDOS!G39 -> 1000
A40: =PEDIDOS!B40 -> 46071 | B40: =PEDIDOS!C40 -> TCL 2025-02-28 | C40: =PEDIDOS!D40 -> THE CHEMIST LOOK | D40: =PEDIDOS!E40 -> MANCHAS 30ML - PIGMENT PROTOCOL | E40: =PEDIDOS!G40 -> 2000
A41: =PEDIDOS!B41 -> 46071 | B41: =PEDIDOS!C41 -> TCL 2025-02-28 | C41: =PEDIDOS!D41 -> THE CHEMIST LOOK | D41: =PEDIDOS!E41 -> BOOSTER VIT C/GLUT | E41: =PEDIDOS!G41 -> 3000 | H41: COMPLETO | I41: 46080
A42: =PEDIDOS!B42 -> 46071 | B42: =PEDIDOS!C42 -> TCL 2025-02-28 | C42: =PEDIDOS!D42 -> THE CHEMIST LOOK | D42: =PEDIDOS!E42 -> BOOSTER NIACI/ZN | E42: =PEDIDOS!G42 -> 3500 | H42: COMPLETO | I42: 46080
A43: =PEDIDOS!B43 -> 46071 | B43: =PEDIDOS!C43 -> TCL 2025-02-28 | C43: =PEDIDOS!D43 -> THE CHEMIST LOOK | D43: =PEDIDOS!E43 -> BOOSTER HYALU-A/SI | E43: =PEDIDOS!G43 -> 2400 | H43: COMPLETO | I43: 46080
A44: =PEDIDOS!B44 -> 46071 | B44: =PEDIDOS!C44 -> TCL 2025-02-28 | C44: =PEDIDOS!D44 -> THE CHEMIST LOOK | D44: =PEDIDOS!E44 -> BOOSTER MUNAP-18 | E44: =PEDIDOS!G44 -> 3000 | H44: COMPLETO | I44: 46080
A45: =PEDIDOS!B45 -> 46071 | B45: =PEDIDOS!C45 -> TCL 2025-02-28 | C45: =PEDIDOS!D45 -> THE CHEMIST LOOK | D45: =PEDIDOS!E45 -> TAN BOOSTER | E45: =PEDIDOS!G45 -> 500
A46: =PEDIDOS!B46 -> 46071 | B46: =PEDIDOS!C46 -> TCL 2025-02-28 | C46: =PEDIDOS!D46 -> THE CHEMIST LOOK | D46: =PEDIDOS!E46 -> BOOSTER RETIN | E46: =PEDIDOS!G46 -> 2000
A47: =PEDIDOS!B47 -> 46071 | B47: =PEDIDOS!C47 -> TCL 2025-02-28 | C47: =PEDIDOS!D47 -> THE CHEMIST LOOK | D47: =PEDIDOS!E47 -> 2ND SKIN | E47: =PEDIDOS!G47 -> 1000
A48: =PEDIDOS!B48 -> 46071 | B48: =PEDIDOS!C48 -> 14331 | C48: =PEDIDOS!D48 -> JACTANS | D48: =PEDIDOS!E48 -> JS-736 BRUMA FIJADORA FACIAL | E48: =PEDIDOS!G48 -> 2000 | H48: COMPLETO
A49: =PEDIDOS!B49 -> 46072 | B49: =PEDIDOS!C49 | C49: =PEDIDOS!D49 -> KALA | D49: =PEDIDOS!E49 -> AGUA DE ROSAS | E49: =PEDIDOS!G49 -> 650 | H49: COMPLETO
A50: =PEDIDOS!B50 -> 46073 | B50: =PEDIDOS!C50 | C50: =PEDIDOS!D50 -> INTENCIONAL | D50: =PEDIDOS!E50 -> CREMA DE ORDEÑE | E50: =PEDIDOS!G50 -> 2000 | H50: COMPLETO
A51: =PEDIDOS!B51 -> 46073 | B51: =PEDIDOS!C51 -> P01256 | C51: =PEDIDOS!D51 -> BIOESENCIA | D51: =PEDIDOS!E51 -> CREMA BABA DE CARACOL | E51: =PEDIDOS!G51 -> 1000 | H51: COMPLETO
A52: =PEDIDOS!B52 -> 46042 | B52: =PEDIDOS!C52 -> P01203 | C52: =PEDIDOS!D52 -> BIOESENCIA | D52: =PEDIDOS!E52 -> SHAMPOO BABY | E52: =PEDIDOS!G52 -> 500 | H52: COMPLETO
A53: =PEDIDOS!B53 -> 46042 | B53: =PEDIDOS!C53 -> P01203 | C53: =PEDIDOS!D53 -> BIOESENCIA | D53: =PEDIDOS!E53 -> SERUM PROBIOTICOS | E53: =PEDIDOS!G53 -> 1000 | H53: COMPLETO
A54: =PEDIDOS!B54 -> 46073 | B54: =PEDIDOS!C54 | C54: =PEDIDOS!D54 -> OSSPRET | D54: =PEDIDOS!E54 -> CREMA DE ORDEÑE | E54: =PEDIDOS!G54 -> 300
A55: =PEDIDOS!B55 -> 46073 | B55: =PEDIDOS!C55 -> P01256 | C55: =PEDIDOS!D55 -> BIOESENCIA | D55: =PEDIDOS!E55 -> UNGUENTO PROPOLEO | E55: =PEDIDOS!G55 -> 1000 | H55: COMPLETO
A56: =PEDIDOS!B56 -> 46073 | B56: =PEDIDOS!C56 -> P01257 | C56: =PEDIDOS!D56 -> BIOESENCIA | D56: =PEDIDOS!E56 -> BAÑO BE KERATINA BE VEGAN | E56: =PEDIDOS!G56 -> 1000 | H56: COMPLETO
A57: =PEDIDOS!B57 -> 46073 | B57: =PEDIDOS!C57 -> P01258 | C57: =PEDIDOS!D57 -> BIOESENCIA | D57: =PEDIDOS!E57 -> REPARADOR DE PUNTAS | E57: =PEDIDOS!G57 -> 1000 | H57: COMPLETO
A58: =PEDIDOS!B58 -> 46073 | B58: =PEDIDOS!C58 -> P01259 | C58: =PEDIDOS!D58 -> BIOESENCIA | D58: =PEDIDOS!E58 -> BRUMA FACIAL ORIGENES | E58: =PEDIDOS!G58 -> 1000 | H58: COMPLETO
A59: =PEDIDOS!B59 -> 46073 | B59: =PEDIDOS!C59 -> P01260 | C59: =PEDIDOS!D59 -> BIOESENCIA | D59: =PEDIDOS!E59 -> EMULSION CORPORAL PROBIOTICOS | E59: =PEDIDOS!G59 -> 1000 | H59: COMPLETO
A60: =PEDIDOS!B60 -> 46073 | B60: =PEDIDOS!C60 -> P01261 | C60: =PEDIDOS!D60 -> BIOESENCIA | D60: =PEDIDOS!E60 -> CREMA DIA/NOCHE ULTRAHIDRATANTE VEGAN | E60: =PEDIDOS!G60 -> 1000 | H60: COMPLETO
A61: =PEDIDOS!B61 -> 46076 | B61: =PEDIDOS!C61 | C61: =PEDIDOS!D61 -> AGUEDA REY - ALMA HAIR | D61: =PEDIDOS!E61 -> ACONDICIONADOR CON EXTRACTO DE CEBOLLA | E61: =PEDIDOS!G61 -> 1050
A62: =PEDIDOS!B62 -> 46076 | B62: =PEDIDOS!C62 -> 774 | C62: =PEDIDOS!D62 -> CAV | D62: =PEDIDOS!E62 -> CRISTAL LIQ (BRIGHT CRYSTAL) CAV EXPRESSION | E62: =PEDIDOS!G62 -> 250
A63: =PEDIDOS!B63 -> 46076 | B63: =PEDIDOS!C63 -> 774 | C63: =PEDIDOS!D63 -> CAV | D63: =PEDIDOS!E63 -> Protector C-Plex x150 Paso 3 | E63: =PEDIDOS!G63 -> 300
A64: =PEDIDOS!B64 -> 46076 | B64: =PEDIDOS!C64 | C64: =PEDIDOS!D64 -> WSABI | D64: =PEDIDOS!E64 -> CONTORNO DE OJOS | E64: =PEDIDOS!G64 -> 480 | H64: COMPLETO
A65: =PEDIDOS!B65 -> 46076 | B65: =PEDIDOS!C65 | C65: =PEDIDOS!D65 -> WSABI | D65: =PEDIDOS!E65 -> LECHE DE LIMPIEZA | E65: =PEDIDOS!G65 -> 500 | H65: COMPLETO
A66: =PEDIDOS!B66 -> 46076 | B66: =PEDIDOS!C66 | C66: =PEDIDOS!D66 -> WSABI | D66: =PEDIDOS!E66 -> SERUM ANTIOXIDANTE VIT C | E66: =PEDIDOS!G66 -> 300 | H66: COMPLETO
A67: =PEDIDOS!B67 -> 46076 | B67: =PEDIDOS!C67 | C67: =PEDIDOS!D67 -> WSABI | D67: =PEDIDOS!E67 -> TONICO CORPORAL EQUILIBRIO | E67: =PEDIDOS!G67 -> 1000 | H67: COMPLETO
A68: =PEDIDOS!B68 -> 46063 | B68: =PEDIDOS!C68 -> 15125 | C68: =PEDIDOS!D68 -> THELMA Y LOUISE | D68: =PEDIDOS!E68 -> SERUM ANTIAGE | E68: =PEDIDOS!G68 -> 2100 | H68: COMPLETO
A69: =PEDIDOS!B69 -> 46063 | B69: =PEDIDOS!C69 -> 15125 | C69: =PEDIDOS!D69 -> THELMA Y LOUISE | D69: =PEDIDOS!E69 -> SERUM DESCONGESTIVO | E69: =PEDIDOS!G69 -> 2100 | H69: COMPLETO
A70: =PEDIDOS!B70 -> 46076 | B70: =PEDIDOS!C70 -> 775 | C70: =PEDIDOS!D70 -> CAV | D70: =PEDIDOS!E70 -> Rebond C-Plex CAV x 500 ml (Paso 1) | E70: =PEDIDOS!G70 -> 200
A71: =PEDIDOS!B71 -> 46076 | B71: =PEDIDOS!C71 -> 775 | C71: =PEDIDOS!D71 -> CAV | D71: =PEDIDOS!E71 -> Finishing C-Plex CAV x 500 ml (Paso 2) | E71: =PEDIDOS!G71 -> 400
A72: =PEDIDOS!B72 -> 46077 | B72: =PEDIDOS!C72 -> 1704 | C72: =PEDIDOS!D72 -> LABORATORIO ONCE | D72: =PEDIDOS!E72 -> ALBA SERUM X 30 ML DRA ROSSI | E72: =PEDIDOS!G72 -> 300 | H72: COMPLETO
A73: =PEDIDOS!B73 -> 46078 | B73: =PEDIDOS!C73 | C73: =PEDIDOS!D73 -> UNICA | D73: =PEDIDOS!E73 -> CREMA CORPORAL HUMECTANTE KARITE | E73: =PEDIDOS!G73 -> 500 | H73: COMPLETO
A74: =PEDIDOS!B74 -> 46078 | B74: =PEDIDOS!C74 | C74: =PEDIDOS!D74 -> OLANN | D74: =PEDIDOS!E74 -> Serum hialurónico 30 ml | E74: =PEDIDOS!G74 -> 250 | H74: COMPLETO
A75: =PEDIDOS!B75 -> 46078 | B75: =PEDIDOS!C75 | C75: =PEDIDOS!D75 -> OLANN | D75: =PEDIDOS!E75 -> BRUMA FACIAL | E75: =PEDIDOS!G75 -> 250 | H75: COMPLETO
A76: =PEDIDOS!B76 -> 46078 | B76: =PEDIDOS!C76 | C76: =PEDIDOS!D76 -> OLANN | D76: =PEDIDOS!E76 -> CREMA FACIAL DE DIA ULTRAHUMECTANTE | E76: =PEDIDOS!G76 -> 250 | H76: COMPLETO
A77: =PEDIDOS!B77 -> 46078 | B77: =PEDIDOS!C77 | C77: =PEDIDOS!D77 -> OLANN | D77: =PEDIDOS!E77 -> CREMA FACIAL DE NOCHE TENSORA | E77: =PEDIDOS!G77 -> 250 | H77: COMPLETO
A78: =PEDIDOS!B78 -> 46078 | B78: =PEDIDOS!C78 | C78: =PEDIDOS!D78 -> OLANN | D78: =PEDIDOS!E78 -> CONTORNO DE OJOS | E78: =PEDIDOS!G78 -> 250 | H78: COMPLETO
A79: =PEDIDOS!B79 -> 46083 | B79: =PEDIDOS!C79 | C79: =PEDIDOS!D79 -> ECODERM - AGUAZU | D79: =PEDIDOS!E79 -> ESPUMA DE BAÑO ADULTO | E79: =PEDIDOS!G79 -> 200 | H79: COMPLETO
A80: =PEDIDOS!B80 -> 46083 | B80: =PEDIDOS!C80 | C80: =PEDIDOS!D80 -> ECODERM - AGUAZU | D80: =PEDIDOS!E80 -> ESPUMA DE BAÑO BALLENA | E80: =PEDIDOS!G80 -> 200 | H80: COMPLETO
A81: =PEDIDOS!B81 -> 46083 | B81: =PEDIDOS!C81 | C81: =PEDIDOS!D81 -> ECODERM - AGUAZU | D81: =PEDIDOS!E81 -> ESPUMA DE BAÑO BALLENA X500 | E81: =PEDIDOS!G81 -> 100 | H81: COMPLETO
A82: =PEDIDOS!B82 -> 46083 | B82: =PEDIDOS!C82 | C82: =PEDIDOS!D82 -> ECODERM - AGUAZU | D82: =PEDIDOS!E82 -> ESPUMA DE BAÑO ADULTO X500 | E82: =PEDIDOS!G82 -> 100 | H82: COMPLETO
A83: =PEDIDOS!B83 -> 46083 | B83: =PEDIDOS!C83 | C83: =PEDIDOS!D83 -> ECODERM - AGUAZU | D83: =PEDIDOS!E83 -> BALSAMO HERBAL | E83: =PEDIDOS!G83 -> 300 | H83: COMPLETO
... A97: =PEDIDOS!B97 -> 46086 | B97: =PEDIDOS!C97 -> 1080 | C97: =PEDIDOS!D97 -> NIZA | D97: =PEDIDOS!E97 -> CLEAR ACNE LOTION | E97: =PEDIDOS!G97 -> 300 | H97: COMPLETO
A98: =PEDIDOS!B98 -> 46086 | B98: =PEDIDOS!C98 -> 1080 | C98: =PEDIDOS!D98 -> NIZA | D98: =PEDIDOS!E98 -> SIGNATURE AGE REVERSE | E98: =PEDIDOS!G98 -> 500
A99: =PEDIDOS!B99 -> 46086 | B99: =PEDIDOS!C99 | C99: =PEDIDOS!D99 -> THE CURIOUS SKIN | D99: =PEDIDOS!E99 -> SERUM BOOSTER Telangyn | E99: =PEDIDOS!G99 -> 500
A100: =PEDIDOS!B100 -> 46086 | B100: =PEDIDOS!C100 | C100: =PEDIDOS!D100 -> THE CURIOUS SKIN | D100: =PEDIDOS!E100 -> CARROT OIL | E100: =PEDIDOS!G100 -> 500
A101: =PEDIDOS!B101 -> 46087 | B101: =PEDIDOS!C101 | C101: =PEDIDOS!D101 -> WSABI | D101: =PEDIDOS!E101 -> CREMA HIDTANATE LIGERA | E101: =PEDIDOS!G101 -> 500
A102: =PEDIDOS!B102 -> 46087 | B102: =PEDIDOS!C102 -> 1594 | C102: =PEDIDOS!D102 -> NE | D102: =PEDIDOS!E102 -> BRUMA FACIAL | E102: =PEDIDOS!G102 -> 500 | H102: COMPLETO
A103: =PEDIDOS!B103 -> 46087 | B103: =PEDIDOS!C103 -> 1594 | C103: =PEDIDOS!D103 -> NE | D103: =PEDIDOS!E103 -> CREMA CORPORAL | E103: =PEDIDOS!G103 -> 500 | H103: COMPLETO
A104: =PEDIDOS!B104 -> 46087 | B104: =PEDIDOS!C104 -> 1597 | C104: =PEDIDOS!D104 -> NE | D104: =PEDIDOS!E104 -> CREMA FACIAL NOCHE | E104: =PEDIDOS!G104 -> 500 | H104: COMPLETO
A105: =PEDIDOS!B105 -> 46087 | B105: =PEDIDOS!C105 -> 140 | C105: =PEDIDOS!D105 -> ICONO | D105: =PEDIDOS!E105 -> MASCARA DESINCRUSTANTE DE PAPAYA x 250GR. | E105: =PEDIDOS!G105 -> 3000
A106: =PEDIDOS!B106 -> 46087 | B106: =PEDIDOS!C106 -> 140 | C106: =PEDIDOS!D106 -> ICONO | D106: =PEDIDOS!E106 -> CREMA EFECTO TENSOR x 50GR. | E106: =PEDIDOS!G106 -> 2000
A107: =PEDIDOS!B107 -> 46090 | B107: =PEDIDOS!C107 -> 15170/15169 | C107: =PEDIDOS!D107 -> THELMA Y LOUISE | D107: =PEDIDOS!E107 -> ALCOHOL EN GEL CHICLE FRUTILLA | E107: =PEDIDOS!G107 -> 4000
A108: =PEDIDOS!B108 -> 46090 | B108: =PEDIDOS!C108 -> 15170/15169 | C108: =PEDIDOS!D108 -> THELMA Y LOUISE | D108: =PEDIDOS!E108 -> ALCOHOL EN GEL CHERRY | E108: =PEDIDOS!G108 -> 5000
A109: =PEDIDOS!B109 -> 46090 | B109: =PEDIDOS!C109 -> 15170 | C109: =PEDIDOS!D109 -> THELMA Y LOUISE | D109: =PEDIDOS!E109 -> ALCOHOL EN GEL CAPUCHINO - esencia vany love | E109: =PEDIDOS!G109 -> 3000
A110: =PEDIDOS!B110 -> 46090 | B110: =PEDIDOS!C110 -> 15170 | C110: =PEDIDOS!D110 -> THELMA Y LOUISE | D110: =PEDIDOS!E110 -> ALCOHOL EN GL NEUTRO PERRO SALCHICHA | E110: =PEDIDOS!G110 -> 3000
A111: =PEDIDOS!B111 -> 46090 | B111: =PEDIDOS!C111 | C111: =PEDIDOS!D111 -> PROFESSIONAL BEAUTY | D111: =PEDIDOS!E111 -> ADVANCE ACIDO HIALURONICO 1% | E111: =PEDIDOS!G111 -> 500
A112: =PEDIDOS!B112 -> 46090 | B112: =PEDIDOS!C112 | C112: =PEDIDOS!D112 -> PROFESSIONAL BEAUTY | D112: =PEDIDOS!E112 -> ADVANCE SILICIO+ OLIGOELEMENTOS | E112: =PEDIDOS!G112 -> 500
A113: =PEDIDOS!B113 -> 46090 | B113: =PEDIDOS!C113 | C113: =PEDIDOS!D113 -> PROFESSIONAL BEAUTY | D113: =PEDIDOS!E113 -> ADVANCE VIT C | E113: =PEDIDOS!G113 -> 500
...

Sheet KPI
A1: Fecha | B1: N° OC | C1: CLIENTE | D1: PRODUCTO | E1: Sector | F1: N° LOTE | G1: LEAD TIME | H1: NIVEL DE SERVICIO | I1: Reclamo
A2: =PEDIDOS!B2 -> 46035 | B2: =PEDIDOS!C2 -> 163 | C2: =PEDIDOS!D2 -> THE MINIMAL CO | D2: =PEDIDOS!E2 -> MILKY TONER | E2: =PEDIDOS!F2 -> P | F2: =PEDIDOS!M2 -> F26021 | G2: =-PEDIDOS!B2+EXPEDICION!K2 -> 41 | H2: =EXPEDICION!I2 -> 0.99888889
A3: =PEDIDOS!B3 -> 46035 | B3: =PEDIDOS!C3 -> 14297 | C3: =PEDIDOS!D3 -> JACTANS | D3: =PEDIDOS!E3 -> JS-941 AGUA MICELAR BIFASCIA | E3: =PEDIDOS!F3 -> P | F3: =PEDIDOS!M3 -> F26031 | G3: =-PEDIDOS!B3+EXPEDICION!K3 -> 45 | H3: =EXPEDICION!I3 -> 1.011
A4: =PEDIDOS!B4 -> 46035 | B4: =PEDIDOS!C4 -> 15074 | C4: =PEDIDOS!D4 -> THELMA Y LOUISE | D4: =PEDIDOS!E4 -> AGUA TERMAL | E4: =PEDIDOS!F4 -> P | F4: =PEDIDOS!M4 -> F26041 | G4: =-PEDIDOS!B4+EXPEDICION!K4 -> 48 | H4: =EXPEDICION!I4 -> 0.99047619
A5: =PEDIDOS!B5 -> 46035 | B5: =PEDIDOS!C5 | C5: =PEDIDOS!D5 -> LIORA | D5: =PEDIDOS!E5 -> CREMA PARA PEINAR RULOS | E5: =PEDIDOS!F5 -> P | F5: =PEDIDOS!M5 -> Y26039 | G5: =-PEDIDOS!B5+EXPEDICION!K5 -> 126 | H5: =EXPEDICION!I5 -> 0.86470588
A6: =PEDIDOS!B6 -> 46042 | B6: =PEDIDOS!C6 -> P01203 | C6: =PEDIDOS!D6 -> BIOESENCIA | D6: =PEDIDOS!E6 -> SERUM ORIGENES | E6: =PEDIDOS!F6 -> P | F6: =PEDIDOS!M6 -> 240201 | G6: =-PEDIDOS!B6+EXPEDICION!K6 -> 35 | H6: =EXPEDICION!I6 -> 1.00125
A7: =PEDIDOS!B7 -> 46042 | B7: =PEDIDOS!C7 | C7: =PEDIDOS!D7 -> WSABI | D7: =PEDIDOS!E7 -> SERUM INTIMO | E7: =PEDIDOS!F7 -> P | F7: =PEDIDOS!M7 -> F26049 | G7: =-PEDIDOS!B7+EXPEDICION!K7 -> 45 | H7: =EXPEDICION!I7 -> 0.97666667
A8: =PEDIDOS!B8 -> 46042 | B8: =PEDIDOS!C8 | C8: =PEDIDOS!D8 -> MERMER | D8: =PEDIDOS!E8 -> ACEITE CORPORAL LAVANDA | E8: =PEDIDOS!F8 -> P | F8: =PEDIDOS!M8 -> E26087 | G8: =-PEDIDOS!B8+EXPEDICION!K8 -> 8 | H8: =EXPEDICION!I8 -> 1.6966667
A9: =PEDIDOS!B9 -> 46042 | B9: =PEDIDOS!C9 | C9: =PEDIDOS!D9 -> MERMER | D9: =PEDIDOS!E9 -> ACEITE CORPORAL ALMENDRA | E9: =PEDIDOS!F9 -> P | F9: =PEDIDOS!M9 -> E26088 | G9: =-PEDIDOS!B9+EXPEDICION!K9 -> 8 | H9: =EXPEDICION!I9 -> 1.02
A10: =PEDIDOS!B10 -> 46042 | B10: =PEDIDOS!C10 | C10: =PEDIDOS!D10 -> MERMER | D10: =PEDIDOS!E10 -> ACEITE CORPORAL ROSAS | E10: =PEDIDOS!F10 -> P | F10: =PEDIDOS!M10 -> E26089 | G10: =-PEDIDOS!B10+EXPEDICION!K10 -> 8 | H10: =EXPEDICION!I10 -> 1.01
A11: =PEDIDOS!B11 -> 46042 | B11: =PEDIDOS!C11 | C11: =PEDIDOS!D11 -> MERMER | D11: =PEDIDOS!E11 -> ACEITE CORPORAL SESAMO | E11: =PEDIDOS!F11 -> P | F11: =PEDIDOS!M11 -> E26090 | G11: =-PEDIDOS!B11+EXPEDICION!K11 -> 8 | H11: =EXPEDICION!I11 -> 1.04
A12: =PEDIDOS!B12 -> 46042 | B12: =PEDIDOS!C12 | C12: =PEDIDOS!D12 -> MERMER | D12: =PEDIDOS!E12 -> ACEITE CORPORAL INCIENSO | E12: =PEDIDOS!F12 -> P | F12: =PEDIDOS!M12 -> E26091 | G12: =-PEDIDOS!B12+EXPEDICION!K12 -> 8 | H12: =EXPEDICION!I12 -> 1.02
A13: =PEDIDOS!B13 -> 46042 | B13: =PEDIDOS!C13 | C13: =PEDIDOS!D13 -> MERMER | D13: =PEDIDOS!E13 -> ACEITE CORPORAL ARNICA | E13: =PEDIDOS!F13 -> P | F13: =PEDIDOS!M13 -> E26092 | G13: =-PEDIDOS!B13+EXPEDICION!K13 -> 8 | H13: =EXPEDICION!I13 -> 1.0133333
... A422: =PEDIDOS!B422 | B422: =PEDIDOS!C422 | C422: =PEDIDOS!D422 | D422: =PEDIDOS!E422 | E422: =PEDIDOS!F422 | F422: =PEDIDOS!M422 | G422: =-PEDIDOS!B422+EXPEDICION!K422 -> 0 | H422: =EXPEDICION!I422

Sheet Dashboard
E2: DASHBOARD OPERATIVO · AÑO 2026 | N2: =TODAY() -> 46204 | R2: ANÁLISIS DE CLIENTES · PERFORMANCE OPERATIVA
B5: NIVEL DE SERVICIO | F5: PEDIDOS SIN RECLAMOS | J5: LEAD TIME PROMEDIO | N5: UNIDADES PRODUCIDAS / AÑO | R5: TOP CLIENTES POR CANTIDAD DE PEDIDOS | U5: CLIENTES CON MENOR LEAD TIME
B6: =AVERAGE(KPI!H2:H500) -> 0.98269572 | F6: =1-(COUNTIF(KPI!I2:I31,"R")/COUNTA(KPI!C2:C31)) -> 1 | J6: =AVERAGEIFS(KPI!G2:G1000,KPI!G2:G1000,">0",KPI!G2:G1000,"<100") -> 26.254658 | N6: =SUM(EXPEDICION!G2:G10966) -> 501120 | R6: CLIENTE | S6: PEDIDOS / BARRA | U6: CLIENTE | V6: DÍAS PROM / BARRA
B7: =IF(AVERAGE(KPI!H2:H1000)>=0.97,"✅ CUMPLE | Obj: ≥97%",IF(AVERAGE(KPI!H2:H1000)>=0.96,"⚠️ ATENCIÓN | Obj: ≥97%","🔴 CRÍTICO | Obj: ≥95%")) -> ✅ CUMPLE | Obj: ≥97% | F7: =IF(1-(COUNTIF(KPI!I2:I31,"R")/COUNTA(KPI!C2:C31))>=0.95,"✅ CUMPLE | Obj: >95%","⚠️ REVISAR | Obj: >95%") -> ✅ CUMPLE | Obj: >95% | J7: =IF(AVERAGEIFS(KPI!G2:G1000,KPI!G2:G1000,">0",KPI!G2:G1000,"<100")<=25,"✅ CUMPLE | Obj: ≤25 días","⚠️ ATENCIÓN | Obj: ≤25 días") -> ⚠️ ATENCIÓN | Obj: ≤25 días | N7: =TEXT(SUM(EXPEDICION!G2:G10966),"#,##0")&" unidades producidas" -> 501.120 unidades producidas | R7: =CALCULOS_CLIENTES!E2 -> THELMA Y LOUISE | S7: =IF(CALCULOS_CLIENTES!F2="","",CALCULOS_CLIENTES!F2&" "&REPT("█",ROUND(CALCULOS_CLIENTES!F2/CALCULOS_CLIENTES!$F$2*20,0))) -> 60 ████████████████████ | U7: =CALCULOS_CLIENTES!H2 -> DWUAM | V7: =IF(CALCULOS_CLIENTES!I2="","",ROUND(CALCULOS_CLIENTES!I2,1)&" d "&REPT("█",ROUND(CALCULOS_CLIENTES!I2/CALCULOS_CLIENTES!$I$11*20,0))) -> 7 d █████████
R8: =CALCULOS_CLIENTES!E3 -> CAV | S8: =IF(CALCULOS_CLIENTES!F3="","",CALCULOS_CLIENTES!F3&" "&REPT("█",ROUND(CALCULOS_CLIENTES!F3/CALCULOS_CLIENTES!$F$2*20,0))) -> 43 ██████████████ | U8: =CALCULOS_CLIENTES!H3 -> PLANTAE | V8: =IF(CALCULOS_CLIENTES!I3="","",ROUND(CALCULOS_CLIENTES!I3,1)&" d "&REPT("█",ROUND(CALCULOS_CLIENTES!I3/CALCULOS_CLIENTES!$I$11*20,0))) -> 7 d █████████
B9: ▌ GESTIÓN DE PEDIDOS | R9: =CALCULOS_CLIENTES!E4 -> PROFESSIONAL BEAUTY | S9: =IF(CALCULOS_CLIENTES!F4="","",CALCULOS_CLIENTES!F4&" "&REPT("█",ROUND(CALCULOS_CLIENTES!F4/CALCULOS_CLIENTES!$F$2*20,0))) -> 27 █████████ | U9: =CALCULOS_CLIENTES!H4 -> DERMION / FRANCO | V9: =IF(CALCULOS_CLIENTES!I4="","",ROUND(CALCULOS_CLIENTES!I4,1)&" d "&REPT("█",ROUND(CALCULOS_CLIENTES!I4/CALCULOS_CLIENTES!$I$11*20,0))) -> 8,7 d ███████████
B10: 🔄 PEDIDOS ACTIVOS | F10: ✅ ENTREGADOS | J10: 🚚 EN DESPACHO | N10: 🧴 PRODUCTOS / AÑO | R10: =CALCULOS_CLIENTES!E5 -> JACTANS - DISNEY | S10: =IF(CALCULOS_CLIENTES!F5="","",CALCULOS_CLIENTES!F5&" "&REPT("█",ROUND(CALCULOS_CLIENTES!F5/CALCULOS_CLIENTES!$F$2*20,0))) -> 55 ██████████████████ | U10: =CALCULOS_CLIENTES!H5 -> LURE | V10: =IF(CALCULOS_CLIENTES!I5="","",ROUND(CALCULOS_CLIENTES!I5,1)&" d "&REPT("█",ROUND(CALCULOS_CLIENTES!I5/CALCULOS_CLIENTES!$I$11*20,0))) -> 9 d ███████████
B11: =COUNTIF(PEDIDOS!J2:J10000,"EN PROCESO")+COUNTIF(PEDIDOS!I2:I10000,"INGRESO") -> 83 | F11: =COUNTIF(PEDIDOS!L2:L10001,"entregado") -> 329 | J11: =COUNTIF(PEDIDOS!K2:K10000,"despacho") -> 8 | N11: =COUNTA(KPI!D2:D10031) -> 420 | R11: =CALCULOS_CLIENTES!E6 -> THE CHEMIST LOOK | S11: =IF(CALCULOS_CLIENTES!F6="","",CALCULOS_CLIENTES!F6&" "&REPT("█",ROUND(CALCULOS_CLIENTES!F6/CALCULOS_CLIENTES!$F$2*20,0))) -> 17 ██████ | U11: =CALCULOS_CLIENTES!H6 -> KALA | V11: =IF(CALCULOS_CLIENTES!I6="","",ROUND(CALCULOS_CLIENTES!I6,1)&" d "&REPT("█",ROUND(CALCULOS_CLIENTES!I6/CALCULOS_CLIENTES!$I$11*20,0))) -> 14 d ██████████████████
B12: En proceso + ingresados | F12: Acumulado año 2026 | J12: Listos para entregar | N12: Ítems distintos producidos | R12: =CALCULOS_CLIENTES!E7 -> BIOESENCIA | S12: =IF(CALCULOS_CLIENTES!F7="","",CALCULOS_CLIENTES!F7&" "&REPT("█",ROUND(CALCULOS_CLIENTES!F7/CALCULOS_CLIENTES!$F$2*20,0))) -> 19 ██████ | U12: =CALCULOS_CLIENTES!H7 -> NE | V12: =IF(CALCULOS_CLIENTES!I7="","",ROUND(CALCULOS_CLIENTES!I7,1)&" d "&REPT("█",ROUND(CALCULOS_CLIENTES!I7/CALCULOS_CLIENTES!$I$11*20,0))) -> 21,5 d ███████████████████████████
R13: =CALCULOS_CLIENTES!E8 -> BL COSMETICS | S13: =IF(CALCULOS_CLIENTES!F8="","",CALCULOS_CLIENTES!F8&" "&REPT("█",ROUND(CALCULOS_CLIENTES!F8/CALCULOS_CLIENTES!$F$2*20,0))) -> 17 ██████ | U13: =CALCULOS_CLIENTES!H8 -> BEKIM | V13: =IF(CALCULOS_CLIENTES!I8="","",ROUND(CALCULOS_CLIENTES!I8,1)&" d "&REPT("█",ROUND(CALCULOS_CLIENTES!I8/CALCULOS_CLIENTES!$I$11*20,0))) -> 14 d ██████████████████
B14: ▌ PRODUCCIÓN · CONSUMO MASIVO vs. PREMIUM | R14: =CALCULOS_CLIENTES!E9 -> LUCENT | S14: =IF(CALCULOS_CLIENTES!F9="","",CALCULOS_CLIENTES!F9&" "&REPT("█",ROUND(CALCULOS_CLIENTES!F9/CALCULOS_CLIENTES!$F$2*20,0))) -> 19 ██████ | U14: =CALCULOS_CLIENTES!H9 -> HEBURN | V14: =IF(CALCULOS_CLIENTES!I9="","",ROUND(CALCULOS_CLIENTES!I9,1)&" d "&REPT("█",ROUND(CALCULOS_CLIENTES!I9/CALCULOS_CLIENTES!$I$11*20,0))) -> 14,5 d ██████████████████
B15: CONSUMO MASIVO (Sector = M) | J15: PRODUCTOS PREMIUM (Sector = P) | R15: =CALCULOS_CLIENTES!E10 -> MERMER | S15: =IF(CALCULOS_CLIENTES!F10="","",CALCULOS_CLIENTES!F10&" "&REPT("█",ROUND(CALCULOS_CLIENTES!F10/CALCULOS_CLIENTES!$F$2*20,0))) -> 8 ███ | U15: =CALCULOS_CLIENTES!H10 -> THE GLOW FACTOR | V15: =IF(CALCULOS_CLIENTES!I10="","",ROUND(CALCULOS_CLIENTES!I10,1)&" d "&REPT("█",ROUND(CALCULOS_CLIENTES!I10/CALCULOS_CLIENTES!$I$11*20,0))) -> 18 d ███████████████████████
B16: =SUMIF(PEDIDOS!F2:F1001,"M",PEDIDOS!G2:G1001) -> 450533 | F16: =SUMIF(PEDIDOS!F2:F1001,"M",PEDIDOS!G2:G1001)/(SUMIF(PEDIDOS!F2:F1001,"M",PEDIDOS!G2:G1001)+SUMIF(PEDIDOS!F2:F1001,"P",PEDIDOS!G2:G1001)) -> 0.73889847 | J16: =SUMIF(PEDIDOS!F2:F1001,"P",PEDIDOS!G2:G1001) -> 159203 | N16: =SUMIF(PEDIDOS!F2:F1001,"P",PEDIDOS!G2:G1001)/(SUMIF(PEDIDOS!F2:F1001,"M",PEDIDOS!G2:G1001)+SUMIF(PEDIDOS!F2:F1001,"P",PEDIDOS!G2:G1001)) -> 0.26110153 | R16: =CALCULOS_CLIENTES!E11 -> LABORATORIO ONCE | S16: =IF(CALCULOS_CLIENTES!F11="","",CALCULOS_CLIENTES!F11&" "&REPT("█",ROUND(CALCULOS_CLIENTES!F11/CALCULOS_CLIENTES!$F$2*20,0))) -> 8 ███ | U16: =CALCULOS_CLIENTES!H11 -> ECODERM - AGUAZU | V16: =IF(CALCULOS_CLIENTES!I11="","",ROUND(CALCULOS_CLIENTES!I11,1)&" d "&REPT("█",ROUND(CALCULOS_CLIENTES!I11/CALCULOS_CLIENTES!$I$11*20,0))) -> 16 d ████████████████████
B17: Unidades pedidas| % del total | J17: Unidades pedidas| % del total | R17: =CALCULOS_CLIENTES!E12 | U17: =CALCULOS_CLIENTES!H12 | V17: =IF(CALCULOS_CLIENTES!I12="","",ROUND(CALCULOS_CLIENTES!I12,1)&" d "&REPT("█",ROUND(CALCULOS_CLIENTES!I12/CALCULOS_CLIENTES!$I$11*20,0)))
B18: =REPT("█",ROUND(SUMIF(PEDIDOS!F2:F1001,"M",PEDIDOS!G2:G1001)/(SUMIF(PEDIDOS!F2:F1001,"M",PEDIDOS!G2:G1001)+SUMIF(PEDIDOS!F2:F1001,"P",PEDIDOS!G2:G1001))*30,0)) -> ██████████████████████ | J18: =REPT("█",ROUND(SUMIF(PEDIDOS!F2:F1001,"P",PEDIDOS!G2:G1001)/(SUMIF(PEDIDOS!F2:F1001,"M",PEDIDOS!G2:G1001)+SUMIF(PEDIDOS!F2:F1001,"P",PEDIDOS!G2:G1001))*30,0)) -> ████████ | R18: RESUMEN GERENCIAL | U18: RESUMEN GERENCIAL
R19: Total clientes activos | S19: =COUNTA(CALCULOS_CLIENTES!A2:A2000)&" clientes" -> 48 clientes | U19: Lead time prom. global | V19: =J6 -> 26.254658
B20: ▌ SEMÁFORO DE INDICADORES · ESTADO EN TIEMPO REAL
B21: INDICADOR | G21: RESULTADO ACTUAL | J21: OBJETIVO | M21: ESTADO
B22: 📊 Nivel de Servicio | G22: =AVERAGE(KPI!H2:H1000) -> 0.98269572 | J22: ≥ 97% | M22: =IF(AVERAGE(KPI!H2:H1000)>=0.97,"✅ CUMPLE",IF(AVERAGE(KPI!H2:H1000)>=0.96,"⚠️ ATENCIÓN","🔴 CRÍTICO")) -> ✅ CUMPLE
B23: ✔️ % Pedidos sin Reclamos | G23: =1-(COUNTIF(KPI!I2:I31,"R")/COUNTA(KPI!C2:C31)) -> 1 | J23: > 95% | M23: =IF(1-(COUNTIF(KPI!I2:I31,"R")/COUNTA(KPI!C2:C31))>=0.95,"✅ CUMPLE","⚠️ REVISAR") -> ✅ CUMPLE
B24: ⏱ Lead Time Promedio | G24: =AVERAGEIFS(KPI!G2:G1000,KPI!G2:G1000,">0",KPI!G2:G1000,"<100") -> 26.254658 | J24: ≤ 25 días | M24: =IF(AVERAGEIFS(KPI!G2:G1000,KPI!G2:G1000,">0",KPI!G2:G1000,"<100")<=25,"✅ CUMPLE","⚠️ ATENCIÓN") -> ⚠️ ATENCIÓN

Sheet CALCULOS_CLIENTES
A1: CLIENTE | B1: CANT_PEDIDOS | C1: LEAD_TIME_PROM | E1: TOP_CLIENTE_PEDIDOS | F1: CANT | H1: TOP_CLIENTE_LEADTIME | I1: LT_PROM
A2: AGUEDA REY - ALMA HAIR | B2: =COUNTIF(PEDIDOS!D:D,A2) -> 1 | C2: =IFERROR(AVERAGEIFS(KPI!G:G,KPI!C:C,A2,KPI!G:G,">"&0,KPI!G:G,"<"&100),"") -> 42 | E2: THELMA Y LOUISE | F2: =COUNTIF(PEDIDOS!D:D,E2) -> 60 | H2: DWUAM | I2: =IFERROR(AVERAGEIFS(KPI!G:G,KPI!C:C,H2,KPI!G:G,">"&0,KPI!G:G,"<"&100),"") -> 7
A3: AGUEDA REY - EPICA | B3: =COUNTIF(PEDIDOS!D:D,A3) -> 1 | C3: =IFERROR(AVERAGEIFS(KPI!G:G,KPI!C:C,A3,KPI!G:G,">"&0,KPI!G:G,"<"&100),"") -> 30 | E3: CAV | F3: =COUNTIF(PEDIDOS!D:D,E3) -> 43 | H3: PLANTAE | I3: =IFERROR(AVERAGEIFS(KPI!G:G,KPI!C:C,H3,KPI!G:G,">"&0,KPI!G:G,"<"&100),"") -> 7
A4: AGUEDA REY - IHC CAPILARES | B4: =COUNTIF(PEDIDOS!D:D,A4) -> 5 | C4: =IFERROR(AVERAGEIFS(KPI!G:G,KPI!C:C,A4,KPI!G:G,">"&0,KPI!G:G,"<"&100),"") -> 9 | E4: PROFESSIONAL BEAUTY | F4: =COUNTIF(PEDIDOS!D:D,E4) -> 27 | H4: DERMION / FRANCO | I4: =IFERROR(AVERAGEIFS(KPI!G:G,KPI!C:C,H4,KPI!G:G,">"&0,KPI!G:G,"<"&100),"") -> 8.6666667
A5: AGUEDA REY - IKIGAI | B5: =COUNTIF(PEDIDOS!D:D,A5) -> 2 | C5: =IFERROR(AVERAGEIFS(KPI!G:G,KPI!C:C,A5,KPI!G:G,">"&0,KPI!G:G,"<"&100),"") -> 49 | E5: JACTANS - DISNEY | F5: =COUNTIF(PEDIDOS!D:D,E5) -> 55 | H5: LURE | I5: =IFERROR(AVERAGEIFS(KPI!G:G,KPI!C:C,H5,KPI!G:G,">"&0,KPI!G:G,"<"&100),"") -> 9
A6: AGUEDA REY - YOUTHFUL | B6: =COUNTIF(PEDIDOS!D:D,A6) -> 2 | C6: =IFERROR(AVERAGEIFS(KPI!G:G,KPI!C:C,A6,KPI!G:G,">"&0,KPI!G:G,"<"&100),"") -> 22 | E6: THE CHEMIST LOOK | F6: =COUNTIF(PEDIDOS!D:D,E6) -> 17 | H6: KALA | I6: =IFERROR(AVERAGEIFS(KPI!G:G,KPI!C:C,H6,KPI!G:G,">"&0,KPI!G:G,"<"&100),"") -> 14
A7: ALL BEAUTY | B7: =COUNTIF(PEDIDOS!D:D,A7) -> 4 | C7: =IFERROR(AVERAGEIFS(KPI!G:G,KPI!C:C,A7,KPI!G:G,">"&0,KPI!G:G,"<"&100),"") -> 28.25 | E7: BIOESENCIA | F7: =COUNTIF(PEDIDOS!D:D,E7) -> 19 | H7: NE | I7: =IFERROR(AVERAGEIFS(KPI!G:G,KPI!C:C,H7,KPI!G:G,">"&0,KPI!G:G,"<"&100),"") -> 21.5
A8: BEKIM | B8: =COUNTIF(PEDIDOS!D:D,A8) -> 2 | C8: =IFERROR(AVERAGEIFS(KPI!G:G,KPI!C:C,A8,KPI!G:G,">"&0,KPI!G:G,"<"&100),"") -> 14 | E8: BL COSMETICS | F8: =COUNTIF(PEDIDOS!D:D,E8) -> 17 | H8: BEKIM | I8: =IFERROR(AVERAGEIFS(KPI!G:G,KPI!C:C,H8,KPI!G:G,">"&0,KPI!G:G,"<"&100),"") -> 14
A9: BIOESENCIA | B9: =COUNTIF(PEDIDOS!D:D,A9) -> 19 | C9: =IFERROR(AVERAGEIFS(KPI!G:G,KPI!C:C,A9,KPI!G:G,">"&0,KPI!G:G,"<"&100),"") -> 21.222222 | E9: LUCENT | F9: =COUNTIF(PEDIDOS!D:D,E9) -> 19 | H9: HEBURN | I9: =IFERROR(AVERAGEIFS(KPI!G:G,KPI!C:C,H9,KPI!G:G,">"&0,KPI!G:G,"<"&100),"") -> 14.5
A10: BL COSMETICS | B10: =COUNTIF(PEDIDOS!D:D,A10) -> 17 | C10: =IFERROR(AVERAGEIFS(KPI!G:G,KPI!C:C,A10,KPI!G:G,">"&0,KPI!G:G,"<"&100),"") -> 32.428571 | E10: MERMER | F10: =COUNTIF(PEDIDOS!D:D,E10) -> 8 | H10: THE GLOW FACTOR | I10: =IFERROR(AVERAGEIFS(KPI!G:G,KPI!C:C,H10,KPI!G:G,">"&0,KPI!G:G,"<"&100),"") -> 18
A11: BLE LIPS | B11: =COUNTIF(PEDIDOS!D:D,A11) -> 2 | C11: =IFERROR(AVERAGEIFS(KPI!G:G,KPI!C:C,A11,KPI!G:G,">"&0,KPI!G:G,"<"&100),"") -> 32 | E11: LABORATORIO ONCE | F11: =COUNTIF(PEDIDOS!D:D,E11) -> 8 | H11: ECODERM - AGUAZU | I11: =IFERROR(AVERAGEIFS(KPI!G:G,KPI!C:C,H11,KPI!G:G,">"&0,KPI!G:G,"<"&100),"") -> 16
A12: BOTIK | B12: =COUNTIF(PEDIDOS!D:D,A12) -> 3 | C12: =IFERROR(AVERAGEIFS(KPI!G:G,KPI!C:C,A12,KPI!G:G,">"&0,KPI!G:G,"<"&100),"")
A13: CAV | B13: =COUNTIF(PEDIDOS!D:D,A13) -> 43 | C13: =IFERROR(AVERAGEIFS(KPI!G:G,KPI!C:C,A13,KPI!G:G,">"&0,KPI!G:G,"<"&100),"") -> 20.575758
A14: COSMECEUTICALS | B14: =COUNTIF(PEDIDOS!D:D,A14) -> 6 | C14: =IFERROR(AVERAGEIFS(KPI!G:G,KPI!C:C,A14,KPI!G:G,">"&0,KPI!G:G,"<"&100),"") -> 19.833333
A15: DEL ARCA BOTANICA | B15: =COUNTIF(PEDIDOS!D:D,A15) -> 1 | C15: =IFERROR(AVERAGEIFS(KPI!G:G,KPI!C:C,A15,KPI!G:G,">"&0,KPI!G:G,"<"&100),"") -> 55
A16: DERMION / FRANCO | B16: =COUNTIF(PEDIDOS!D:D,A16) -> 3 | C16: =IFERROR(AVERAGEIFS(KPI!G:G,KPI!C:C,A16,KPI!G:G,">"&0,KPI!G:G,"<"&100),"") -> 8.6666667
A17: DWUAM | B17: =COUNTIF(PEDIDOS!D:D,A17) -> 1 | C17: =IFERROR(AVERAGEIFS(KPI!G:G,KPI!C:C,A17,KPI!G:G,">"&0,KPI!G:G,"<"&100),"") -> 7
A18: ECODERM - AGUAZU | B18: =COUNTIF(PEDIDOS!D:D,A18) -> 5 | C18: =IFERROR(AVERAGEIFS(KPI!G:G,KPI!C:C,A18,KPI!G:G,">"&0,KPI!G:G,"<"&100),"") -> 16
A19: ECODERM - DUGA | B19: =COUNTIF(PEDIDOS!D:D,A19) -> 3 | C19: =IFERROR(AVERAGEIFS(KPI!G:G,KPI!C:C,A19,KPI!G:G,">"&0,KPI!G:G,"<"&100),"") -> 18
A20: ECODERM - ROSEHIP | B20: =COUNTIF(PEDIDOS!D:D,A20) -> 4 | C20: =IFERROR(AVERAGEIFS(KPI!G:G,KPI!C:C,A20,KPI!G:G,">"&0,KPI!G:G,"<"&100),"") -> 21
A21: ECOS DE HUEMUL | B21: =COUNTIF(PEDIDOS!D:D,A21) -> 4 | C21: =IFERROR(AVERAGEIFS(KPI!G:G,KPI!C:C,A21,KPI!G:G,">"&0,KPI!G:G,"<"&100),"")
A22: HEBURN | B22: =COUNTIF(PEDIDOS!D:D,A22) -> 2 | C22: =IFERROR(AVERAGEIFS(KPI!G:G,KPI!C:C,A22,KPI!G:G,">"&0,KPI!G:G,"<"&100),"") -> 14.5
A23: ICONO | B23: =COUNTIF(PEDIDOS!D:D,A23) -> 8 | C23: =IFERROR(AVERAGEIFS(KPI!G:G,KPI!C:C,A23,KPI!G:G,">"&0,KPI!G:G,"<"&100),"") -> 23.285714
... A49: ASHA | B49: =COUNTIF(PEDIDOS!D:D,A49) -> 1 | C49: =IFERROR(AVERAGEIFS(KPI!G:G,KPI!C:C,A49,KPI!G:G,">"&0,KPI!G:G,"<"&100),"")
